Workbook
Name Nom_Société: 'Desgagné TRIM 2'!$B$2
Name Nom_Société: 'Desgagné 1'!$B$2
Name OLE_LINK4: Données!#REF!
Name TitreColonne1: [1]!Facture[[#Headers],[Quantité]]
Name TitreColonne1: [2]!Facture[[#Headers],[Quantité]]
Name TitreColonne1: [2]!Facture[[#Headers],[Quantité]]
Name TitreColonne1: [3]!Facture[[#Headers],[Quantité]]
Name TitreColonne1: [1]!Facture[[#Headers],[Quantité]]
Name TitreColonne1: [2]!Facture[[#Headers],[Quantité]]
Name TitreColonne1: [3]!Facture[[#Headers],[Quantité]]
Name TitreColonne1: [2]!Facture[[#Headers],[Quantité]]
Name TitreColonne1: [4]!Facture[[#Headers],[Quantité]]
Name ZoneTitreColonne1..E13.1: 'Desgagné TRIM 2'!$B$12
Name ZoneTitreColonne1..E13.1: 'Desgagné 1'!$B$12
Name ZoneTitreLigne1..E5: 'Desgagné TRIM 2'!$D$3
Name ZoneTitreLigne1..E5: 'Desgagné 1'!$D$3

Sheet Données
A1: ISSA OUEDRAOGO
B4: Produits | C4: Dimension unitaire | D4: La | E4: Lo | F4: Ha | G4: Dimension en mètre cube | H4: Coûts unitaires (+15% «express») | I4: Prix de vente unitaire | J4: Lots | K4: Demande max. | L4: Demande min. | M4: Projection de ventes trim 1 | N4: Projection Mois 1
B6: P1 | C6: 1x0,4x0,45 m | D6: 1 | E6: 0.4 | F6: 0.45 | G6: =D6*E6*F6 -> 0.18 | H6: 6.75 | I6: 10.87 | J6: 50 | K6: 5390 | L6: 5080 | M6: =AVERAGE(K6:L6) -> 5235 | N6: =M6*Données!$F$26 -> 1555.7207
B7: P2 | C7: 0,5x0,5x0,9 m | D7: 0.5 | E7: 0.5 | F7: 0.9 | G7: =D7*E7*F7 -> 0.225 | H7: 13.5 | I7: 21.74 | J7: 100 | K7: 6290 | L7: 5980 | M7: =AVERAGE(K7:L7) -> 6135 | N7: =M7*Données!$F$26 -> 1823.1798
A8: Trim 1 et trim 4 | B8: P3 | C8: 0,9x0,5x1½ m | D8: 0.9 | E8: 0.5 | F8: 1.5 | G8: =D8*E8*F8 -> 0.675 | H8: 20 | I8: 35.02 | J8: 100 | K8: 3880 | L8: 3370 | M8: =AVERAGE(K8:L8) -> 3625 | N8: =M8*Données!$F$26 -> 1077.266 | AI8: =$AD8*(1+AI$5) -> 0 | AJ8: =$AD8*1+(AJ$5) -> 0 | AK8: =$AD8*1+(AK$5) -> 0 | AL8: =$AD8*1+(AL$5) -> 0 | AM8: =$AD8*1+(AM$5) -> 0 | AN8: =$AD8*1+(AN$5) -> 0 | AO8: =$AD8*1+(AO$5) -> 0 | AP8: =$AD8*1+(AP$5) -> 0 | AQ8: =$AD8*1+(AQ$5) -> 0 | ... AT8: =$AD8*1+(AT$5) -> 0 | AU8: =SUM(AI8:AT8) -> 0
B9: P4 | C9: 1x0,5x1 m | D9: 1 | E9: 0.5 | F9: 1 | G9: =D9*E9*F9 -> 0.5 | H9: 29 | I9: 42.26 | J9: 100 | K9: 2960 | L9: 2760 | M9: =AVERAGE(K9:L9) -> 2860 | N9: =M9*Données!$F$26 -> 849.92571 | AI9: =$N9*(1+AI$5) -> 849.92571 | AJ9: =$N9*(1+AJ$5) -> 849.92571 | AK9: =$N9*(1+AK$5) -> 849.92571 | AL9: =$N9*(1+AL$5) -> 849.92571 | AM9: =$N9*(1+AM$5) -> 849.92571 | AN9: =$N9*(1+AN$5) -> 849.92571 | AO9: =$N9*(1+AO$5) -> 849.92571 | AP9: =$N9*(1+AP$5) -> 849.92571 | ... AT9: =$N9*(1+AT$5) -> 849.92571 | AU9: =SUM(AI9:AT9) -> 10199.108
B10: P5 | C10: 0,5x1x1½ m | D10: 0.5 | E10: 1 | F10: 1.5 | G10: =D10*E10*F10 -> 0.75 | H10: 35 | I10: 59.17 | J10: 50 | K10: 4800 | L10: 4700 | M10: =AVERAGE(K10:L10) -> 4750 | N10: =M10*Données!$F$26 -> 1411.5899 | AU10: =SUM(AI10:AT10) -> 0
A11: Trim 1 et trim 4 | B11: P6 | C11: 0,5x1x1,8 m | D11: 0.5 | E11: 1 | F11: 1.8 | G11: =D11*E11*F11 -> 0.9 | H11: 42 | I11: 64 | J11: 100 | K11: 1690 | L11: 1590 | M11: =AVERAGE(K11:L11) -> 1640 | N11: =M11*Données!$F$26 -> 487.36999 | AI11: =$N11*(1+AI$5) -> 487.36999 | AJ11: =$N11*(1+AJ$5) -> 487.36999 | AK11: =$N11*(1+AK$5) -> 487.36999 | AL11: =$N11*(1+AL$5) -> 487.36999 | AM11: =$N11*(1+AM$5) -> 487.36999 | AN11: =$N11*(1+AN$5) -> 487.36999 | AO11: =$N11*(1+AO$5) -> 487.36999 | AP11: =$N11*(1+AP$5) -> 487.36999 | ... AT11: =$N11*(1+AT$5) -> 487.36999 | AU11: =SUM(AI11:AT11) -> 5848.4398
B12: P7 | C12: 0,5x1x1¾ m | D12: 0.5 | E12: 1 | F12: 1.75 | G12: =D12*E12*F12 -> 0.875 | H12: 54 | I12: 82.11 | J12: 50 | K12: 2480 | L12: 2430 | M12: =AVERAGE(K12:L12) -> 2455 | N12: =M12*Données!$F$26 -> 729.56909 | AI12: =$N12*(1+AI$5) -> 729.56909 | AJ12: =$N12*(1+AJ$5) -> 729.56909 | AK12: =$N12*(1+AK$5) -> 729.56909 | AL12: =$N12*(1+AL$5) -> 729.56909 | AM12: =$N12*(1+AM$5) -> 729.56909 | AN12: =$N12*(1+AN$5) -> 729.56909 | AO12: =$N12*(1+AO$5) -> 729.56909 | AP12: =$N12*(1+AP$5) -> 729.56909 | ... AT12: =$N12*(1+AT$5) -> 729.56909 | AU12: =SUM(AI12:AT12) -> 8754.8291
B13: P8 | C13: 1,8x1x1 m | D13: 1.8 | E13: 1 | F13: 1 | G13: =D13*E13*F13 -> 1.8 | H13: 59 | I13: 85.73 | J13: 10 | K13: 7530 | L13: 7490 | M13: =AVERAGE(K13:L13) -> 7510 | N13: =M13*Données!$F$26 -> 2231.7979 | AU13: =SUM(AI13:AT13) -> 0
A14: Trim 1 et trim 4 | B14: P9 | C14: 0,9x0,5x1¼ m | D14: 0.9 | E14: 0.5 | F14: 1.25 | G14: =D14*E14*F14 -> 0.5625 | H14: 66 | I14: 108.68 | J14: 10 | K14: 4290 | L14: 4260 | M14: =AVERAGE(K14:L14) -> 4275 | N14: =M14*Données!$F$26 -> 1270.4309 | AI14: =$N14*(1+AI$5) -> 1270.4309 | AJ14: =$N14*(1+AJ$5) -> 1270.4309 | AK14: =$N14*(1+AK$5) -> 1270.4309 | AL14: =$N14*(1+AL$5) -> 1270.4309 | AM14: =$N14*(1+AM$5) -> 1270.4309 | AN14: =$N14*(1+AN$5) -> 1270.4309 | AO14: =$N14*(1+AO$5) -> 1270.4309 | AP14: =$N14*(1+AP$5) -> 1270.4309 | ... AT14: =$N14*(1+AT$5) -> 1270.4309 | AU14: =SUM(AI14:AT14) -> 15245.171
B15: P10 | C15: 1x0,5x1½ m | D15: 1 | E15: 0.5 | F15: 1.5 | G15: =D15*E15*F15 -> 0.75 | H15: 69 | I15: 107.47 | J15: 10 | K15: 1130 | L15: 1120 | M15: =AVERAGE(K15:L15) -> 1125 | N15: =M15*Données!$F$26 -> 334.32392 | AI15: =$N15*(1+AI$5) -> 334.32392 | AJ15: =$N15*(1+AJ$5) -> 334.32392 | AK15: =$N15*(1+AK$5) -> 334.32392 | AL15: =$N15*(1+AL$5) -> 334.32392 | AM15: =$N15*(1+AM$5) -> 334.32392 | AN15: =$N15*(1+AN$5) -> 334.32392 | AO15: =$N15*(1+AO$5) -> 334.32392 | AP15: =$N15*(1+AP$5) -> 334.32392 | ... AT15: =$N15*(1+AT$5) -> 334.32392 | AU15: =SUM(AI15:AT15) -> 4011.8871
A16: Trim 1 et trim 4 | B16: P11 | C16: 0,5x0,9x1½ m | D16: 0.5 | E16: 0.9 | F16: 1.5 | G16: =D16*E16*F16 -> 0.675 | H16: 22 | I16: 36.23 | J16: 100 | K16: 920 | L16: 820 | M16: =AVERAGE(K16:L16) -> 870 | N16: =M16*Données!$F$26 -> 258.54383 | AU16: =SUM(AI16:AT16) -> 0
A17: Trim 2 et trim 4 | B17: P12 | C17: 1x1¾x1 m | D17: 1 | E17: 1.75 | F17: 1 | G17: =D17*E17*F17 -> 1.75 | H17: 43 | I17: 63.4 | J17: 10 | K17: 2660 | L17: 2530 | M17: =AVERAGE(K17:L17) -> 2595 | N17: =M17*Données!$F$26 -> 771.17385 | AI17: =$N17*(1+AI$5) -> 771.17385 | AJ17: =$N17*(1+AJ$5) -> 771.17385 | AK17: =$N17*(1+AK$5) -> 771.17385 | AL17: =$N17*(1+AL$5) -> 771.17385 | AM17: =$N17*(1+AM$5) -> 771.17385 | AN17: =$N17*(1+AN$5) -> 771.17385 | AO17: =$N17*(1+AO$5) -> 771.17385 | AP17: =$N17*(1+AP$5) -> 771.17385 | ... AT17: =$N17*(1+AT$5) -> 771.17385 | AU17: =SUM(AI17:AT17) -> 9254.0862
A18: Trim 2 et trim 4 | B18: P13 | C18: 1x1x1¼ m | D18: 1 | E18: 1 | F18: 1.25 | G18: =D18*E18*F18 -> 1.25 | H18: 65 | I18: 99.62 | J18: 10 | K18: 1080 | L18: 1020 | M18: =AVERAGE(K18:L18) -> 1050 | N18: =M18*Données!$F$26 -> 312.03566 | AU18: =SUM(AI18:AT18) -> 0
AU19: =SUM(AI19:AT19) -> 0
AU20: =SUM(AI20:AT20) -> 0
D21: 0.1 | E21: 0.15 | AE21: =SUM(AE8:AE20) -> 0 | AI21: =SUM(AI8:AI20) -> 4442.7935 | AJ21: =SUM(AJ8:AJ20) -> 4442.7935 | AK21: =SUM(AK8:AK20) -> 4442.7935 | AL21: =SUM(AL8:AL20) -> 4442.7935 | AM21: =SUM(AM8:AM20) -> 4442.7935 | AN21: =SUM(AN8:AN20) -> 4442.7935 | AO21: =SUM(AO8:AO20) -> 4442.7935 | AP21: =SUM(AP8:AP20) -> 4442.7935 | ... AU21: =SUM(AU8:AU20) -> 53313.522
C22: Mois 1 | D22: Mois 2 | E22: Mois 3 | F22: trimestre
B23: Valeur | C23: 1 | D23: =C23*(1+D21) -> 1.1 | E23: =(1+E21)*D23 -> 1.265 | F23: =SUM(C23:E23) -> 3.365 | G23: =1 + 1.2 + 1.44 -> 3.64
C24: =C8*$A24 -> #VALUE! | O24: =SUM(C24:N24) -> #VALUE! | S24: =$Q24*S8 -> 0 | AE24: =SUM(S24:AD24) -> 0 | AI24: =AI8*$AG24 -> 0 | AJ24: =AJ8*$AG24 -> 0 | AK24: =AK8*$AG24 -> 0 | AL24: =AL8*$AG24 -> 0 | AM24: =AM8*$AG24 -> 0 | AN24: =AN8*$AG24 -> 0 | AO24: =AO8*$AG24 -> 0 | AP24: =AP8*$AG24 -> 0 | ... AT24: =AT8*$AG24 -> 0 | AU24: =SUM(AI24:AT24) -> 0
B25: Donc, le rapport entre le mois 1 et le trimestre est de : 1 / 3,64, soit 27,5%. | S25: =$Q25*S9 -> 0 | AE25: =SUM(S25:AD25) -> 0 | AI25: =AI9*$AG25 -> 0 | AJ25: =AJ9*$AG25 -> 0 | AK25: =AK9*$AG25 -> 0 | AL25: =AL9*$AG25 -> 0 | AM25: =AM9*$AG25 -> 0 | AN25: =AN9*$AG25 -> 0 | AO25: =AO9*$AG25 -> 0 | AP25: =AP9*$AG25 -> 0 | ... AT25: =AT9*$AG25 -> 0 | AU25: =SUM(AI25:AT25) -> 0
F26: =1/F23 -> 0.29717682 | AE26: =SUM(S26:AD26) -> 0 | AI26: =AI10*$AG26 -> 0 | AJ26: =AJ10*$AG26 -> 0 | AK26: =AK10*$AG26 -> 0 | AL26: =AL10*$AG26 -> 0 | AM26: =AM10*$AG26 -> 0 | AN26: =AN10*$AG26 -> 0 | AO26: =AO10*$AG26 -> 0 | AP26: =AP10*$AG26 -> 0 | ... AT26: =AT10*$AG26 -> 0 | AU26: =SUM(AI26:AT26) -> 0
AE27: =SUM(S27:AD27) -> 0 | AI27: =AI11*$AG27 -> 0 | AJ27: =AJ11*$AG27 -> 0 | AK27: =AK11*$AG27 -> 0 | AL27: =AL11*$AG27 -> 0 | AM27: =AM11*$AG27 -> 0 | AN27: =AN11*$AG27 -> 0 | AO27: =AO11*$AG27 -> 0 | AP27: =AP11*$AG27 -> 0 | ... AT27: =AT11*$AG27 -> 0 | AU27: =SUM(AI27:AT27) -> 0
AE28: =SUM(S28:AD28) -> 0 | AI28: =AI12*$AG28 -> 0 | AJ28: =AJ12*$AG28 -> 0 | AK28: =AK12*$AG28 -> 0 | AL28: =AL12*$AG28 -> 0 | AM28: =AM12*$AG28 -> 0 | AN28: =AN12*$AG28 -> 0 | AO28: =AO12*$AG28 -> 0 | AP28: =AP12*$AG28 -> 0 | ... AT28: =AT12*$AG28 -> 0 | AU28: =SUM(AI28:AT28) -> 0
AE29: =SUM(S29:AD29) -> 0 | AI29: =AI13*$AG29 -> 0 | AJ29: =AJ13*$AG29 -> 0 | AK29: =AK13*$AG29 -> 0 | AL29: =AL13*$AG29 -> 0 | AM29: =AM13*$AG29 -> 0 | AN29: =AN13*$AG29 -> 0 | AO29: =AO13*$AG29 -> 0 | AP29: =AP13*$AG29 -> 0 | ... AT29: =AT13*$AG29 -> 0 | AU29: =SUM(AI29:AT29) -> 0
AE30: =SUM(S30:AD30) -> 0 | AI30: =AI14*$AG30 -> 0 | AJ30: =AJ14*$AG30 -> 0 | AK30: =AK14*$AG30 -> 0 | AL30: =AL14*$AG30 -> 0 | AM30: =AM14*$AG30 -> 0 | AN30: =AN14*$AG30 -> 0 | AO30: =AO14*$AG30 -> 0 | AP30: =AP14*$AG30 -> 0 | ... AT30: =AT14*$AG30 -> 0 | AU30: =SUM(AI30:AT30) -> 0
AE31: =SUM(S31:AD31) -> 0 | AI31: =AI15*$AG31 -> 0 | AJ31: =AJ15*$AG31 -> 0 | AK31: =AK15*$AG31 -> 0 | AL31: =AL15*$AG31 -> 0 | AM31: =AM15*$AG31 -> 0 | AN31: =AN15*$AG31 -> 0 | AO31: =AO15*$AG31 -> 0 | AP31: =AP15*$AG31 -> 0 | ... AT31: =AT15*$AG31 -> 0 | AU31: =SUM(AI31:AT31) -> 0
AE32: =SUM(S32:AD32) -> 0 | AI32: =AI16*$AG32 -> 0 | AJ32: =AJ16*$AG32 -> 0 | AK32: =AK16*$AG32 -> 0 | AL32: =AL16*$AG32 -> 0 | AM32: =AM16*$AG32 -> 0 | AN32: =AN16*$AG32 -> 0 | AO32: =AO16*$AG32 -> 0 | AP32: =AP16*$AG32 -> 0 | ... AT32: =AT16*$AG32 -> 0 | AU32: =SUM(AI32:AT32) -> 0
S33: =$Q33*S17 -> 0 | AE33: =SUM(S33:AD33) -> 0 | AI33: =AI17*$AG33 -> 0 | AJ33: =AJ17*$AG33 -> 0 | AK33: =AK17*$AG33 -> 0 | AL33: =AL17*$AG33 -> 0 | AM33: =AM17*$AG33 -> 0 | AN33: =AN17*$AG33 -> 0 | AO33: =AO17*$AG33 -> 0 | AP33: =AP17*$AG33 -> 0 | ... AT33: =AT17*$AG33 -> 0 | AU33: =SUM(AI33:AT33) -> 0
S34: =$Q34*S18 -> 0 | AE34: =SUM(S34:AD34) -> 0 | AI34: =AI18*$AG34 -> 0 | AJ34: =AJ18*$AG34 -> 0 | AK34: =AK18*$AG34 -> 0 | AL34: =AL18*$AG34 -> 0 | AM34: =AM18*$AG34 -> 0 | AN34: =AN18*$AG34 -> 0 | AO34: =AO18*$AG34 -> 0 | AP34: =AP18*$AG34 -> 0 | ... AT34: =AT18*$AG34 -> 0 | AU34: =SUM(AI34:AT34) -> 0
AE35: =SUM(S35:AD35) -> 0 | AI35: =AI19*$AG35 -> 0 | AJ35: =AJ19*$AG35 -> 0 | AK35: =AK19*$AG35 -> 0 | AL35: =AL19*$AG35 -> 0 | AM35: =AM19*$AG35 -> 0 | AN35: =AN19*$AG35 -> 0 | AO35: =AO19*$AG35 -> 0 | AP35: =AP19*$AG35 -> 0 | ... AT35: =AT19*$AG35 -> 0 | AU35: =SUM(AI35:AT35) -> 0
AE36: =SUM(S36:AD36) -> 0 | AI36: =AI20*$AG36 -> 0 | AJ36: =AJ20*$AG36 -> 0 | AK36: =AK20*$AG36 -> 0 | AL36: =AL20*$AG36 -> 0 | AM36: =AM20*$AG36 -> 0 | AN36: =AN20*$AG36 -> 0 | AO36: =AO20*$AG36 -> 0 | AP36: =AP20*$AG36 -> 0 | ... AT36: =AT20*$AG36 -> 0 | AU36: =SUM(AI36:AT36) -> 0
S37: =SUM(S24:S36) -> 0 | T37: =SUM(T24:T36) -> 0 | U37: =SUM(U24:U36) -> 0 | V37: =SUM(V24:V36) -> 0 | W37: =SUM(W24:W36) -> 0 | X37: =SUM(X24:X36) -> 0 | Y37: =SUM(Y24:Y36) -> 0 | Z37: =SUM(Z24:Z36) -> 0 | ... AE37: =SUM(AE24:AE36) -> 0 | AI37: =SUM(AI24:AI36) -> 0 | AJ37: =SUM(AJ24:AJ36) -> 0 | AK37: =SUM(AK24:AK36) -> 0 | AL37: =SUM(AL24:AL36) -> 0 | AM37: =SUM(AM24:AM36) -> 0 | AN37: =SUM(AN24:AN36) -> 0 | AO37: =SUM(AO24:AO36) -> 0 | AP37: =SUM(AP24:AP36) -> 0 | ... AU37: =SUM(AU24:AU36) -> 0
B40: Année 1 | C40: Année 2 | D40: Année 3
A41: Trimestre 1 | B41: =SUM(C21+D21+E21) -> 0.25 | C41: =SUM(S21:U21) -> 0 | D41: =SUM(AI21:AK21) -> 13328.38
A42: Trimestre 2 | B42: =SUM(E21+F21+G21) -> 0.15 | C42: =SUM(V21:X21) -> 0 | D42: =SUM(AL21:AN21) -> 13328.38
A43: Trimestre 3 | B43: =SUM(I21+J21+K21) -> 0 | C43: =SUM(Y21:AA21) -> 0 | D43: =SUM(AO21:AQ21) -> 13328.38
A44: Trimestre 4 | B44: =SUM(L21:N21) -> 0 | C44: =SUM(AB21:AD21) -> 0 | D44: =SUM(AR21:AT21) -> 13328.38

Sheet S1 - projections
A1: ISSA OUEDRAOGO
A3: Prévision ventes année 1 : | Q3: Prévision ventes année 2 : | AG3: Prévision ventes année 3 :
C4: TRIM 1 | F4: TRIM 2 | I4: TRIM 3 | L4: TRIM 4 | S4: TRIM 1 | V4: TRIM 2 | Y4: TRIM 3 | AB4: TRIM 4 | AI4: TRIM 1 | AL4: TRIM 2 | AO4: TRIM 3 | AR4: TRIM 4
B5: Augmentations : | D5: 0.1 | E5: 0.15 | F5: 0.15 | G5: 0.15 | H5: 0.1 | I5: 0.1 | J5: 0.05 | K5: 0.05 | L5: 0.05 | M5: 0 | N5: 0 | R5: Augmentations : | S5: 0 | T5: 0 | U5: 0 | V5: 0 | W5: 0 | X5: 0 | Y5: 0 | Z5: 0 | AA5: 0 | AB5: 0 | AC5: 0 | AD5: 0 | AH5: Augmentations : | AI5: 0 | AJ5: 0 | AK5: 0 | AL5: 0 | AM5: 0 | AN5: 0 | AO5: 0 | AP5: 0 | AQ5: 0 | AR5: 0 | AS5: 0 | AT5: 0
C6: Mois 1 | D6: Mois 2 | E6: Mois 3 | F6: Mois 4 | G6: Mois 5 | H6: Mois 6 | I6: Mois 7 | J6: Mois 8 | K6: Mois 9 | L6: Mois 10 | M6: Mois 11 | N6: Mois 12 | O6: Année 1 | S6: Mois 1 | T6: Mois 2 | U6: Mois 3 | V6: Mois 4 | W6: Mois 5 | X6: Mois 6 | Y6: Mois 7 | Z6: Mois 8 | AA6: Mois 9 | AB6: Mois 10 | AC6: Mois 11 | AD6: Mois 12 | AE6: Année 2 | AI6: Mois 1 | AJ6: Mois 2 | AK6: Mois 3 | AL6: Mois 4 | AM6: Mois 5 | AN6: Mois 6 | AO6: Mois 7 | AP6: Mois 8 | AQ6: Mois 9 | AR6: Mois 10 | AS6: Mois 11 | AT6: Mois 12 | AU6: Année 3
A7: Quantité : | B7: Produits | Q7: Quantité : | R7: Produits | AG7: Quantité : | AH7: Produits
B8: P1 | C8: =Données!N6 -> 1555.7207 | D8: =C8*(1+D$5) -> 1711.2927 | E8: =D8*(1+E$5) -> 1967.9866 | F8: =E8*(1+F$5) -> 2263.1846 | G8: =F8*(1+G$5) -> 2602.6623 | H8: =G8*(1+H$5) -> 2862.9285 | I8: =H8*(1+I$5) -> 3149.2214 | J8: =I8*(1+J$5) -> 3306.6825 | K8: =J8*(1+K$5) -> 3472.0166 | ... N8: =M8*(1+N$5) -> 3645.6174 | O8: =SUM(C8:N8) -> 33828.548 | R8: P1 | S8: =$N8*(1+$T5) -> 3645.6174 | T8: =$N8*(1+$T5) -> 3645.6174 | U8: =$N8*(1+$T5) -> 3645.6174 | V8: =$N8*(1+$T5) -> 3645.6174 | W8: =$N8*(1+$T5) -> 3645.6174 | X8: =$N8*(1+$T5) -> 3645.6174 | Y8: =$N8*(1+$T5) -> 3645.6174 | Z8: =$N8*(1+$T5) -> 3645.6174 | ... AD8: =$N8*(1+$T5) -> 3645.6174 | AE8: =SUM(S8:AD8) -> 43747.409 | AH8: P1 | AI8: =$AD8*(1+AI$5) -> 3645.6174 | AJ8: =$AD8*1+(AJ$5) -> 3645.6174 | AK8: =$AD8*1+(AK$5) -> 3645.6174 | AL8: =$AD8*1+(AL$5) -> 3645.6174 | AM8: =$AD8*1+(AM$5) -> 3645.6174 | AN8: =$AD8*1+(AN$5) -> 3645.6174 | AO8: =$AD8*1+(AO$5) -> 3645.6174 | AP8: =$AD8*1+(AP$5) -> 3645.6174 | AQ8: =$AD8*1+(AQ$5) -> 3645.6174 | ... AT8: =$AD8*1+(AT$5) -> 3645.6174 | AU8: =SUM(AI8:AT8) -> 43747.409
B9: P2 | C9: =Données!N7 -> 1823.1798 | D9: =C9*(1+D$5) -> 2005.4978 | E9: =D9*(1+E$5) -> 2306.3224 | F9: =E9*(1+F$5) -> 2652.2708 | G9: =F9*(1+G$5) -> 3050.1114 | H9: =G9*(1+H$5) -> 3355.1226 | I9: =H9*(1+I$5) -> 3690.6348 | J9: =I9*(1+J$5) -> 3875.1666 | K9: =J9*(1+K$5) -> 4068.9249 | ... N9: =M9*(1+N$5) -> 4272.3711 | O9: =SUM(C9:N9) -> 39644.344 | R9: P2 | S9: =$N9*(1+T$5) -> 4272.3711 | T9: =$N9*(1+U$5) -> 4272.3711 | U9: =$N9*(1+V$5) -> 4272.3711 | V9: =$N9*(1+W$5) -> 4272.3711 | W9: =$N9*(1+X$5) -> 4272.3711 | X9: =$N9*(1+Y$5) -> 4272.3711 | Y9: =$N9*(1+Z$5) -> 4272.3711 | Z9: =$N9*(1+AA$5) -> 4272.3711 | ... AD9: =$N9*(1+AE$5) -> 4272.3711 | AE9: =SUM(S9:AD9) -> 51268.454 | AH9: P2 | AI9: =$N9*(1+AI$5) -> 4272.3711 | AJ9: =$N9*(1+AJ$5) -> 4272.3711 | AK9: =$N9*(1+AK$5) -> 4272.3711 | AL9: =$N9*(1+AL$5) -> 4272.3711 | AM9: =$N9*(1+AM$5) -> 4272.3711 | AN9: =$N9*(1+AN$5) -> 4272.3711 | AO9: =$N9*(1+AO$5) -> 4272.3711 | AP9: =$N9*(1+AP$5) -> 4272.3711 | ... AT9: =$N9*(1+AT$5) -> 4272.3711 | AU9: =SUM(AI9:AT9) -> 51268.454
A10: (Trim 1 et 4 seulement) | B10: P3 | C10: =Données!N8 -> 1077.266 | D10: =C10*(1+D$5) -> 1184.9926 | E10: =D10*(1+E$5) -> 1362.7415 | L10: =E10*(1+F$5) -> 1567.1527 | M10: =L10*(1+G$5) -> 1802.2256 | N10: =M10*(1+H$5) -> 1982.4481 | O10: =SUM(C10:N10) -> 8976.8264 | R10: P3 | S10: =1077.26597325409*1+(I$5) -> 1077.366 | T10: =1184.99257057949*1+(J$5) -> 1185.0426 | U10: =1362.74145616642*1+(L$5) -> 1362.7915 | AB10: =2524.42467241654*1+(T$5) -> 2524.4247 | AC10: =2524.42467241654*1+(U$5) -> 2524.4247 | AD10: =2524.42467241654*1+(V$5) -> 2524.4247 | AE10: =SUM(S10:AD10) -> 11198.474 | AH10: P3 | AI10: =1077.26597325409*1+(W$5) -> 1077.266 | AJ10: =1077.26597325409*1+(X$5) -> 1077.266 | AK10: =1077.26597325409*1+(Y$5) -> 1077.266 | AR10: =2524.42467241654*1+(AC$5) -> 2524.4247 | AS10: =2524.42467241654*1+(AD$5) -> 2524.4247 | AT10: =2524.42467241654*1+(AE$5) -> 2524.4247 | AU10: =SUM(AI10:AT10) -> 10805.072
B11: P4 | C11: =Données!N9 -> 849.92571 | D11: =C11*(1+D$5) -> 934.91828 | E11: =D11*(1+E$5) -> 1075.156 | F11: =E11*(1+F$5) -> 1236.4294 | G11: =F11*(1+G$5) -> 1421.8938 | H11: =G11*(1+H$5) -> 1564.0832 | I11: =H11*(1+I$5) -> 1720.4915 | J11: =I11*(1+J$5) -> 1806.5161 | K11: =J11*(1+K$5) -> 1896.8419 | ... N11: =M11*(1+N$5) -> 1991.684 | O11: =SUM(C11:N11) -> 18481.308 | R11: P4 | S11: =$N11*(1+T$5) -> 1991.684 | T11: =$N11*(1+U$5) -> 1991.684 | U11: =$N11*(1+V$5) -> 1991.684 | V11: =$N11*(1+W$5) -> 1991.684 | W11: =$N11*(1+X$5) -> 1991.684 | X11: =$N11*(1+Y$5) -> 1991.684 | Y11: =$N11*(1+Z$5) -> 1991.684 | Z11: =$N11*(1+AA$5) -> 1991.684 | ... AD11: =$N11*(1+AE$5) -> 1991.684 | AE11: =SUM(S11:AD11) -> 23900.208 | AH11: P4 | AI11: =$N11*(1+AI$5) -> 1991.684 | AJ11: =$N11*(1+AJ$5) -> 1991.684 | AK11: =$N11*(1+AK$5) -> 1991.684 | AL11: =$N11*(1+AL$5) -> 1991.684 | AM11: =$N11*(1+AM$5) -> 1991.684 | AN11: =$N11*(1+AN$5) -> 1991.684 | AO11: =$N11*(1+AO$5) -> 1991.684 | AP11: =$N11*(1+AP$5) -> 1991.684 | ... AT11: =$N11*(1+AT$5) -> 1991.684 | AU11: =SUM(AI11:AT11) -> 23900.208
B12: P5 | C12: =Données!N10 -> 1411.5899 | D12: =C12*(1+D$5) -> 1552.7489 | E12: =D12*(1+E$5) -> 1785.6612 | F12: =E12*(1+F$5) -> 2053.5104 | G12: =F12*(1+G$5) -> 2361.537 | H12: =G12*(1+H$5) -> 2597.6907 | I12: =H12*(1+I$5) -> 2857.4597 | J12: =I12*(1+J$5) -> 3000.3327 | K12: =J12*(1+K$5) -> 3150.3493 | ... N12: =M12*(1+N$5) -> 3307.8668 | O12: =SUM(C12:N12) -> 30694.48 | R12: P5 | S12: =$N12*(1+T$5) -> 3307.8668 | T12: =$N12*(1+U$5) -> 3307.8668 | U12: =$N12*(1+V$5) -> 3307.8668 | V12: =$N12*(1+W$5) -> 3307.8668 | W12: =$N12*(1+X$5) -> 3307.8668 | X12: =$N12*(1+Y$5) -> 3307.8668 | Y12: =$N12*(1+Z$5) -> 3307.8668 | Z12: =$N12*(1+AA$5) -> 3307.8668 | ... AD12: =$N12*(1+AE$5) -> 3307.8668 | AE12: =SUM(S12:AD12) -> 39694.402 | AH12: P5 | AI12: =$N12*(1+AI$5) -> 3307.8668 | AJ12: =$N12*(1+AJ$5) -> 3307.8668 | AK12: =$N12*(1+AK$5) -> 3307.8668 | AL12: =$N12*(1+AL$5) -> 3307.8668 | AM12: =$N12*(1+AM$5) -> 3307.8668 | AN12: =$N12*(1+AN$5) -> 3307.8668 | AO12: =$N12*(1+AO$5) -> 3307.8668 | AP12: =$N12*(1+AP$5) -> 3307.8668 | ... AT12: =$N12*(1+AT$5) -> 3307.8668 | AU12: =SUM(AI12:AT12) -> 39694.402
A13: (Trim 1 et 4 seulement) | B13: P6 | C13: =Données!N11 -> 487.36999 | D13: =C13*(1+D$5) -> 536.10698 | E13: =D13*(1+E$5) -> 616.52303 | L13: =E13*(1+F$5) -> 709.00149 | M13: =L13*(1+G$5) -> 815.35171 | N13: =M13*(1+H$5) -> 896.88688 | O13: =SUM(C13:N13) -> 4061.2401 | R13: P6 | S13: =487.369985141159*1+(I$5) -> 487.46999 | T13: =536.106983655275*1+(J$5) -> 536.15698 | U13: =616.523031203566*1+(L$5) -> 616.57303 | AB13: =1142.08454145189*1+(T$5) -> 1142.0845 | AC13: =1142.08454145189*1+(U$5) -> 1142.0845 | AD13: =1142.08454145189*1+(V$5) -> 1142.0845 | AE13: =SUM(S13:AD13) -> 5066.4536 | AH13: P6 | AI13: =487.369985141159*1+(W$5) -> 487.36999 | AJ13: =487.369985141159*1+(X$5) -> 487.36999 | AK13: =487.369985141159*1+(Y$5) -> 487.36999 | AR13: =1142.08454145189*1+(AC$5) -> 1142.0845 | AS13: =1142.08454145189*1+(AD$5) -> 1142.0845 | AT13: =1142.08454145189*1+(AE$5) -> 1142.0845 | AU13: =SUM(AI13:AT13) -> 4888.3636
B14: P7 | C14: =Données!N12 -> 729.56909 | D14: =C14*(1+D$5) -> 802.526 | E14: =D14*(1+E$5) -> 922.9049 | F14: =E14*(1+F$5) -> 1061.3406 | G14: =F14*(1+G$5) -> 1220.5417 | H14: =G14*(1+H$5) -> 1342.5959 | I14: =H14*(1+I$5) -> 1476.8555 | J14: =I14*(1+J$5) -> 1550.6983 | K14: =J14*(1+K$5) -> 1628.2332 | ... N14: =M14*(1+N$5) -> 1709.6448 | O14: =SUM(C14:N14) -> 15864.2 | R14: P7 | S14: =$N14*(1+T$5) -> 1709.6448 | T14: =$N14*(1+U$5) -> 1709.6448 | U14: =$N14*(1+V$5) -> 1709.6448 | V14: =$N14*(1+W$5) -> 1709.6448 | W14: =$N14*(1+X$5) -> 1709.6448 | X14: =$N14*(1+Y$5) -> 1709.6448 | Y14: =$N14*(1+Z$5) -> 1709.6448 | Z14: =$N14*(1+AA$5) -> 1709.6448 | ... AD14: =$N14*(1+AE$5) -> 1709.6448 | AE14: =SUM(S14:AD14) -> 20515.738 | AH14: P7 | AI14: =$N14*(1+AI$5) -> 1709.6448 | AJ14: =$N14*(1+AJ$5) -> 1709.6448 | AK14: =$N14*(1+AK$5) -> 1709.6448 | AL14: =$N14*(1+AL$5) -> 1709.6448 | AM14: =$N14*(1+AM$5) -> 1709.6448 | AN14: =$N14*(1+AN$5) -> 1709.6448 | AO14: =$N14*(1+AO$5) -> 1709.6448 | AP14: =$N14*(1+AP$5) -> 1709.6448 | ... AT14: =$N14*(1+AT$5) -> 1709.6448 | AU14: =SUM(AI14:AT14) -> 20515.738
B15: P8 | C15: =Données!N13 -> 2231.7979 | D15: =C15*(1+D$5) -> 2454.9777 | E15: =D15*(1+E$5) -> 2823.2244 | F15: =E15*(1+F$5) -> 3246.708 | G15: =F15*(1+G$5) -> 3733.7142 | H15: =G15*(1+H$5) -> 4107.0857 | I15: =H15*(1+I$5) -> 4517.7942 | J15: =I15*(1+J$5) -> 4743.6839 | K15: =J15*(1+K$5) -> 4980.8681 | ... N15: =M15*(1+N$5) -> 5229.9115 | O15: =SUM(C15:N15) -> 48529.589 | R15: P8 | S15: =$N15*(1+T$5) -> 5229.9115 | T15: =$N15*(1+U$5) -> 5229.9115 | U15: =$N15*(1+V$5) -> 5229.9115 | V15: =$N15*(1+W$5) -> 5229.9115 | W15: =$N15*(1+X$5) -> 5229.9115 | X15: =$N15*(1+Y$5) -> 5229.9115 | Y15: =$N15*(1+Z$5) -> 5229.9115 | Z15: =$N15*(1+AA$5) -> 5229.9115 | ... AD15: =$N15*(1+AE$5) -> 5229.9115 | AE15: =SUM(S15:AD15) -> 62758.938 | AH15: P8 | AI15: =$N15*(1+AI$5) -> 5229.9115 | AJ15: =$N15*(1+AJ$5) -> 5229.9115 | AK15: =$N15*(1+AK$5) -> 5229.9115 | AL15: =$N15*(1+AL$5) -> 5229.9115 | AM15: =$N15*(1+AM$5) -> 5229.9115 | AN15: =$N15*(1+AN$5) -> 5229.9115 | AO15: =$N15*(1+AO$5) -> 5229.9115 | AP15: =$N15*(1+AP$5) -> 5229.9115 | ... AT15: =$N15*(1+AT$5) -> 5229.9115 | AU15: =SUM(AI15:AT15) -> 62758.938
A16: (Trim 1 et 4 seulement) | B16: P9 | C16: =Données!N14 -> 1270.4309 | D16: =C16*(1+D$5) -> 1397.474 | E16: =D16*(1+E$5) -> 1607.0951 | L16: =E16*(1+F$5) -> 1848.1594 | M16: =L16*(1+G$5) -> 2125.3833 | N16: =M16*(1+H$5) -> 2337.9216 | O16: =SUM(C16:N16) -> 10586.464 | R16: P9 | S16: =1270.4309063893*1+(I5) -> 1270.5309 | T16: =1397.47399702823*1+(J5) -> 1397.524 | U16: =1607.09509658247*1+(L5) -> 1607.1451 | AB16: =2977.08013091881*1+(T$5) -> 2977.0801 | AC16: =2977.08013091881*1+(U$5) -> 2977.0801 | AD16: =2977.08013091881*1+(V$5) -> 2977.0801 | AE16: =SUM(S16:AD16) -> 13206.44 | AH16: P9 | AI16: =1270.4309063893*1+(W$3) -> 1270.4309 | AJ16: =1270.4309063893*1+(X$3) -> 1270.4309 | AK16: =1270.4309063893*1+(Y$3) -> 1270.4309 | AR16: =2977.08013091881*1+(AC$5) -> 2977.0801 | AS16: =2977.08013091881*1+(AD$5) -> 2977.0801 | AT16: =2977.08013091881*1+(AE$5) -> 2977.0801 | AU16: =SUM(AI16:AT16) -> 12742.533
B17: P10 | C17: =Données!N15 -> 334.32392 | D17: =C17*(1+D$5) -> 367.75632 | E17: =D17*(1+E$5) -> 422.91976 | F17: =E17*(1+F$5) -> 486.35773 | G17: =F17*(1+G$5) -> 559.31139 | H17: =G17*(1+H$5) -> 615.24252 | I17: =H17*(1+I$5) -> 676.76678 | J17: =I17*(1+J$5) -> 710.60512 | K17: =J17*(1+K$5) -> 746.13537 | ... N17: =M17*(1+N$5) -> 783.44214 | O17: =SUM(C17:N17) -> 7269.7453 | R17: P10 | S17: =$N17*(1+T$5) -> 783.44214 | T17: =$N17*(1+U$5) -> 783.44214 | U17: =$N17*(1+V$5) -> 783.44214 | V17: =$N17*(1+W$5) -> 783.44214 | W17: =$N17*(1+X$5) -> 783.44214 | X17: =$N17*(1+Y$5) -> 783.44214 | Y17: =$N17*(1+Z$5) -> 783.44214 | Z17: =$N17*(1+AA$5) -> 783.44214 | ... AD17: =$N17*(1+AE$5) -> 783.44214 | AE17: =SUM(S17:AD17) -> 9401.3057 | AH17: P10 | AI17: =$N17*(1+AI$5) -> 783.44214 | AJ17: =$N17*(1+AJ$5) -> 783.44214 | AK17: =$N17*(1+AK$5) -> 783.44214 | AL17: =$N17*(1+AL$5) -> 783.44214 | AM17: =$N17*(1+AM$5) -> 783.44214 | AN17: =$N17*(1+AN$5) -> 783.44214 | AO17: =$N17*(1+AO$5) -> 783.44214 | AP17: =$N17*(1+AP$5) -> 783.44214 | ... AT17: =$N17*(1+AT$5) -> 783.44214 | AU17: =SUM(AI17:AT17) -> 9401.3057
A18: (Trim 2 et 4 seulement) | B18: P11 | F18: =Données!N16*(1+Données!F$26) -> 335.37707 | G18: =F18*(1+$D$5) -> 368.91477 | H18: =G18*(1+$E$5) -> 424.25199 | L18: =H18*(1+F$5) -> 487.88979 | M18: =L18*(1+$G$5) -> 561.07326 | N18: =M18*(1+$H$5) -> 617.18058 | O18: =SUM(C18:N18) -> 2794.6875 | R18: P11 | V18: =335.377067928969*1+($M5) -> 335.37707 | W18: =368.914774721866*1+(N$5) -> 368.91477 | X18: =424.251990930146*1+(S5) -> 424.25199 | AB18: =487.889789569668*1+(T$5) -> 487.88979 | AC18: =487.889789569668*1+(U$5) -> 487.88979 | AD18: =487.889789569668*1+(V$5) -> 487.88979 | AE18: =SUM(S18:AD18) -> 2592.2132 | AH18: P11 | AL18: =335.377067928969*1+(Z$5) -> 335.37707 | AM18: =335.377067928969*1+(AA$5) -> 335.37707 | AN18: =335.377067928969*1+(AB$5) -> 335.37707 | AR18: =487.889789569668*1+(AC$5) -> 487.88979 | AS18: =487.889789569668*1+(AD$5) -> 487.88979 | AT18: =487.889789569668*1+(AE$5) -> 487.88979 | AU18: =SUM(AI18:AT18) -> 2469.8006
A19: (Trim 2 et 4 seulement) | B19: P12 | F19: =Données!N17*(1+Données!F$26) -> 1000.3488 | G19: =F19*(1+$D$5) -> 1100.3837 | H19: =G19*(1+$E$5) -> 1265.4413 | L19: =H19*(1+F$5) -> 1455.2575 | M19: =L19*(1+$G$5) -> 1673.5461 | N19: =M19*(1+$H$5) -> 1840.9007 | O19: =SUM(C19:N19) -> 8335.8781 | R19: P12 | V19: =1000.34884054675*1+(M5) -> 1000.3488 | W19: =1100.38372460143*1+(N5) -> 1100.3837 | X19: =1265.44128329164*1+(S5) -> 1265.4413 | AB19: =1455.25747578539*1+(T$5) -> 1455.2575 | AC19: =1455.25747578539*1+(U$5) -> 1455.2575 | AD19: =1455.25747578539*1+(V$5) -> 1455.2575 | AE19: =SUM(S19:AD19) -> 7731.9463 | AH19: P12 | AL19: =1000.34884054675*1+(Z$5) -> 1000.3488 | AM19: =1000.34884054675*1+(AA$5) -> 1000.3488 | AN19: =1000.34884054675*1+(AB$5) -> 1000.3488 | AR19: =1455.25747578539*1+(AC$5) -> 1455.2575 | AS19: =1455.25747578539*1+(AD$5) -> 1455.2575 | AT19: =1455.25747578539*1+(AE$5) -> 1455.2575 | AU19: =SUM(AI19:AT19) -> 7366.8189
A20: (Trim 2 et 4 seulement) | B20: P13 | F20: =Données!N18*(1+Données!F$26) -> 404.76543 | G20: =F20*(1+$D$5) -> 445.24197 | H20: =G20*(1+$E$5) -> 512.02826 | L20: =H20*(1+F$5) -> 588.8325 | M20: =L20*(1+$G$5) -> 677.15738 | N20: =M20*(1+$H$5) -> 744.87312 | O20: =SUM(C20:N20) -> 3372.8987 | R20: P13 | V20: =404.765426810825*1+(M5) -> 404.76543 | W20: =445.241969491907*1+(N5) -> 445.24197 | X20: =512.028264915693*1+(S5) -> 512.02826 | AB20: =588.832504653047*1+(T$5) -> 588.8325 | AC20: =588.832504653047*1+(U$5) -> 588.8325 | AD20: =588.832504653047*1+(V$5) -> 588.8325 | AE20: =SUM(S20:AD20) -> 3128.5332 | AH20: P13 | AL20: =404.765426810825*1+(Z$5) -> 404.76543 | AM20: =404.765426810825*1+(AA$5) -> 404.76543 | AN20: =404.765426810825*1+(AB$5) -> 404.76543 | AR20: =588.832504653047*1+(AC$5) -> 588.8325 | AS20: =588.832504653047*1+(AD$5) -> 588.8325 | AT20: =588.832504653047*1+(AE$5) -> 588.8325 | AU20: =SUM(AI20:AT20) -> 2980.7938
B21: Total | C21: =SUM(C8:C20) -> 11771.174 | D21: =SUM(D8:D20) -> 12948.291 | E21: =SUM(E8:E20) -> 14890.535 | F21: =SUM(F8:F20) -> 14740.293 | G21: =SUM(G8:G20) -> 16864.312 | H21: =SUM(H8:H20) -> 18646.471 | I21: =SUM(I8:I20) -> 18089.224 | J21: =SUM(J8:J20) -> 18993.685 | ... O21: =SUM(O8:O20) -> 232440.21 | S21: =SUM(S8:S20) -> 23775.905 | T21: =SUM(T8:T20) -> 24059.261 | U21: =SUM(U8:U20) -> 24527.047 | V21: =SUM(V8:V20) -> 22681.029 | W21: =SUM(W8:W20) -> 22855.078 | X21: =SUM(X8:X20) -> 23142.259 | Y21: =SUM(Y8:Y20) -> 20940.538 | Z21: =SUM(Z8:Z20) -> 20940.538 | ... AE21: =SUM(AE8:AE20) -> 294210.52 | AI21: =SUM(AI8:AI20) -> 23775.605 | AJ21: =SUM(AJ8:AJ20) -> 23775.605 | AK21: =SUM(AK8:AK20) -> 23775.605 | AL21: =SUM(AL8:AL20) -> 22681.029 | AM21: =SUM(AM8:AM20) -> 22681.029 | AN21: =SUM(AN8:AN20) -> 22681.029 | AO21: =SUM(AO8:AO20) -> 20940.538 | AP21: =SUM(AP8:AP20) -> 20940.538 | ... AU21: =SUM(AU8:AU20) -> 292539.84
A23: Prix de vente unitaire | B23: Produits | C23: Mois 1 | D23: Mois 2 | E23: Mois 3 | F23: Mois 4 | G23: Mois 5 | H23: Mois 6 | I23: Mois 7 | J23: Mois 8 | K23: Mois 9 | L23: Mois 10 | M23: Mois 11 | N23: Mois 12 | O23: Année 1 | Q23: Prix de vente unitaire | R23: Produits | S23: Mois 1 | T23: Mois 2 | U23: Mois 3 | V23: Mois 4 | W23: Mois 5 | X23: Mois 6 | Y23: Mois 7 | Z23: Mois 8 | AA23: Mois 9 | AB23: Mois 10 | AC23: Mois 11 | AD23: Mois 12 | AE23: Année 2 | AG23: Prix de vente unitaire | AH23: Produits | AI23: Mois 1 | AJ23: Mois 2 | AK23: Mois 3 | AL23: Mois 4 | AM23: Mois 5 | AN23: Mois 6 | AO23: Mois 7 | AP23: Mois 8 | AQ23: Mois 9 | AR23: Mois 10 | AS23: Mois 11 | AT23: Mois 12 | AU23: Année 3
A24: {=Données!$I$6:$I$18} -> 10.87 | B24: P1 | C24: =C8*$A24 -> 16910.684 | D24: =D8*$A24 -> 18601.752 | E24: =E8*$A24 -> 21392.015 | F24: =F8*$A24 -> 24600.817 | G24: =G8*$A24 -> 28290.939 | H24: =H8*$A24 -> 31120.033 | I24: =I8*$A24 -> 34232.037 | J24: =J8*$A24 -> 35943.638 | ... N24: =N8*$A24 -> 39627.861 | O24: =SUM(C24:N24) -> 367716.32 | Q24: =A24 -> 10.87 | R24: P1 | S24: =$Q24*S8 -> 39627.861 | T24: =$Q24*T8 -> 39627.861 | U24: =$Q24*U8 -> 39627.861 | V24: =$Q24*V8 -> 39627.861 | W24: =$Q24*W8 -> 39627.861 | X24: =$Q24*X8 -> 39627.861 | Y24: =$Q24*Y8 -> 39627.861 | Z24: =$Q24*Z8 -> 39627.861 | ... AD24: =$Q24*AD8 -> 39627.861 | AE24: =SUM(S24:AD24) -> 475534.34 | AG24: =Q24 -> 10.87 | AH24: P1 | AI24: =AI8*$AG24 -> 39627.861 | AJ24: =AJ8*$AG24 -> 39627.861 | AK24: =AK8*$AG24 -> 39627.861 | AL24: =AL8*$AG24 -> 39627.861 | AM24: =AM8*$AG24 -> 39627.861 | AN24: =AN8*$AG24 -> 39627.861 | AO24: =AO8*$AG24 -> 39627.861 | AP24: =AP8*$AG24 -> 39627.861 | ... AT24: =AT8*$AG24 -> 39627.861 | AU24: =SUM(AI24:AT24) -> 475534.34
A25: 21.74 | B25: P2 | C25: =C9*$A25 -> 39635.929 | D25: =D9*$A25 -> 43599.522 | E25: =E9*$A25 -> 50139.45 | F25: =F9*$A25 -> 57660.367 | G25: =G9*$A25 -> 66309.422 | H25: =H9*$A25 -> 72940.365 | I25: =I9*$A25 -> 80234.401 | J25: =J9*$A25 -> 84246.121 | ... N25: =N9*$A25 -> 92881.348 | O25: =SUM(C25:N25) -> 861868.05 | Q25: =A25 -> 21.74 | R25: P2 | S25: =$Q25*S9 -> 92881.348 | T25: =$Q25*T9 -> 92881.348 | U25: =$Q25*U9 -> 92881.348 | V25: =$Q25*V9 -> 92881.348 | W25: =$Q25*W9 -> 92881.348 | X25: =$Q25*X9 -> 92881.348 | Y25: =$Q25*Y9 -> 92881.348 | Z25: =$Q25*Z9 -> 92881.348 | ... AD25: =$Q25*AD9 -> 92881.348 | AE25: =SUM(S25:AD25) -> 1114576.2 | AG25: =Q25 -> 21.74 | AH25: P2 | AI25: =AI9*$AG25 -> 92881.348 | AJ25: =AJ9*$AG25 -> 92881.348 | AK25: =AK9*$AG25 -> 92881.348 | AL25: =AL9*$AG25 -> 92881.348 | AM25: =AM9*$AG25 -> 92881.348 | AN25: =AN9*$AG25 -> 92881.348 | AO25: =AO9*$AG25 -> 92881.348 | AP25: =AP9*$AG25 -> 92881.348 | ... AT25: =AT9*$AG25 -> 92881.348 | AU25: =SUM(AI25:AT25) -> 1114576.2
A26: 35.02 | B26: P3 | C26: =C10*$A26 -> 37725.854 | D26: =D10*$A26 -> 41498.44 | E26: =E10*$A26 -> 47723.206 | F26: =F10*$A26 -> 0 | G26: =G10*$A26 -> 0 | H26: =H10*$A26 -> 0 | I26: =I10*$A26 -> 0 | J26: =J10*$A26 -> 0 | ... N26: =N10*$A26 -> 69425.334 | O26: =SUM(C26:N26) -> 314368.46 | Q26: =A26 -> 35.02 | R26: P3 | S26: =$Q26*S10 -> 37729.356 | T26: =$Q26*T10 -> 41500.191 | U26: =$Q26*U10 -> 47724.957 | V26: =$Q26*V10 -> 0 | W26: =$Q26*W10 -> 0 | X26: =$Q26*X10 -> 0 | Y26: =$Q26*Y10 -> 0 | Z26: =$Q26*Z10 -> 0 | ... AD26: =$Q26*AD10 -> 88405.352 | AE26: =SUM(S26:AD26) -> 392170.56 | AG26: =Q26 -> 35.02 | AH26: P3 | AI26: =AI10*$AG26 -> 37725.854 | AJ26: =AJ10*$AG26 -> 37725.854 | AK26: =AK10*$AG26 -> 37725.854 | AL26: =AL10*$AG26 -> 0 | AM26: =AM10*$AG26 -> 0 | AN26: =AN10*$AG26 -> 0 | AO26: =AO10*$AG26 -> 0 | AP26: =AP10*$AG26 -> 0 | ... AT26: =AT10*$AG26 -> 88405.352 | AU26: =SUM(AI26:AT26) -> 378393.62
A27: 42.26 | B27: P4 | C27: =C11*$A27 -> 35917.86 | D27: =D11*$A27 -> 39509.646 | E27: =E11*$A27 -> 45436.093 | F27: =F11*$A27 -> 52251.507 | G27: =G11*$A27 -> 60089.233 | H27: =H11*$A27 -> 66098.157 | I27: =I11*$A27 -> 72707.972 | J27: =J11*$A27 -> 76343.371 | ... N27: =N11*$A27 -> 84168.567 | O27: =SUM(C27:N27) -> 781020.08 | Q27: =A27 -> 42.26 | R27: P4 | S27: =$Q27*S11 -> 84168.567 | T27: =$Q27*T11 -> 84168.567 | U27: =$Q27*U11 -> 84168.567 | V27: =$Q27*V11 -> 84168.567 | W27: =$Q27*W11 -> 84168.567 | X27: =$Q27*X11 -> 84168.567 | Y27: =$Q27*Y11 -> 84168.567 | Z27: =$Q27*Z11 -> 84168.567 | ... AD27: =$Q27*AD11 -> 84168.567 | AE27: =SUM(S27:AD27) -> 1010022.8 | AG27: =Q27 -> 42.26 | AH27: P4 | AI27: =AI11*$AG27 -> 84168.567 | AJ27: =AJ11*$AG27 -> 84168.567 | AK27: =AK11*$AG27 -> 84168.567 | AL27: =AL11*$AG27 -> 84168.567 | AM27: =AM11*$AG27 -> 84168.567 | AN27: =AN11*$AG27 -> 84168.567 | AO27: =AO11*$AG27 -> 84168.567 | AP27: =AP11*$AG27 -> 84168.567 | ... AT27: =AT11*$AG27 -> 84168.567 | AU27: =SUM(AI27:AT27) -> 1010022.8
A28: 59.17 | B28: P5 | C28: =C12*$A28 -> 83523.774 | D28: =D12*$A28 -> 91876.152 | E28: =E12*$A28 -> 105657.57 | F28: =F12*$A28 -> 121506.21 | G28: =G12*$A28 -> 139732.14 | H28: =H12*$A28 -> 153705.36 | I28: =I12*$A28 -> 169075.89 | J28: =J12*$A28 -> 177529.69 | ... N28: =N12*$A28 -> 195726.48 | O28: =SUM(C28:N28) -> 1816192.4 | Q28: =A28 -> 59.17 | R28: P5 | S28: =$Q28*S12 -> 195726.48 | T28: =$Q28*T12 -> 195726.48 | U28: =$Q28*U12 -> 195726.48 | V28: =$Q28*V12 -> 195726.48 | W28: =$Q28*W12 -> 195726.48 | X28: =$Q28*X12 -> 195726.48 | Y28: =$Q28*Y12 -> 195726.48 | Z28: =$Q28*Z12 -> 195726.48 | ... AD28: =$Q28*AD12 -> 195726.48 | AE28: =SUM(S28:AD28) -> 2348717.8 | AG28: =Q28 -> 59.17 | AH28: P5 | AI28: =AI12*$AG28 -> 195726.48 | AJ28: =AJ12*$AG28 -> 195726.48 | AK28: =AK12*$AG28 -> 195726.48 | AL28: =AL12*$AG28 -> 195726.48 | AM28: =AM12*$AG28 -> 195726.48 | AN28: =AN12*$AG28 -> 195726.48 | AO28: =AO12*$AG28 -> 195726.48 | AP28: =AP12*$AG28 -> 195726.48 | ... AT28: =AT12*$AG28 -> 195726.48 | AU28: =SUM(AI28:AT28) -> 2348717.8
A29: 64 | B29: P6 | C29: =C13*$A29 -> 31191.679 | D29: =D13*$A29 -> 34310.847 | E29: =E13*$A29 -> 39457.474 | F29: =F13*$A29 -> 0 | G29: =G13*$A29 -> 0 | H29: =H13*$A29 -> 0 | I29: =I13*$A29 -> 0 | J29: =J13*$A29 -> 0 | ... N29: =N13*$A29 -> 57400.76 | O29: =SUM(C29:N29) -> 259919.36 | Q29: =A29 -> 64 | R29: P6 | S29: =$Q29*S13 -> 31198.079 | T29: =$Q29*T13 -> 34314.047 | U29: =$Q29*U13 -> 39460.674 | V29: =$Q29*V13 -> 0 | W29: =$Q29*W13 -> 0 | X29: =$Q29*X13 -> 0 | Y29: =$Q29*Y13 -> 0 | Z29: =$Q29*Z13 -> 0 | ... AD29: =$Q29*AD13 -> 73093.411 | AE29: =SUM(S29:AD29) -> 324253.03 | AG29: =Q29 -> 64 | AH29: P6 | AI29: =AI13*$AG29 -> 31191.679 | AJ29: =AJ13*$AG29 -> 31191.679 | AK29: =AK13*$AG29 -> 31191.679 | AL29: =AL13*$AG29 -> 0 | AM29: =AM13*$AG29 -> 0 | AN29: =AN13*$AG29 -> 0 | AO29: =AO13*$AG29 -> 0 | AP29: =AP13*$AG29 -> 0 | ... AT29: =AT13*$AG29 -> 73093.411 | AU29: =SUM(AI29:AT29) -> 312855.27
A30: 82.11 | B30: P7 | C30: =C14*$A30 -> 59904.918 | D30: =D14*$A30 -> 65895.41 | E30: =E14*$A30 -> 75779.722 | F30: =F14*$A30 -> 87146.68 | G30: =G14*$A30 -> 100218.68 | H30: =H14*$A30 -> 110240.55 | I30: =I14*$A30 -> 121264.61 | J30: =J14*$A30 -> 127327.84 | ... N30: =N14*$A30 -> 140378.94 | O30: =SUM(C30:N30) -> 1302609.4 | Q30: =A30 -> 82.11 | R30: P7 | S30: =$Q30*S14 -> 140378.94 | T30: =$Q30*T14 -> 140378.94 | U30: =$Q30*U14 -> 140378.94 | V30: =$Q30*V14 -> 140378.94 | W30: =$Q30*W14 -> 140378.94 | X30: =$Q30*X14 -> 140378.94 | Y30: =$Q30*Y14 -> 140378.94 | Z30: =$Q30*Z14 -> 140378.94 | ... AD30: =$Q30*AD14 -> 140378.94 | AE30: =SUM(S30:AD30) -> 1684547.3 | AG30: =Q30 -> 82.11 | AH30: P7 | AI30: =AI14*$AG30 -> 140378.94 | AJ30: =AJ14*$AG30 -> 140378.94 | AK30: =AK14*$AG30 -> 140378.94 | AL30: =AL14*$AG30 -> 140378.94 | AM30: =AM14*$AG30 -> 140378.94 | AN30: =AN14*$AG30 -> 140378.94 | AO30: =AO14*$AG30 -> 140378.94 | AP30: =AP14*$AG30 -> 140378.94 | ... AT30: =AT14*$AG30 -> 140378.94 | AU30: =SUM(AI30:AT30) -> 1684547.3
A31: 85.73 | B31: P8 | C31: =C15*$A31 -> 191332.04 | D31: =D15*$A31 -> 210465.24 | E31: =E15*$A31 -> 242035.03 | F31: =F15*$A31 -> 278340.28 | G31: =G15*$A31 -> 320091.32 | H31: =H15*$A31 -> 352100.45 | I31: =I15*$A31 -> 387310.5 | J31: =J15*$A31 -> 406676.02 | ... N31: =N15*$A31 -> 448360.32 | O31: =SUM(C31:N31) -> 4160441.6 | Q31: =A31 -> 85.73 | R31: P8 | S31: =$Q31*S15 -> 448360.32 | T31: =$Q31*T15 -> 448360.32 | U31: =$Q31*U15 -> 448360.32 | V31: =$Q31*V15 -> 448360.32 | W31: =$Q31*W15 -> 448360.32 | X31: =$Q31*X15 -> 448360.32 | Y31: =$Q31*Y15 -> 448360.32 | Z31: =$Q31*Z15 -> 448360.32 | ... AD31: =$Q31*AD15 -> 448360.32 | AE31: =SUM(S31:AD31) -> 5380323.8 | AG31: =Q31 -> 85.73 | AH31: P8 | AI31: =AI15*$AG31 -> 448360.32 | AJ31: =AJ15*$AG31 -> 448360.32 | AK31: =AK15*$AG31 -> 448360.32 | AL31: =AL15*$AG31 -> 448360.32 | AM31: =AM15*$AG31 -> 448360.32 | AN31: =AN15*$AG31 -> 448360.32 | AO31: =AO15*$AG31 -> 448360.32 | AP31: =AP15*$AG31 -> 448360.32 | ... AT31: =AT15*$AG31 -> 448360.32 | AU31: =SUM(AI31:AT31) -> 5380323.8
A32: 108.68 | B32: P9 | C32: =C16*$A32 -> 138070.43 | D32: =D16*$A32 -> 151877.47 | E32: =E16*$A32 -> 174659.1 | F32: =F16*$A32 -> 0 | G32: =G16*$A32 -> 0 | H32: =H16*$A32 -> 0 | I32: =I16*$A32 -> 0 | J32: =J16*$A32 -> 0 | ... N32: =N16*$A32 -> 254085.32 | O32: =SUM(C32:N32) -> 1150536.9 | Q32: =A32 -> 108.68 | R32: P9 | S32: =$Q32*S16 -> 138081.3 | T32: =$Q32*T16 -> 151882.91 | U32: =$Q32*U16 -> 174664.53 | V32: =$Q32*V16 -> 0 | W32: =$Q32*W16 -> 0 | X32: =$Q32*X16 -> 0 | Y32: =$Q32*Y16 -> 0 | Z32: =$Q32*Z16 -> 0 | ... AD32: =$Q32*AD16 -> 323549.07 | AE32: =SUM(S32:AD32) -> 1435275.9 | AG32: =Q32 -> 108.68 | AH32: P9 | AI32: =AI16*$AG32 -> 138070.43 | AJ32: =AJ16*$AG32 -> 138070.43 | AK32: =AK16*$AG32 -> 138070.43 | AL32: =AL16*$AG32 -> 0 | AM32: =AM16*$AG32 -> 0 | AN32: =AN16*$AG32 -> 0 | AO32: =AO16*$AG32 -> 0 | AP32: =AP16*$AG32 -> 0 | ... AT32: =AT16*$AG32 -> 323549.07 | AU32: =SUM(AI32:AT32) -> 1384858.5
A33: 107.47 | B33: P10 | C33: =C17*$A33 -> 35929.792 | D33: =D17*$A33 -> 39522.771 | E33: =E17*$A33 -> 45451.187 | F33: =F17*$A33 -> 52268.865 | G33: =G17*$A33 -> 60109.195 | H33: =H17*$A33 -> 66120.114 | I33: =I17*$A33 -> 72732.125 | J33: =J17*$A33 -> 76368.732 | ... N33: =N17*$A33 -> 84196.527 | O33: =SUM(C33:N33) -> 781279.53 | Q33: =A33 -> 107.47 | R33: P10 | S33: =$Q33*S17 -> 84196.527 | T33: =$Q33*T17 -> 84196.527 | U33: =$Q33*U17 -> 84196.527 | V33: =$Q33*V17 -> 84196.527 | W33: =$Q33*W17 -> 84196.527 | X33: =$Q33*X17 -> 84196.527 | Y33: =$Q33*Y17 -> 84196.527 | Z33: =$Q33*Z17 -> 84196.527 | ... AD33: =$Q33*AD17 -> 84196.527 | AE33: =SUM(S33:AD33) -> 1010358.3 | AG33: =Q33 -> 107.47 | AH33: P10 | AI33: =AI17*$AG33 -> 84196.527 | AJ33: =AJ17*$AG33 -> 84196.527 | AK33: =AK17*$AG33 -> 84196.527 | AL33: =AL17*$AG33 -> 84196.527 | AM33: =AM17*$AG33 -> 84196.527 | AN33: =AN17*$AG33 -> 84196.527 | AO33: =AO17*$AG33 -> 84196.527 | AP33: =AP17*$AG33 -> 84196.527 | ... AT33: =AT17*$AG33 -> 84196.527 | AU33: =SUM(AI33:AT33) -> 1010358.3
A34: 36.23 | B34: P11 | C34: =C18*$A34 -> 0 | D34: =D18*$A34 -> 0 | E34: =E18*$A34 -> 0 | F34: =F18*$A34 -> 12150.711 | G34: =G18*$A34 -> 13365.782 | H34: =H18*$A34 -> 15370.65 | I34: =I18*$A34 -> 0 | J34: =J18*$A34 -> 0 | ... N34: =N18*$A34 -> 22360.453 | O34: =SUM(C34:N34) -> 101251.53 | Q34: =A34 -> 36.23 | R34: P11 | S34: =$Q34*S18 -> 0 | T34: =$Q34*T18 -> 0 | U34: =$Q34*U18 -> 0 | V34: =$Q34*V18 -> 12150.711 | W34: =$Q34*W18 -> 13365.782 | X34: =$Q34*X18 -> 15370.65 | Y34: =$Q34*Y18 -> 0 | Z34: =$Q34*Z18 -> 0 | ... AD34: =$Q34*AD18 -> 17676.247 | AE34: =SUM(S34:AD34) -> 93915.884 | AG34: =Q34 -> 36.23 | AH34: P11 | AI34: =AI18*$AG34 -> 0 | AJ34: =AJ18*$AG34 -> 0 | AK34: =AK18*$AG34 -> 0 | AL34: =AL18*$AG34 -> 12150.711 | AM34: =AM18*$AG34 -> 12150.711 | AN34: =AN18*$AG34 -> 12150.711 | AO34: =AO18*$AG34 -> 0 | AP34: =AP18*$AG34 -> 0 | ... AT34: =AT18*$AG34 -> 17676.247 | AU34: =SUM(AI34:AT34) -> 89480.875
A35: 63.4 | B35: P12 | C35: =C19*$A35 -> 0 | D35: =D19*$A35 -> 0 | E35: =E19*$A35 -> 0 | F35: =F19*$A35 -> 63422.116 | G35: =G19*$A35 -> 69764.328 | H35: =H19*$A35 -> 80228.977 | I35: =I19*$A35 -> 0 | J35: =J19*$A35 -> 0 | ... N35: =N19*$A35 -> 116713.1 | O35: =SUM(C35:N35) -> 528494.67 | Q35: =A35 -> 63.4 | R35: P12 | S35: =$Q35*S19 -> 0 | T35: =$Q35*T19 -> 0 | U35: =$Q35*U19 -> 0 | V35: =$Q35*V19 -> 63422.116 | W35: =$Q35*W19 -> 69764.328 | X35: =$Q35*X19 -> 80228.977 | Y35: =$Q35*Y19 -> 0 | Z35: =$Q35*Z19 -> 0 | ... AD35: =$Q35*AD19 -> 92263.324 | AE35: =SUM(S35:AD35) -> 490205.39 | AG35: =Q35 -> 63.4 | AH35: P12 | AI35: =AI19*$AG35 -> 0 | AJ35: =AJ19*$AG35 -> 0 | AK35: =AK19*$AG35 -> 0 | AL35: =AL19*$AG35 -> 63422.116 | AM35: =AM19*$AG35 -> 63422.116 | AN35: =AN19*$AG35 -> 63422.116 | AO35: =AO19*$AG35 -> 0 | AP35: =AP19*$AG35 -> 0 | ... AT35: =AT19*$AG35 -> 92263.324 | AU35: =SUM(AI35:AT35) -> 467056.32
A36: 99.62 | B36: P13 | C36: =C20*$A36 -> 0 | D36: =D20*$A36 -> 0 | E36: =E20*$A36 -> 0 | F36: =F20*$A36 -> 40322.732 | G36: =G20*$A36 -> 44355.005 | H36: =H20*$A36 -> 51008.256 | I36: =I20*$A36 -> 0 | J36: =J20*$A36 -> 0 | ... N36: =N20*$A36 -> 74204.26 | O36: =SUM(C36:N36) -> 336008.16 | Q36: =A36 -> 99.62 | R36: P13 | S36: =$Q36*S20 -> 0 | T36: =$Q36*T20 -> 0 | U36: =$Q36*U20 -> 0 | V36: =$Q36*V20 -> 40322.732 | W36: =$Q36*W20 -> 44355.005 | X36: =$Q36*X20 -> 51008.256 | Y36: =$Q36*Y20 -> 0 | Z36: =$Q36*Z20 -> 0 | ... AD36: =$Q36*AD20 -> 58659.494 | AE36: =SUM(S36:AD36) -> 311664.47 | AG36: =Q36 -> 99.62 | AH36: P13 | AI36: =AI20*$AG36 -> 0 | AJ36: =AJ20*$AG36 -> 0 | AK36: =AK20*$AG36 -> 0 | AL36: =AL20*$AG36 -> 40322.732 | AM36: =AM20*$AG36 -> 40322.732 | AN36: =AN20*$AG36 -> 40322.732 | AO36: =AO20*$AG36 -> 0 | AP36: =AP20*$AG36 -> 0 | ... AT36: =AT20*$AG36 -> 58659.494 | AU36: =SUM(AI36:AT36) -> 296946.68
C37: =SUM(C24:C36) -> 670142.96 | D37: =SUM(D24:D36) -> 737157.25 | E37: =SUM(E24:E36) -> 847730.84 | F37: =SUM(F24:F36) -> 789670.28 | G37: =SUM(G24:G36) -> 902326.05 | H37: =SUM(H24:H36) -> 998932.91 | I37: =SUM(I24:I36) -> 937557.53 | J37: =SUM(J24:J36) -> 984435.41 | ... O37: =SUM(O24:O36) -> 12761707 | S37: =SUM(S24:S36) -> 1292348.8 | T37: =SUM(T24:T36) -> 1313037.2 | U37: =SUM(U24:U36) -> 1347190.2 | V37: =SUM(V24:V36) -> 1201235.6 | W37: =SUM(W24:W36) -> 1212825.2 | X37: =SUM(X24:X36) -> 1231947.9 | Y37: =SUM(Y24:Y36) -> 1085340 | Z37: =SUM(Z24:Z36) -> 1085340 | ... AE37: =SUM(AE24:AE36) -> 16071566 | AI37: =SUM(AI24:AI36) -> 1292328 | AJ37: =SUM(AJ24:AJ36) -> 1292328 | AK37: =SUM(AK24:AK36) -> 1292328 | AL37: =SUM(AL24:AL36) -> 1201235.6 | AM37: =SUM(AM24:AM36) -> 1201235.6 | AN37: =SUM(AN24:AN36) -> 1201235.6 | AO37: =SUM(AO24:AO36) -> 1085340 | AP37: =SUM(AP24:AP36) -> 1085340 | ... AU37: =SUM(AU24:AU36) -> 15953672
B40: Année 1 | C40: Année 2 | D40: Année 3
A41: Trimestre 1 | B41: =SUM(C21+D21+E21) -> 39610 | C41: =SUM(S21:U21) -> 72362.214 | D41: =SUM(AI21:AK21) -> 71326.814
A42: Trimestre 2 | B42: =SUM(E21+F21+G21) -> 46495.14 | C42: =SUM(V21:X21) -> 68678.367 | D42: =SUM(AL21:AN21) -> 68043.088
A43: Trimestre 3 | B43: =SUM(I21+J21+K21) -> 57026.279 | C43: =SUM(Y21:AA21) -> 62821.614 | D43: =SUM(AO21:AQ21) -> 62821.614
A44: Trimestre 4 | B44: =SUM(L21:N21) -> 85552.855 | C44: =SUM(AB21:AD21) -> 90348.321 | D44: =SUM(AR21:AT21) -> 90348.321

Sheet S2  - Inventaire départ
A1: Évaluation de l'inventaire au démarrage TRIM 1: | H1: Données d'entreprise à ajuster en fonction de la situation
E2: (Plafond ou Plancher) | K2: Tableau de comparaison des transporteurs:
C3: Ventes TRIM 1 | D3: Lot | E3: Qté à commander | F3: Coût unitaire | G3: Coût total | H3: Volume unitaire (M3) | I3: Volume total (M3) | M3: M3 | N3: Coût | O3: Nombre de voyages | P3: Coût total
B4: P1 | C4: ='S1 - projections'!C8+'S1 - projections'!D8+'S1 - projections'!E8 -> 5235 | D4: =Données!J6 -> 50 | E4: =CEILING(C4,D4) -> 5250 | F4: =Données!H6 -> 6.75 | G4: =E4*F4 -> 35437.5 | H4: =Données!G6 -> 0.18 | I4: =E4*H4 -> 945 | K4: FTL | L4: Fournisseur: | M4: 150 | N4: 925 | O4: =I23 -> 32 | P4: =O4*N4 -> 29600 | Q4: =P4+P5 -> 30250
B5: P2 | C5: ='S1 - projections'!C9+'S1 - projections'!D9+'S1 - projections'!E9 -> 6135 | D5: =Données!J7 -> 100 | E5: =CEILING(C5,D5) -> 6200 | F5: =Données!H7 -> 13.5 | G5: =E5*F5 -> 83700 | H5: =Données!G7 -> 0.225 | I5: =E5*H5 -> 1395 | M5: 100 | N5: 650 | O5: =ROUNDUP(I26,0) -> 1 | P5: =O5*N5 -> 650
B6: P3 | C6: ='S1 - projections'!C10+'S1 - projections'!D10+'S1 - projections'!E10 -> 3625 | D6: =Données!J8 -> 100 | E6: =CEILING(C6,D6) -> 3700 | F6: =Données!H8 -> 20 | G6: =E6*F6 -> 74000 | H6: =Données!G8 -> 0.675 | I6: =E6*H6 -> 2497.5 | K6: LTL | L6: Desgagné: | M6: 150 | N6: 865 | O6: =I23 -> 32 | P6: =O6*N6 -> 27680 | Q6: =P6+P7 -> 27959.375
B7: P4 | C7: ='S1 - projections'!C11+'S1 - projections'!D11+'S1 - projections'!E11 -> 2860 | D7: =Données!J9 -> 100 | E7: =CEILING(C7,D7) -> 2900 | F7: =Données!H9 -> 29 | G7: =E7*F7 -> 84100 | H7: =Données!G9 -> 0.5 | I7: =E7*H7 -> 1450 | M7: 100 | N7: 745 | O7: =I26 -> 0.375 | P7: =O7*N7 -> 279.375
B8: P5 | C8: ='S1 - projections'!C12+'S1 - projections'!D12+'S1 - projections'!E12 -> 4750 | D8: =Données!J10 -> 50 | E8: =CEILING(C8,D8) -> 4750 | F8: =Données!H10 -> 35 | G8: =E8*F8 -> 166250 | H8: =Données!G10 -> 0.75 | I8: =E8*H8 -> 3562.5
B9: P6 | C9: ='S1 - projections'!C13+'S1 - projections'!D13+'S1 - projections'!E13 -> 1640 | D9: =Données!J11 -> 100 | E9: =CEILING(C9,D9) -> 1700 | F9: =Données!H11 -> 42 | G9: =E9*F9 -> 71400 | H9: =Données!G11 -> 0.9 | I9: =E9*H9 -> 1530
B10: P7 | C10: ='S1 - projections'!C14+'S1 - projections'!D14+'S1 - projections'!E14 -> 2455 | D10: =Données!J12 -> 50 | E10: =CEILING(C10,D10) -> 2500 | F10: =Données!H12 -> 54 | G10: =E10*F10 -> 135000 | H10: =Données!G12 -> 0.875 | I10: =E10*H10 -> 2187.5
B11: P8 | C11: ='S1 - projections'!C15+'S1 - projections'!D15+'S1 - projections'!E15 -> 7510 | D11: =Données!J13 -> 10 | E11: =CEILING(C11,D11) -> 7510 | F11: =Données!H13 -> 59 | G11: =E11*F11 -> 443090 | H11: =Données!G13 -> 1.8 | I11: =E11*H11 -> 13518
B12: P9 | C12: ='S1 - projections'!C16+'S1 - projections'!D16+'S1 - projections'!E16 -> 4275 | D12: =Données!J14 -> 10 | E12: =CEILING(C12,D12) -> 4280 | F12: =Données!H14 -> 66 | G12: =E12*F12 -> 282480 | H12: =Données!G14 -> 0.5625 | I12: =E12*H12 -> 2407.5
B13: P10 | C13: ='S1 - projections'!C17+'S1 - projections'!D17+'S1 - projections'!E17 -> 1125 | D13: =Données!J15 -> 10 | E13: =CEILING(C13,D13) -> 1130 | F13: =Données!H15 -> 69 | G13: =E13*F13 -> 77970 | H13: =Données!G15 -> 0.75 | I13: =E13*H13 -> 847.5
B14: P11 | C14: ='S1 - projections'!C18+'S1 - projections'!D18+'S1 - projections'!E18 -> 0 | D14: =Données!J16 -> 100 | E14: =CEILING(C14,D14) -> 0 | F14: =Données!H16 -> 22 | G14: =E14*F14 -> 0 | H14: =Données!G16 -> 0.675 | I14: =E14*H14 -> 0
B15: P12 | C15: ='S1 - projections'!C19+'S1 - projections'!D19+'S1 - projections'!E19 -> 0 | D15: =Données!J17 -> 10 | E15: =CEILING(C15,D15) -> 0 | F15: =Données!H17 -> 43 | G15: =E15*F15 -> 0 | H15: =Données!G17 -> 1.75 | I15: =E15*H15 -> 0
B16: P13 | C16: ='S1 - projections'!C20+'S1 - projections'!D20+'S1 - projections'!E20 -> 0 | D16: =Données!J18 -> 10 | E16: =CEILING(C16,D16) -> 0 | F16: =Données!H18 -> 65 | G16: =E16*F16 -> 0 | H16: =Données!G18 -> 1.25 | I16: =E16*H16 -> 0
G22: =SUM(G4:G16) -> 1453427.5 | I22: =SUM(I4:I6) -> 4837.5 | J22: volume total
I23: =ROUNDDOWN(I22/M4,0) -> 32 | J23: Nombre de voyage de 150 m3 en FTL
H24: volume chargé: | I24: =I23*M4 -> 4800
H25: reste | I25: =I22-I24 -> 37.5 | J25: m3
H26: Voyage 100 m3 | I26: =I25/M7 -> 0.375
B28: Coût de la commande 1= | G28: =G22 -> 1453427.5
B29: +frais de transport = le plus petit montant | G29: =MIN(Q4,Q6) -> 27959.375
B30: Total: | G30: =SUM(G28:G29) -> 1481386.9
B33: Note: Taxes à recevoir à traiter plus tard

Sheet S3 - IMMO
A1: Évaluation du bâtiment | C1: Choix: | D1: Acheter | E1: Louer
H2: Volume d'étalage = | N2: Caisses enregistreuses: | V2: Cafétéria:
A3: Magasin et Entrepôt | E3: =K23 -> 22717.048 | H3: Produits | I3: Votre choix: Ventes en unité | J3: Volume unitaire (M3) | K3: Volume total (M3) | N3: ='S1 - projections'!D44 -> 90348.321 | O3: Nombre d'unité vendues totales (en fct de votre choix) | W3: m de hauteur
A4: Espace pour les caisses enregistreuses | E4: =N9 -> 175 | H4: P1 | I4: ='S1 - projections'!AR8+'S1 - projections'!AS8+'S1 - projections'!AT8 -> 10936.852 | J4: =Données!G6 -> 0.18 | K4: =I4*J4 -> 1968.6334 | N4: =1000*13 -> 13000 | O4: capacité des caisses enregistreuses en nombre d'unités par trimestre
A5: Espace de cafétéria pour les employés (60% des employés) | E5: =V14 -> 185.75907 | H5: P2 | I5: ='S1 - projections'!AR9+'S1 - projections'!AS9+'S1 - projections'!AT9 -> 12817.113 | J5: =Données!G7 -> 0.225 | K5: =I5*J5 -> 2883.8505 | N5: =CEILING(N3/N4,1) -> 7 | O5: caisses enregistreuses nécessaires (plafond 1) | U5: Gestionnaire | V5: 1
A6: Espace de bureaux pour vous et certains employés | E6: =W39 -> 192 | H6: P3 | I6: ='S1 - projections'!AR10+'S1 - projections'!AS10+'S1 - projections'!AT10 -> 7573.274 | J6: =Données!G8 -> 0.675 | K6: =I6*J6 -> 5111.96 | N6: 5 | O6: m2 par caisse enregistreuse | U6: Caissier | V6: 7 | X6: (en lien avec le nombre de caisse, non-arrondi)
H7: P4 | I7: ='S1 - projections'!AR11+'S1 - projections'!AS11+'S1 - projections'!AT11 -> 5975.0521 | J7: =Données!G9 -> 0.5 | K7: =I7*J7 -> 2987.526 | N7: =N5*N6 -> 35 | O7: m2 pour le total des caisses enregistreuses | U7: Comptable-gestionnaire | V7: =N3/(W7*K18) -> 2.5740262 | W7: 2700 | X7: (capacité X produits/semaine)
A8: Volume total du bâtiment = | E8: =SUM(E3:E6) -> 23269.807 | F8: m3 | H8: P5 | I8: ='S1 - projections'!AR12+'S1 - projections'!AS12+'S1 - projections'!AT12 -> 9923.6004 | J8: =Données!G10 -> 0.75 | K8: =I8*J8 -> 7442.7003 | N8: 5 | O8: m de hauteur | U8: Vendeur | V8: =N3/(W8*K18) -> 6.9498709 | W8: 1000 | X8: (capacité X produits/semaine)
H9: P6 | I9: ='S1 - projections'!AR13+'S1 - projections'!AS13+'S1 - projections'!AT13 -> 3426.2536 | J9: =Données!G11 -> 0.9 | K9: =I9*J9 -> 3083.6283 | N9: =N7*N8 -> 175 | O9: m3 pour les caisses enregistreuses | U9: Manutentionnaire | V9: =3+(3000-2652)/3000 -> 3.116 | X9: (capacité X m3 de marchandises/semaine)
H10: P7 | I10: ='S1 - projections'!AR14+'S1 - projections'!AS14+'S1 - projections'!AT14 -> 5128.9345 | J10: =Données!G12 -> 0.875 | K10: =I10*J10 -> 4487.8177 | U10: Concierge | W10: =E8 -> 23269.807 | X10: (1 pour 12000 m3) ne pas automatiser
H11: P8 | I11: ='S1 - projections'!AR15+'S1 - projections'!AS15+'S1 - projections'!AT15 -> 15689.735 | J11: =Données!G13 -> 1.8 | K11: =I11*J11 -> 28241.522 | U11: Total des employés: | V11: =SUM(V5:V9) -> 20.639897 | W11: ajouter le nombre de concierges à la main
H12: P9 | I12: ='S1 - projections'!AR16+'S1 - projections'!AS16+'S1 - projections'!AT16 -> 8931.2404 | J12: =Données!G14 -> 0.5625 | K12: =I12*J12 -> 5023.8227 | U12: 0.6 | V12: =V11*U12 -> 12.383938 | W12: (60% des employés)
H13: P10 | I13: ='S1 - projections'!AR17+'S1 - projections'!AS17+'S1 - projections'!AT17 -> 2350.3264 | J13: =Données!G15 -> 0.75 | K13: =I13*J13 -> 1762.7448 | T13: m2/employé | U13: 5 | V13: =V12*U13 -> 61.919691 | W13: M2 total pour les 60% employé
H14: P11 | I14: ='S1 - projections'!AR18+'S1 - projections'!AS18+'S1 - projections'!AT18 -> 1463.6694 | J14: =Données!G16 -> 0.675 | K14: =I14*J14 -> 987.97682 | T14: H | U14: 3 | V14: =V13*U14 -> 185.75907 | W14: M3 (ajout de la hauteur désirée)
H15: P12 | I15: ='S1 - projections'!AR19+'S1 - projections'!AS19+'S1 - projections'!AT19 -> 4365.7724 | J15: =Données!G17 -> 1.75 | K15: =I15*J15 -> 7640.1017
H16: P13 | I16: ='S1 - projections'!AR20+'S1 - projections'!AS20+'S1 - projections'!AT20 -> 1766.4975 | J16: =Données!G18 -> 1.25 | K16: =I16*J16 -> 2208.1219
A17: Achat versus Location du bâtiment | J17: Volume total (étalage) | K17: =SUM(K4:K16) -> 73830.406 | L17: M3 | U17: Volume total en M3 | V17: =N3 -> 90348.321 | W17: Estimation chariots | Z17: (si je prends seulement des chariots élévateurs)
B18: Location | D18: Achat | K18: 13 | L18: semaine par trimestre | U18: Équipement | V18: Coût | W18: Capacité mensuelle M3 de manutention | X18: Capacité trimestrielle M3 de manutention | Y18: Nombre d'équipement | Z18: Volume traité (M3) | AA18: Coût totaux
A19: Location | B19: 1.35 | C19: /m3 | D19: 75 | E19: /m3 | K19: =K17/K18 -> 5679.262 | L19: M3 par semaine | U19: Petit diable | V19: 200 | W19: 1000 | X19: =W19*3 -> 3000 | Y19: 1 | Z19: =X19*Y19 -> 3000 | AA19: =V19*Y19 -> 200 | AB19: Obligatoire pour les petits colis
A20: Amélioration loc. | B20: 15 | C20: /m3 | D20: = | E20: Bâtiment | K20: 2 | L20: semaine d'inventaire | U20: Transpalette | V20: 2200 | W20: 5000 | X20: =W20*3 -> 15000 | Z20: =X20*Y20 -> 0 | AA20: =V20*Y20 -> 0
K21: =K19*2 -> 11358.524 | L21: M3 de marchandise à placer | U21: Chariot élévateur électrique | V21: 11500 | W21: 10000 | X21: =W21*3 -> 30000 | Y21: 3 | Z21: =X21*Y21 -> 90000 | AA21: =V21*Y21 -> 34500 | AB21: Obligatoire si entrepôt supérieur à 5 m de hauteur
K22: 2 | L22: doubler pour espace de circulation | Y22: Total = | Z22: =SUM(Z19:Z21) -> 93000
D23: =SUM(D24:D25) -> 1745235.5 | E23: Total | K23: =K21*2 -> 22717.048 | L23: m3 volume du magasin entrepôt | V23: Nombre: | Y23: Écart besoin | Z23: =Z22-V17 -> 2651.6789
A24: Loyer | B24: =B19*E8 -> 31414.24 | C24: /mois | D24: =(D19*E8)*85% -> 1483450.2 | E24: Terrain | K24: 5 | L24: mètre en hauteur | U24: Besoin en manutentionnaire: | V24: =Y21+(V17-Z22)/X20 -> 2.8232214
A25: Amélioration loc | B25: =ROUND((B20*E8),-3) -> 349000 | D25: =(D19*E8)*15% -> 261785.33 | E25: Bâtiment | K25: =K23/K24 -> 4543.4096 | L25: Surface d'étalages (en m2)
H28: Votre choix provient de ce tableau que vous avez calculé dans la feuille Excel des estimés de ventes!
A29: Module de caisses enregistreuses ( 4500$/module) | C29: =4500*N5 -> 31500 | E29: bureau vendeur | F29: =ROUND(7/2,0) -> 4
A30: Bureaux - Administration (955$/bureau) | C30: =CEILING((955*4),100) -> 3900
A31: Bureaux - vendeur ( 900$/ 2 bureaux) | C31: =CEILING((900*4),100) -> 3600
A32: Ameublement cafétéria (350$ / 4 employés) | C32: =CEILING((V12/4)*350,1) -> 1084 | V32: Espace bureau
A33: Étalage magasin (120$/ 10 m3) | C33: =(K21*30%)/10*120 -> 40890.687 | V33: Gestionnaire | W33: =V5 -> 1
A34: Étalage entrepôt (70$/ 10 m3) | C34: =(K21*70%)/10*70 -> 55656.768 | V34: Comptable-gestionnaire | W34: =V7 -> 2.5740262
A35: Équipement informatique (5000$/bureaux) | C35: =5000*(F29+W36) -> 40000 | V35: Total = | W35: =SUM(W33:W34) -> 3.5740262
A36: Équipement de manutention (voir tableau + haut) | C36: =AA21+AA19 -> 34700 | V36: arrondi.sup | W36: =ROUNDUP(W35,0) -> 4 | X36: bureau
A37: Équipement de cuisine (1000$ / 5 employés) | C37: =CEILING(V11/5,1)*1000 -> 5000 | W37: 16 | X37: m2
V38: Hauteur | W38: 3
V39: Volume M3 pour espace bureau | W39: =(W36*W37)*W38 -> 192

Sheet S4 - Montage financier
B1: Actif | E1: Passif | G1: Calculs des passifs: | K1: Actif | N1: Passif | P1: Calculs des passifs:
A2: =0.05+0.09975 -> 0.14975 | B2: Taxes à recevoir | C2: =C3*J2 -> 217650.77 | D2: =CEILING(((C2-0)*Q2)+((C3-D3)*R2)+(0*S2),1000) -> 670000 | E2: Marge de crédit | J2: =0.05+0.09975 -> 0.14975 | K2: Taxes à recevoir | L2: =C2 -> 217650.77 | M2: =D2 -> 670000 | N2: Marge de crédit | P2: 0.11 | Q2: 1 | R2: 0.75 | S2: 0.7 | T2: plafond (1000$)
B3: Stock de marchandises | C3: ='S2 - Inventaire départ'!G28 -> 1453427.5 | D3: ='S2 - Inventaire départ'!G30*(1+J2)*P3 -> 851612.28 | E3: Comptes fournisseurs | K3: Stock de marchandises | L3: =C3 -> 1453427.5 | M3: =D3 -> 851612.28 | N3: Comptes fournisseurs | P3: 0.5
B4: Charges payées d'avance | C4: =25000 -> 25000 | D4: {=SUM(C11+C9:C10)*70%} -> 59290 | E4: Hypothèque | K4: Charges payées d'avance | L4: =C4 -> 25000 | M4: =D4 -> 59290 | N4: Hypothèque | P4: 0.06 | Q4: 0.7 | R4: plafond (1000$)
B5: Frais d'incorporation | C5: =6500 -> 6500 | D5: =18498+133509 -> 152007 | E5: Capital de risque | K5: Frais d'incorporation | L5: =C5 -> 6500 | M5: =D5 -> 152007 | N5: Capital de risque | P5: 0.1
B6: Améliorations locatives | C6: ='S3 - IMMO'!B25 -> 349000 | K6: Terrain | L6: ='S3 - IMMO'!D24 -> 1483450.2
B7: Caisses enregistreuses | C7: ='S3 - IMMO'!C29 -> 31500 | K7: Bâtiment | L7: ='S3 - IMMO'!D25 -> 261785.33
B8: Ameublement | C8: =SUM('S3 - IMMO'!C30:C34) -> 105131.45 | K8: Caisses enregistreuses | L8: =C7 -> 31500
B9: Équipement informatique | C9: ='S3 - IMMO'!C35 -> 40000 | E9: Capitaux propres | K9: Ameublement | L9: =C8 -> 105131.45
B10: Équipement de manutention | C10: ='S3 - IMMO'!C36 -> 34700 | D10: =450000 -> 450000 | E10: Capital-actions | K10: Équipement informatique | L10: =C9 -> 40000 | N10: Capitaux propres
B11: Équipement de cuisine | C11: ='S3 - IMMO'!C37 -> 5000 | D11: =85000 -> 85000 | E11: Subvention | K11: Équipement de manutention | L11: =C10 -> 34700 | M11: =D10 -> 450000 | N11: Capital-actions
K12: Équipement de cuisine | L12: =C11 -> 5000 | N12: Subvention
B13: Total des actifs: | C13: =SUM(C2:C11) -> 2267909.7 | D13: =SUM(D2:D11) -> 2267909.3 | E13: :Total des passifs et des capitaux propres
K14: Total des actifs: | L14: =SUM(L2:L12) -> 3664145.3 | M14: =SUM(M2:M12) -> 2182909.3 | N14: :Total des passifs et des capitaux propres
C15: écart: | D15: =C13-D13 -> 0.44298388
L16: écart: | M16: =L14-M14 -> 1481236
A17: Faites votre choix final et inscrire les informations dans votre bilan de démarrage sur Acomba
A18: Dans les soldes d'ouverture de chacun de vos comptes | J18: Faire votre bon de commande 1 (énoncé de travail)
J19: Voir modèle disponible sur Léa
H29: Marge de crédit:

Sheet IMPORTANT

Sheet S5 -Outil - Ventes
C3: Analyse des ventes
D4: VOIR DOC. LÉA | H4: E *prix de vente + F*50%*Prix de vente | I4: =(C-E-F) | J4: H * Prix coûtant | K4: Analyse complémentaire (ventes perdue)
B5: Produits | C5: Quantités commandées | D5: Ventes potentielles | E5: Ventes réelles en unités | F5: Inventaire de début | G5: Ventes produit saisonniers en unités | H5: Ventes totales (TRIM 1) en $ (sans les taxes à payer) | I5: Inventaire de fin (en unités) | J5: Inventaire de fin (en $) | K5: Produits | L5: Écart (en unité) | M5: Écart (en $) | N5: Besoins commande 2 | O5: Volume unitaire (M3) | P5: Volume total achété (M3)
B6: P1 | C6: ='S2 - Inventaire départ'!E4 -> 5250 | D6: 5385 | E6: =MIN(C6:D6) -> 5250 | F6: ='Fournisseur 1'!B10 -> 5300 | H6: =(E6*Données!I6)+(G6*50%)*Données!I6 -> 57067.5 | I6: =C6-E6-G6 -> 0 | J6: =I6*Données!H6 -> 0 | K6: =B6 -> P1 | L6: =IF(D6>E6,D6-E6,0) -> 135 | M6: =L6*Données!I6 -> 1467.45 | O6: ='S3 - IMMO'!J4 -> 0.18 | P6: =(E6+N6)*O6 -> 945
B7: P2 | C7: ='S2 - Inventaire départ'!E5 -> 6200 | D7: 6270 | E7: =MIN(C7:D7) -> 6200 | F7: ='Fournisseur 1'!B11 -> 6200 | H7: =(E7*Données!I7)+(G7*50%)*Données!I7 -> 134788 | I7: =C7-E7-G7 -> 0 | J7: =I7*Données!H7 -> 0 | K7: =B7 -> P2 | L7: =IF(D7>E7,D7-E7,0) -> 70 | M7: =L7*Données!I7 -> 1521.8 | O7: ='S3 - IMMO'!J5 -> 0.225 | P7: =(E7+N7)*O7 -> 1395
B8: P3 | C8: ='S2 - Inventaire départ'!E6 -> 3700 | D8: 3477 | E8: =MIN(C8:D8) -> 3477 | F8: ='Fournisseur 1'!B12 -> 3700 | H8: =(E8*Données!I8)+(G8*50%)*Données!I8 -> 121764.54 | I8: =C8-E8-G8 -> 223 | J8: =I8*Données!H8 -> 4460 | K8: =B8 -> P3 | L8: =IF(D8>E8,D8-E8,0) -> 0 | M8: =L8*Données!I8 -> 0 | O8: ='S3 - IMMO'!J6 -> 0.675 | P8: =(E8+N8)*O8 -> 2346.975
B9: P4 | C9: ='S2 - Inventaire départ'!E7 -> 2900 | D9: 2923 | E9: =MIN(C9:D9) -> 2900 | F9: ='Fournisseur 1'!B13 -> 2900 | H9: =(E9*Données!I9)+(G9*50%)*Données!I9 -> 122554 | I9: =C9-E9-G9 -> 0 | J9: =I9*Données!H9 -> 0 | K9: =B9 -> P4 | L9: =IF(D9>E9,D9-E9,0) -> 23 | M9: =L9*Données!I9 -> 971.98 | O9: ='S3 - IMMO'!J7 -> 0.5 | P9: =(E9+N9)*O9 -> 1450
B10: P5 | C10: ='S2 - Inventaire départ'!E8 -> 4750 | D10: 4754 | E10: =MIN(C10:D10) -> 4750 | F10: ='Fournisseur 1'!B14 -> 4800 | H10: =(E10*Données!I10)+(G10*50%)*Données!I10 -> 281057.5 | I10: =C10-E10-G10 -> 0 | J10: =I10*Données!H10 -> 0 | K10: =B10 -> P5 | L10: =IF(D10>E10,D10-E10,0) -> 4 | M10: =L10*Données!I10 -> 236.68 | O10: ='S3 - IMMO'!J8 -> 0.75 | P10: =(E10+N10)*O10 -> 3562.5
B11: P6 | C11: ='S2 - Inventaire départ'!E9 -> 1700 | D11: 1621 | E11: =MIN(C11:D11) -> 1621 | F11: ='Fournisseur 1'!B15 -> 1700 | H11: =(E11*Données!I11)+(G11*50%)*Données!I11 -> 103744 | I11: =C11-E11-G11 -> 79 | J11: =I11*Données!H11 -> 3318 | K11: =B11 -> P6 | L11: =IF(D11>E11,D11-E11,0) -> 0 | M11: =L11*Données!I11 -> 0 | O11: ='S3 - IMMO'!J9 -> 0.9 | P11: =(E11+N11)*O11 -> 1458.9
B12: P7 | C12: ='S2 - Inventaire départ'!E10 -> 2500 | D12: 2454 | E12: =MIN(C12:D12) -> 2454 | F12: ='Fournisseur 1'!B16 -> 2500 | H12: =(E12*Données!I12)+(G12*50%)*Données!I12 -> 201497.94 | I12: =C12-E12-G12 -> 46 | J12: =I12*Données!H12 -> 2484 | K12: =B12 -> P7 | L12: =IF(D12>E12,D12-E12,0) -> 0 | M12: =L12*Données!I12 -> 0 | O12: ='S3 - IMMO'!J10 -> 0.875 | P12: =(E12+N12)*O12 -> 2147.25
B13: P8 | C13: ='S2 - Inventaire départ'!E11 -> 7510 | D13: 7505 | E13: =MIN(C13:D13) -> 7505 | F13: ='Fournisseur 1'!B17 -> 7600 | H13: =(E13*Données!I13)+(G13*50%)*Données!I13 -> 643403.65 | I13: =C13-E13-G13 -> 5 | J13: =I13*Données!H13 -> 295 | K13: =B13 -> P8 | L13: =IF(D13>E13,D13-E13,0) -> 0 | M13: =L13*Données!I13 -> 0 | O13: ='S3 - IMMO'!J11 -> 1.8 | P13: =(E13+N13)*O13 -> 13509
B14: P9 | C14: ='S2 - Inventaire départ'!E12 -> 4280 | D14: 4276 | E14: =MIN(C14:D14) -> 4276 | F14: ='Fournisseur 1'!B18 -> 4300 | H14: =(E14*Données!I14)+(G14*50%)*Données!I14 -> 464715.68 | I14: =C14-E14-G14 -> 4 | J14: =I14*Données!H14 -> 264 | K14: =B14 -> P9 | L14: =IF(D14>E14,D14-E14,0) -> 0 | M14: =L14*Données!I14 -> 0 | O14: ='S3 - IMMO'!J12 -> 0.5625 | P14: =(E14+N14)*O14 -> 2405.25
B15: P10 | C15: ='S2 - Inventaire départ'!E13 -> 1130 | D15: 1130 | E15: =MIN(C15:D15) -> 1130 | F15: ='Fournisseur 1'!B19 -> 1200 | H15: =(E15*Données!I15)+(G15*50%)*Données!I15 -> 121441.1 | I15: =C15-E15-G15 -> 0 | J15: =I15*Données!H15 -> 0 | K15: =B15 -> P10 | L15: =IF(D15>E15,D15-E15,0) -> 0 | M15: =L15*Données!I15 -> 0 | O15: ='S3 - IMMO'!J13 -> 0.75 | P15: =(E15+N15)*O15 -> 847.5
B16: P11 | C16: ='S2 - Inventaire départ'!E14 -> 0 | D16: 0 | E16: =MIN(C16:D16) -> 0 | F16: ='Fournisseur 1'!B20 -> 900 | G16: =IF(C16<D16,0,C16-D16) -> 0 | H16: =(E16*Données!I16)+(G16*50%)*Données!I16 -> 0 | I16: =C16-E16-G16 -> 0 | J16: =I16*Données!H16 -> 0 | K16: =B16 -> P11 | L16: =IF(D16>E16,D16-E16,0) -> 0 | M16: =L16*Données!I16 -> 0 | O16: ='S3 - IMMO'!J14 -> 0.675 | P16: =(E16+N16)*O16 -> 0
B17: P12 | C17: ='S2 - Inventaire départ'!E15 -> 0 | D17: 0 | E17: =MIN(C17:D17) -> 0 | F17: ='Fournisseur 1'!B21 -> 2600 | G17: =IF(C17<D17,0,C17-D17) -> 0 | H17: =(E17*Données!I17)+(G17*50%)*Données!I17 -> 0 | I17: =C17-E17-G17 -> 0 | J17: =I17*Données!H17 -> 0 | K17: =B17 -> P12 | L17: =IF(D17>E17,D17-E17,0) -> 0 | M17: =L17*Données!I17 -> 0 | O17: ='S3 - IMMO'!J15 -> 1.75 | P17: =(E17+N17)*O17 -> 0
B18: P13 | C18: ='S2 - Inventaire départ'!E16 -> 0 | D18: 0 | E18: =MIN(C18:D18) -> 0 | F18: ='Fournisseur 1'!B22 -> 1100 | G18: =IF(C18<D18,0,C18-D18) -> 0 | H18: =(E18*Données!I18)+(G18*50%)*Données!I18 -> 0 | I18: =C18-E18-G18 -> 0 | J18: =I18*Données!H18 -> 0 | K18: =B18 -> P13 | L18: =IF(D18>E18,D18-E18,0) -> 0 | M18: =L18*Données!I18 -> 0 | O18: ='S3 - IMMO'!J16 -> 1.25 | P18: =(E18+N18)*O18 -> 0
C19: =SUM(C6:C18) -> 39920 | D19: =SUM(D6:D18) -> 39795 | E19: =SUM(E6:E18) -> 39563 | F19: =SUM(F6:F18) -> 44800 | G19: =SUM(G6:G18) -> 0 | H19: =SUM(H6:H18) -> 2252033.9 | I19: =SUM(I6:I18) -> 357 | J19: =SUM(J6:J18) -> 10821 | L19: =SUM(L6:L18) -> 232 | M19: =SUM(M6:M18) -> 4197.91 | O19: ='S3 - IMMO'!J17 -> Volume total (étalage) | P19: =SUM(P6:P18) -> 30067.375 | Q19: m3

Sheet Desgagné 1
C1: Avec Transport Desgagné, vous allez toujours arriver en premier! | D1: Bon de commande
B2: Transport Desgagnés
B3: 123, rue XYZ | D3: N° de commande : | E3: 1256
B4: Québec, G4D 1S5 | D4: Date : | E4: 45704
B5: 410-555-555 | D5: ID du client : | E5: ABC12345
B6: Service@DGT.com
B7: Simul inc
B8: Entreprise Issa
B9: Cégep Limoilou
B10: Québec, G4D 1S5
B11: 0
B12: Vendeur | C12: Tâche | D12: Conditions de paiement | E12: Date d’échéance
B13: Robert Vézina | C13: Représentant | D13: N/30 +5% retard | E13: 17/02/2026
B15: Quantité | C15: Description | D15: Prix unitaire | E15: Total de la ligne
B16: 32 | C16: voyages 150 m3 | D16: =865 -> 865 | E16: =Facture[[#This Row],[Prix unitaire]]*Facture[[#This Row],[Quantité]] -> 27680
B17: 0.47 | C17: voyages 100 m3 | D17: 745 | E17: =Facture[[#This Row],[Prix unitaire]]*Facture[[#This Row],[Quantité]] -> 350.15
D26: Sous-total | E26: =SUM(Facture[Total de la ligne]) -> 28030.15
B27: Taxes | D27: 0.14975 | E27: =Facture[[#Totals],[Total de la ligne]]*0.14975 -> 4197.515
B28: TOTAL | E28: =SUM(E26:E27) -> 32227.665
B29: ***Ceci n'est pas une facture ****
B30: NOUS VOUS REMERCIONS DE VOTRE CONFIANCE.

Sheet Fournisseur 1
B2: Vendu à | C2: Simul inc. | F2: N° bon de commande | G2: 48826
C3: No. 1112223 | F3: Date | G3: 45703
C4: cégep Limoilou
C5: G1G1G1
C6: 581-090-2426
B9: Quantité | C9: Nº de l’article | D9: Description | E9: Prix unitaire | F9: Remise | G9: Total de la ligne
B10: 5300 | C10: 1 | D10: P1 | E10: 6.75 | G10: =Table_SalesReceiptDetails[[#This Row],[Quantité]]*Table_SalesReceiptDetails[[#This Row],[Prix unitaire]] -> 35775
B11: 6200 | C11: 2 | D11: P2 | E11: 13.5 | G11: =Table_SalesReceiptDetails[[#This Row],[Quantité]]*Table_SalesReceiptDetails[[#This Row],[Prix unitaire]] -> 83700
B12: 3700 | C12: 3 | D12: P3 | E12: 20 | G12: =Table_SalesReceiptDetails[[#This Row],[Quantité]]*Table_SalesReceiptDetails[[#This Row],[Prix unitaire]] -> 74000
B13: 2900 | C13: 4 | D13: P4 | E13: 29 | G13: =Table_SalesReceiptDetails[[#This Row],[Quantité]]*Table_SalesReceiptDetails[[#This Row],[Prix unitaire]] -> 84100
B14: 4800 | C14: 5 | D14: P5 | E14: 35 | G14: =Table_SalesReceiptDetails[[#This Row],[Quantité]]*Table_SalesReceiptDetails[[#This Row],[Prix unitaire]] -> 168000
B15: 1700 | C15: 6 | D15: P6 | E15: 42 | G15: =Table_SalesReceiptDetails[[#This Row],[Quantité]]*Table_SalesReceiptDetails[[#This Row],[Prix unitaire]] -> 71400
B16: 2500 | C16: 7 | D16: P7 | E16: 54 | G16: =Table_SalesReceiptDetails[[#This Row],[Quantité]]*Table_SalesReceiptDetails[[#This Row],[Prix unitaire]] -> 135000
B17: 7600 | C17: 8 | D17: P8 | E17: 59 | G17: =Table_SalesReceiptDetails[[#This Row],[Quantité]]*Table_SalesReceiptDetails[[#This Row],[Prix unitaire]] -> 448400
B18: 4300 | C18: 9 | D18: P9 | E18: 66 | G18: =Table_SalesReceiptDetails[[#This Row],[Quantité]]*Table_SalesReceiptDetails[[#This Row],[Prix unitaire]] -> 283800
B19: 1200 | C19: 10 | D19: P10 | E19: 69 | G19: =Table_SalesReceiptDetails[[#This Row],[Quantité]]*Table_SalesReceiptDetails[[#This Row],[Prix unitaire]] -> 82800
B20: 900 | C20: 11 | D20: P11 | E20: 22 | G20: =Table_SalesReceiptDetails[[#This Row],[Quantité]]*Table_SalesReceiptDetails[[#This Row],[Prix unitaire]] -> 19800
B21: 2600 | C21: 12 | D21: P12 | E21: 43 | G21: =Table_SalesReceiptDetails[[#This Row],[Quantité]]*Table_SalesReceiptDetails[[#This Row],[Prix unitaire]] -> 111800
B22: 1100 | C22: 13 | D22: P13 | E22: 65 | G22: =Table_SalesReceiptDetails[[#This Row],[Quantité]]*Table_SalesReceiptDetails[[#This Row],[Prix unitaire]] -> 71500
G24: =SUM(Table_SalesReceiptDetails[Total de la ligne]) -> 1670075
B25: Pour toute question concernant cette facture, utilisez les informations de contact : | F25: Sous-total | G25: =SUM(Table_SalesReceiptDetails[Total de la ligne]) -> 1670075
B26: Nom, numéro de téléphone, e-mail du contact | E26: T.P.S. | F26: 0.05 | G26: =F26*G25 -> 83503.75
B27: Nous vous remercions de votre confiance. | E27: T.V.Q | F27: 0.09975 | G27: =G25*F27 -> 166589.98
F28: Total | G28: =G25+G26+G27 -> 1920168.7

Sheet S5 -Outil - Charges
A1: Outil - Coûts TRIM 1
A2: Tableau des indicateurs: | H2: Sections à compléter
A3: Quantités vendues | B3: ='S5 -Outil - Ventes'!E19 -> 39563 | C3: unités
A4: Volume acheté | B4: ='S5 -Outil - Ventes'!P19 -> 30067.375 | C4: M3 | H4: Taux de taxes = | I4: 0.14975
A5: Valeur des ventes | B5: ='S5 -Outil - Ventes'!H19 -> 2252033.9 | H5: Trimestre/an = | I5: 4
A6: Volume du bâtiment | B6: ='S3 - IMMO'!E8 -> 23269.807 | C6: M3 | H6: Nombre de sem = | I6: 13
H7: Mois/Trimestre = | I7: 3
A9: Coût des marchandises vendues | D9: Salaires (selon Ventes Trim 1)
A11: Inventaire du début | B11: 0
A12: Achats | B12: =Facture[[#Totals],[Total de la ligne]]+'Fournisseur 1'!G24 -> 1698105.1 | E12: Capacité TRIM | F12: UDM | G12: salaire/semaine | H12: Nombre | I12: Salaire TRIM 1
A13: Fret à l'achat | D13: Gestionnaire | G13: 1000 | H13: 1 | I13: =H13*G13*$I$6 -> 13000
A14: Inventaire de fin | B14: ='S5 -Outil - Ventes'!J19 -> 10821 | D14: Cassier.e.s | E14: 13000 | F14: un | G14: 600 | H14: =B3/E14 -> 3.0433077 | I14: =H14*G14*$I$6 -> 23737.8
D15: Comptable-gestionnaires | E15: 35100 | F15: un | G15: 950 | H15: =B3/E15 -> 1.127151 | I15: =H15*G15*$I$6 -> 13920.315
D16: Vendeur.e.s | E16: 13000 | F16: un | G16: 0.025 | H16: =B3/E16 -> 3.0433077 | I16: =G16*B5 -> 56300.848
D17: Manutentionnaire.s | E17: 30000 | F17: m3 | G17: 620 | H17: =B4/E17 -> 1.0022458 | I17: =H17*G17*$I$6 -> 8078.1014
D18: Concierge.s | E18: 12000 | F18: m3 | G18: 640 | H18: =B6/E18 -> 1.9391506 | I18: =H18*G18*$I$6 -> 16133.733
D19: Salaires | H19: =ROUND(SUM(H13:H18),1) -> 11.2 | I19: =SUM(I13:I18) -> 131170.8
D20: Retenues à la sources = | E20: 0.26101 | I20: =I19*E20 -> 34236.89
D21: Avantages sociaux = | E21: 0.20317 | I21: =I19*E21 -> 26649.971
D22: Assurances coll = | E22: 12 | I22: =E22*H19*13 -> 1747.2
D23: Fonds de pension = | E23: 0.04 | I23: =I19*E23 -> 5246.8319
D24: Vacances = | E24: 0.04 | I24: =E24*I19 -> 5246.8319
A28: Téléphonie et système de communication | F28: Frais de livraison aux clients:
A29: Coût location/ système / mois | B29: 250
A30: Nombre d'employé par location | B30: 4 | G30: qté vendue | H30: vol. unitaire | I30: Total M3
A31: Nombre de location | B31: =CEILING((H13+H14+H15+H16)/B30,1) -> 3 | F31: P7 | G31: ='S5 -Outil - Ventes'!E12 -> 2454 | H31: =Données!G12 -> 0.875 | I31: =G31*H31 -> 2147.25
A32: Coût total par mois = | B32: =B29*B31 -> 750 | F32: P8 | G32: ='S5 -Outil - Ventes'!E13 -> 7505 | H32: =Données!G13 -> 1.8 | I32: =G32*H32 -> 13509
A33: Coût par trimestre = | B33: =B32*I7 -> 2250 | F33: P9 | G33: ='S5 -Outil - Ventes'!E14 -> 4276 | H33: =Données!G14 -> 0.5625 | I33: =G33*H33 -> 2405.25
A34: Taxes | B34: =B33*I4 -> 336.9375 | I34: =SUM(I31:I33) -> 18061.5 | J34: m3
H35: voyage = | I35: =ROUNDDOWN(I34/G38,0) -> 120 | J35: =I35*G38 -> 18000
A36: Électricité (même valeur pour tous) - Dépenses fixes (facture équilibrée) | H36: volume restant = | I36: =I34-(I35*G38) -> 61.5
A37: Total | D37: 18500 | I37: $ voyage
A38: Taxes | D38: =D37*I4 -> 2770.375 | F38: Camion | G38: 150 | H38: m3 | I38: 640 | J38: =I35*I38 -> 76800
G39: 100 | H39: m3 | I39: 500 | J39: =I39*(I36/G39) -> 307.5
F40: Frais de livraison = | J40: =J38+J39 -> 77107.5
A41: Frais d'entretien | F41: Taxes | J41: =J40*I4 -> 11546.848
B42: $/an | C42: Référence | D42: $T1
A43: Bâti. Ou Amélior. Loc. | B43: 8 | C43: /an /m3 | D43: ='S3 - IMMO'!E8*'S5 -Outil - Charges'!B43 -> 186158.46
A44: Caisses enregis. | B44: 600 | C44: /an / par utilisation | D44: =('S3 - IMMO'!N5*'S5 -Outil - Charges'!B44)/4 -> 1050
A45: Équip. De cuisine | B45: 0.1 | C45: $ coût total de l'équipement/an | D45: =('S3 - IMMO'!C37*'S5 -Outil - Charges'!B45)/4 -> 125 | F45: Loyer | G45: (Pour ceux qui louent le bâtiment)
A46: Équipement de manutention | B46: 0.1 | C46: $ coût total de l'équipement / an / utilisation | D46: =(('S3 - IMMO'!C36*B46)/4)/H17 -> 865.55611 | F46: Location mensuelle | G46: =1.35*B6 -> 31414.24
A47: Téléphonie et comm. | B47: 0 | C47: inclus dans la location | F47: Location trimestrielle | G47: =I7*G46 -> 94242.719
A48: Ameublement | B48: 0.05 | C48: $ coût total de l'équipement/an | D48: =('S4 - Montage financier'!C8*'S5 -Outil - Charges'!B48)/4 -> 1314.1432 | F48: Taxes | G48: =G47*I4 -> 14112.847
A49: Équip. Inform | B49: 500 | C49: /an / par utilisation | D49: =(B49/(H13+H14+H15))/4 -> 24.175805
A50: Total | D50: =SUM(D43:D49) -> 189537.33 | F50: Publicité
A51: Taxes | D51: =D50*I4 -> 28383.216
F52: % ventes M1 | G52: /mois
A53: Assurances: | F53: 0.12 | G53: 3000
B54: $/an | C54: Référence | D54: $T1 | F54: =(F53*B5) -> 270244.07 | G54: =G53*2 -> 6000
A55: Bâti. Ou Amélior. Loc. | B55: 0.015 | C55: $ coût total par an | D55: =('S4 - Montage financier'!C6*'S5 -Outil - Charges'!B55)/4 -> 1308.75 | F55: Total | G55: =G54+F54 -> 276244.07
A56: Équipements (tous) | B56: 0.03 | C56: $ coût total par an | D56: =(B56*('S4 - Montage financier'!C7+'S4 - Montage financier'!C9+'S4 - Montage financier'!C10+'S4 - Montage financier'!C11))/4 -> 834 | F56: Taxes | G56: =G55*I4 -> 41367.549
A57: Mobilier (tous) | B57: 0.005 | C57: $ coût total par an | D57: =(B57*('S3 - IMMO'!C30+'S3 - IMMO'!C31+'S3 - IMMO'!C32+'S3 - IMMO'!C33+'S3 - IMMO'!C34))/4 -> 131.41432
A58: Total | D58: =SUM(D55:D57) -> 2274.1643
A59: Taxes 9% (à inclure) | B59: 0.09 | D59: =D58*(1+B59) -> 2478.8391 | F59: Fournitures de bureau:
F61: $ Employé / an | G61: Équivalent temps plein
A62: Taxes municipales: | B62: Ne s'applique pas à la location | F62: 700 | G62: =H13+H14+H15+H16 -> 8.2137664
D63: $T1 | F63: Total | G63: =G62*F62/I5 -> 1437.4091
A64: Taxes municipales | B64: 0.025 | C64: /an du coût Terrain et Bâtiment | D64: =(('S4 - Montage financier'!L6+'S4 - Montage financier'!L7)*'S5 -Outil - Charges'!B64)/4 -> 10907.722 | F64: Taxes | G64: =G63*I4 -> 215.25202
A65: Taxes | D65: =D64*I4 -> 1633.4314
F67: Frais de banque (pas taxables)
A68: Amortissement (pas taxables) | F68: 15 | G68: 5000 | H68: un vendues
A69: Biens | B69: Amortissement annuel | C69: Valeur | D69: Charges d'amort. TRIM | F69: Produits vendus = | G69: =B3 -> 39563 | H69: un vendues
A70: Terrain | B70: NA | C70: ='S4 - Montage financier'!L6 -> 1483450.2 | F70: Frais de banque | G70: =G69/G68*F68 -> 118.689
A71: Bâtiment | B71: 0.04
A72: Améliorations locatives | B72: 0.2 | C72: ='S4 - Montage financier'!C6 -> 349000 | D72: =(C72*B72)/4 -> 17450
A73: Site transactionnel | B73: 0.5
A74: Modules de caisses enre. | B74: 0.2 | C74: ='S4 - Montage financier'!C7 -> 31500 | D74: =(C74*B74)/4 -> 1575
A75: Équipement de cuisine | B75: 0.2 | C75: ='S4 - Montage financier'!C11 -> 5000 | D75: =(C75*B75)/4 -> 250 | F75: Honoraires professionnelles
A76: Équipement de manutention | B76: 0.2 | C76: ='S4 - Montage financier'!C10 -> 34700 | D76: =(C76*B76)/4 -> 1735 | F76: 0.0035 | G76: des ventes totales
A77: Équipement informatique | B77: 0.3 | C77: ='S4 - Montage financier'!C9 -> 40000 | D77: =(C77*B77)/4 -> 3000 | F77: Total | G77: =F76*B5 -> 7882.1187
A78: Ameublements | B78: 0.2 | C78: ='S4 - Montage financier'!C8 -> 105131.45 | D78: =(C78*B78)/4 -> 5256.5727 | F78: Taxes | G78: =G77*I4 -> 1180.3473
F80: Si commerce électronique
F82: Frais de site électronique
F83: Domaine = | G83: 750 | H83: /an
F84: Total | G84: =G83/I5 -> 187.5 | H84: /trimestre
F85: Espace de stockage= | G85: 155 | H85: /mois
F86: Total | G86: =G85*I7 -> 465
F87: Frais de site total | G87: =G86+G84 -> 652.5
F88: Taxes | G88: =G87*I4 -> 97.711875
F90: Frais de transactions via internet
F91: Taux | G91: 0.025
F92: Frais de transaction
F93: Taxes | G93: =G92*I4 -> 0

Sheet S5 -Emprunt
B1: Hypothèque | J1: Capital de risque | R1: Marge de crédit
C3: Valeur de l'emprunt : | D3: ='S4 - Montage financier'!D4 -> 59290 | K3: Valeur de l'emprunt : | L3: ='S4 - Montage financier'!D5 -> 152007 | S3: Valeur de l'emprunt : | T3: ='S4 - Montage financier'!D2 -> 670000 | AA3: Valeur de l'emprunt : | AB3: 0
C4: Taux de l'emprunt : | D4: 0.06 | K4: Taux de l'emprunt : | L4: 0.1 | S4: Taux de l'emprunt : | T4: 0.06 | AA4: Taux de l'emprunt : | AB4: 0
C5: Durée de l'emprunt : | D5: 10 | E5: ans | K5: Durée de l'emprunt : | L5: 10 | M5: ans | S5: Durée de l'emprunt : | T5: 10 | U5: ans | AA5: Durée de l'emprunt : | AB5: 0 | AC5: ans
C6: Versement : | D6: =-PMT(D4/12,D5*12,D3) -> 658.24056 | E6: par mois | K6: Versement : | L6: =-PMT(L4/12,L5*12,L3) -> 2008.7837 | M6: par mois | S6: Versement : | T6: =-PMT(T4/12,T5*12,T3) -> 7438.3736 | U6: par mois | AA6: Versement : | AB6: =-PMT(AB4/12,AB5*12,AB3) -> #NUM! | AC6: par mois
B9: Date | C9: portion du capital | D9: portion intérêt | E9: capital cumulé | F9: intérêt cumulé | G9: solde | J9: Date | K9: portion du capital | L9: portion intérêt | M9: capital cumulé | N9: intérêt cumulé | O9: solde | R9: Date | S9: portion du capital | T9: portion intérêt | U9: capital cumulé | V9: intérêt cumulé | W9: solde | Z9: Date | AA9: portion du capital | AB9: portion intérêt | AC9: capital cumulé | AD9: intérêt cumulé | AE9: solde
B10: M1 | C10: =D6-D10 -> 361.79056 | D10: =D4/12*D3 -> 296.45 | E10: =C10 -> 361.79056 | F10: =D10 -> 296.45 | G10: =D3-C10 -> 58928.209 | J10: =B10 -> M1 | K10: =L6-L10 -> 742.05871 | L10: =L4/12*L3 -> 1266.725 | M10: =K10 -> 742.05871 | N10: =L10 -> 1266.725 | O10: =L3-K10 -> 151264.94 | S10: =T6-T10 -> 4088.3736 | T10: =T4/12*T3 -> 3350 | U10: =S10 -> 4088.3736 | V10: =T10 -> 3350 | W10: =T3-S10 -> 665911.63 | AA10: =AB6-AB10 -> #NUM! | AB10: =AB4/12*AB3 -> 0 | AC10: =AA10 -> #NUM! | AD10: =AB10 -> 0 | AE10: =AB3-AA10 -> #NUM!
B11: M2 | C11: =$D$6-D11 -> 363.59951 | D11: =$D$4/12*G10 -> 294.64105 | E11: =E10+C11 -> 725.39006 | F11: =F10+D11 -> 591.09105 | G11: =G10-C11 -> 58564.61 | J11: =B11 -> M2 | K11: =$L$6-L11 -> 748.24253 | L11: =$L$4/12*O10 -> 1260.5412 | M11: =M10+K11 -> 1490.3012 | N11: =N10+L11 -> 2527.2662 | O11: =O10-K11 -> 150516.7 | S11: =$T$6-T11 -> 4108.8155 | T11: =$T$4/12*W10 -> 3329.5581 | U11: =U10+S11 -> 8197.1891 | V11: =V10+T11 -> 6679.5581 | W11: =W10-S11 -> 661802.81 | AA11: =$AB$6-AB11 -> #NUM! | AB11: =$AB$4/12*AE10 -> #NUM! | AC11: =AC10+AA11 -> #NUM! | AD11: =AD10+AB11 -> #NUM! | AE11: =AE10-AA11 -> #NUM!
B12: M3 | C12: =$D$6-D12 -> 365.41751 | D12: =$D$4/12*G11 -> 292.82305 | E12: =E11+C12 -> 1090.8076 | F12: =F11+D12 -> 883.9141 | G12: =G11-C12 -> 58199.192 | J12: =B12 -> M3 | K12: =$L$6-L12 -> 754.47788 | L12: =$L$4/12*O11 -> 1254.3058 | M12: =M11+K12 -> 2244.7791 | N12: =N11+L12 -> 3781.572 | O12: =O11-K12 -> 149762.22 | S12: =$T$6-T12 -> 1923.3502 | T12: =$L$4/12*W11 -> 5515.0234 | U12: =U11+S12 -> 10120.539 | V12: =V11+T12 -> 12194.582 | W12: =W11-S12 -> 659879.46 | AA12: =$T$6-AB12 -> #NUM! | AB12: =$AB$4/12*AE11 -> #NUM! | AC12: =AC11+AA12 -> #NUM! | AD12: =AD11+AB12 -> #NUM! | AE12: =AE11-AA12 -> #NUM!
B13: M4 | C13: =$D$6-D13 -> 367.24459 | D13: =$D$4/12*G12 -> 290.99596 | E13: =E12+C13 -> 1458.0522 | F13: =F12+D13 -> 1174.9101 | G13: =G12-C13 -> 57831.948 | J13: =B13 -> M4 | K13: =$L$6-L13 -> 760.7652 | L13: =$L$4/12*O12 -> 1248.0185 | M13: =M12+K13 -> 3005.5443 | N13: =N12+L13 -> 5029.5905 | O13: =O12-K13 -> 149001.46 | S13: =$T$6-T13 -> 1939.3781 | T13: =$L$4/12*W12 -> 5498.9955 | U13: =U12+S13 -> 12059.917 | V13: =V12+T13 -> 17693.577 | W13: =W12-S13 -> 657940.08 | AA13: =$T$6-AB13 -> #NUM! | AB13: =$AB$4/12*AE12 -> #NUM! | AC13: =AC12+AA13 -> #NUM! | AD13: =AD12+AB13 -> #NUM! | AE13: =AE12-AA13 -> #NUM!
B14: M5 | C14: =$D$6-D14 -> 369.08082 | D14: =$D$4/12*G13 -> 289.15974 | E14: =E13+C14 -> 1827.133 | F14: =F13+D14 -> 1464.0698 | G14: =G13-C14 -> 57462.867 | J14: =B14 -> M5 | K14: =$L$6-L14 -> 767.10491 | L14: =$L$4/12*O13 -> 1241.6788 | M14: =M13+K14 -> 3772.6492 | N14: =N13+L14 -> 6271.2693 | O14: =O13-K14 -> 148234.35 | S14: =$T$6-T14 -> 1955.5396 | T14: =$L$4/12*W13 -> 5482.834 | U14: =U13+S14 -> 14015.457 | V14: =V13+T14 -> 23176.411 | W14: =W13-S14 -> 655984.54 | AA14: =$T$6-AB14 -> #NUM! | AB14: =$AB$4/12*AE13 -> #NUM! | AC14: =AC13+AA14 -> #NUM! | AD14: =AD13+AB14 -> #NUM! | AE14: =AE13-AA14 -> #NUM!
B15: M6 | C15: =$D$6-D15 -> 370.92622 | D15: =$D$4/12*G14 -> 287.31434 | E15: =E14+C15 -> 2198.0592 | F15: =F14+D15 -> 1751.3841 | G15: =G14-C15 -> 57091.941 | J15: =B15 -> M6 | K15: =$L$6-L15 -> 773.49745 | L15: =$L$4/12*O14 -> 1235.2863 | M15: =M14+K15 -> 4546.1467 | N15: =N14+L15 -> 7506.5556 | O15: =O14-K15 -> 147460.85 | S15: =$T$6-T15 -> 1971.8358 | T15: =$L$4/12*W14 -> 5466.5379 | U15: =U14+S15 -> 15987.293 | V15: =V14+T15 -> 28642.949 | W15: =W14-S15 -> 654012.71 | AA15: =$T$6-AB15 -> #NUM! | AB15: =$AB$4/12*AE14 -> #NUM! | AC15: =AC14+AA15 -> #NUM! | AD15: =AD14+AB15 -> #NUM! | AE15: =AE14-AA15 -> #NUM!
B16: M7 | C16: =$D$6-D16 -> 372.78085 | D16: =$D$4/12*G15 -> 285.4597 | E16: =E15+C16 -> 2570.8401 | F16: =F15+D16 -> 2036.8438 | G16: =G15-C16 -> 56719.16 | J16: =B16 -> M7 | K16: =$L$6-L16 -> 779.94326 | L16: =$L$4/12*O15 -> 1228.8404 | M16: =M15+K16 -> 5326.0899 | N16: =N15+L16 -> 8735.396 | O16: =O15-K16 -> 146680.91 | S16: =$T$6-T16 -> 1988.2677 | T16: =$L$4/12*W15 -> 5450.1059 | U16: =U15+S16 -> 17975.561 | V16: =V15+T16 -> 34093.055 | W16: =W15-S16 -> 652024.44 | AA16: =$T$6-AB16 -> #NUM! | AB16: =$AB$4/12*AE15 -> #NUM! | AC16: =AC15+AA16 -> #NUM! | AD16: =AD15+AB16 -> #NUM! | AE16: =AE15-AA16 -> #NUM!
B17: M8 | C17: =$D$6-D17 -> 374.64476 | D17: =$D$4/12*G16 -> 283.5958 | E17: =E16+C17 -> 2945.4848 | F17: =F16+D17 -> 2320.4396 | G17: =G16-C17 -> 56344.515 | J17: =B17 -> M8 | K17: =$L$6-L17 -> 786.44279 | L17: =$L$4/12*O16 -> 1222.3409 | M17: =M16+K17 -> 6112.5327 | N17: =N16+L17 -> 9957.7369 | O17: =O16-K17 -> 145894.47 | S17: =$T$6-T17 -> 2004.8366 | T17: =$L$4/12*W16 -> 5433.537 | U17: =U16+S17 -> 19980.397 | V17: =V16+T17 -> 39526.592 | W17: =W16-S17 -> 650019.6 | AA17: =$T$6-AB17 -> #NUM! | AB17: =$AB$4/12*AE16 -> #NUM! | AC17: =AC16+AA17 -> #NUM! | AD17: =AD16+AB17 -> #NUM! | AE17: =AE16-AA17 -> #NUM!
B18: M9 | C18: =$D$6-D18 -> 376.51798 | D18: =$D$4/12*G17 -> 281.72258 | E18: =E17+C18 -> 3322.0028 | F18: =F17+D18 -> 2602.1622 | G18: =G17-C18 -> 55967.997 | J18: =B18 -> M9 | K18: =$L$6-L18 -> 792.99648 | L18: =$L$4/12*O17 -> 1215.7872 | M18: =M17+K18 -> 6905.5292 | N18: =N17+L18 -> 11173.524 | O18: =O17-K18 -> 145101.47 | S18: =$T$6-T18 -> 2021.5436 | T18: =$L$4/12*W17 -> 5416.83 | U18: =U17+S18 -> 22001.941 | V18: =V17+T18 -> 44943.422 | W18: =W17-S18 -> 647998.06 | AA18: =$T$6-AB18 -> #NUM! | AB18: =$AB$4/12*AE17 -> #NUM! | AC18: =AC17+AA18 -> #NUM! | AD18: =AD17+AB18 -> #NUM! | AE18: =AE17-AA18 -> #NUM!
B19: M10 | C19: =$D$6-D19 -> 378.40057 | D19: =$D$4/12*G18 -> 279.83999 | E19: =E18+C19 -> 3700.4034 | F19: =F18+D19 -> 2882.0022 | G19: =G18-C19 -> 55589.597 | J19: =B19 -> M10 | K19: =$L$6-L19 -> 799.60478 | L19: =$L$4/12*O18 -> 1209.1789 | M19: =M18+K19 -> 7705.134 | N19: =N18+L19 -> 12382.703 | O19: =O18-K19 -> 144301.87 | S19: =$T$6-T19 -> 2038.3898 | T19: =$L$4/12*W18 -> 5399.9838 | U19: =U18+S19 -> 24040.331 | V19: =V18+T19 -> 50343.406 | W19: =W18-S19 -> 645959.67 | AA19: =$T$6-AB19 -> #NUM! | AB19: =$AB$4/12*AE18 -> #NUM! | AC19: =AC18+AA19 -> #NUM! | AD19: =AD18+AB19 -> #NUM! | AE19: =AE18-AA19 -> #NUM!
B20: M11 | C20: =$D$6-D20 -> 380.29257 | D20: =$D$4/12*G19 -> 277.94798 | E20: =E19+C20 -> 4080.6959 | F20: =F19+D20 -> 3159.9502 | G20: =G19-C20 -> 55209.304 | J20: =B20 -> M11 | K20: =$L$6-L20 -> 806.26816 | L20: =$L$4/12*O19 -> 1202.5156 | M20: =M19+K20 -> 8511.4021 | N20: =N19+L20 -> 13585.219 | O20: =O19-K20 -> 143495.6 | S20: =$T$6-T20 -> 2055.3764 | T20: =$L$4/12*W19 -> 5382.9972 | U20: =U19+S20 -> 26095.707 | V20: =V19+T20 -> 55726.403 | W20: =W19-S20 -> 643904.29 | AA20: =$T$6-AB20 -> #NUM! | AB20: =$AB$4/12*AE19 -> #NUM! | AC20: =AC19+AA20 -> #NUM! | AD20: =AD19+AB20 -> #NUM! | AE20: =AE19-AA20 -> #NUM!
B21: M12 | C21: =$D$6-D21 -> 382.19404 | D21: =$D$4/12*G20 -> 276.04652 | E21: =E20+C21 -> 4462.89 | F21: =F20+D21 -> 3435.9967 | G21: =G20-C21 -> 54827.11 | J21: =B21 -> M12 | K21: =$L$6-L21 -> 812.98706 | L21: =$L$4/12*O20 -> 1195.7966 | M21: =M20+K21 -> 9324.3892 | N21: =N20+L21 -> 14781.015 | O21: =O20-K21 -> 142682.61 | S21: =$T$6-T21 -> 2072.5045 | T21: =$L$4/12*W20 -> 5365.8691 | U21: =U20+S21 -> 28168.212 | V21: =V20+T21 -> 61092.272 | W21: =W20-S21 -> 641831.79 | AA21: =$T$6-AB21 -> #NUM! | AB21: =$AB$4/12*AE20 -> #NUM! | AC21: =AC20+AA21 -> #NUM! | AD21: =AD20+AB21 -> #NUM! | AE21: =AE20-AA21 -> #NUM!
B22: M13 | C22: =$D$6-D22 -> 384.10501 | D22: =$D$4/12*G21 -> 274.13555 | E22: =E21+C22 -> 4846.995 | F22: =F21+D22 -> 3710.1323 | G22: =G21-C22 -> 54443.005 | J22: =B22 -> M13 | K22: =$L$6-L22 -> 819.76195 | L22: =$L$4/12*O21 -> 1189.0218 | M22: =M21+K22 -> 10144.151 | N22: =N21+L22 -> 15970.037 | O22: =O21-K22 -> 141862.85 | S22: =$T$6-T22 -> 2089.7754 | T22: =$L$4/12*W21 -> 5348.5982 | U22: =U21+S22 -> 30257.987 | V22: =V21+T22 -> 66440.87 | W22: =W21-S22 -> 639742.01 | AA22: =$T$6-AB22 -> #NUM! | AB22: =$AB$4/12*AE21 -> #NUM! | AC22: =AC21+AA22 -> #NUM! | AD22: =AD21+AB22 -> #NUM! | AE22: =AE21-AA22 -> #NUM!
B23: M14 | C23: =$D$6-D23 -> 386.02553 | D23: =$D$4/12*G22 -> 272.21503 | E23: =E22+C23 -> 5233.0205 | F23: =F22+D23 -> 3982.3473 | G23: =G22-C23 -> 54056.979 | J23: =B23 -> M14 | K23: =$L$6-L23 -> 826.5933 | L23: =$L$4/12*O22 -> 1182.1904 | M23: =M22+K23 -> 10970.744 | N23: =N22+L23 -> 17152.227 | O23: =O22-K23 -> 141036.26 | S23: =$T$6-T23 -> 2107.1902 | T23: =$L$4/12*W22 -> 5331.1834 | U23: =U22+S23 -> 32365.177 | V23: =V22+T23 -> 71772.054 | W23: =W22-S23 -> 637634.82 | AA23: =$T$6-AB23 -> #NUM! | AB23: =$AB$4/12*AE22 -> #NUM! | AC23: =AC22+AA23 -> #NUM! | AD23: =AD22+AB23 -> #NUM! | AE23: =AE22-AA23 -> #NUM!
... B36: M27 | C36: =$D$6-D36 -> 411.88391 | D36: =$D$4/12*G35 -> 246.35664 | E36: =E35+C36 -> 10430.556 | F36: =F35+D36 -> 7341.9394 | G36: =G35-C36 -> 48859.444 | J36: =B36 -> M27 | K36: =$L$6-L36 -> 920.75799 | L36: =$L$4/12*O35 -> 1088.0257 | M36: =M35+K36 -> 22364.672 | N36: =N35+L36 -> 31872.488 | O36: =O35-K36 -> 129642.33 | S36: =$T$6-T36 -> 2347.2392 | T36: =$L$4/12*W35 -> 5091.1344 | U36: =U35+S36 -> 61411.108 | V36: =V35+T36 -> 139424.98 | W36: =W35-S36 -> 608588.89 | AA36: =$T$6-AB36 -> #NUM! | AB36: =$AB$4/12*AE35 -> #NUM! | AC36: =AC35+AA36 -> #NUM! | AD36: =AD35+AB36 -> #NUM! | AE36: =AE35-AA36 -> #NUM!
B37: M28 | C37: =$D$6-D37 -> #VALUE! | D37: =B6*B37/I5 -> #VALUE! | E37: =E36+C37 -> #VALUE! | F37: =F36+D37 -> #VALUE! | G37: =G36-C37 -> #VALUE! | J37: =B37 -> M28 | K37: =$L$6-L37 -> 928.43097 | L37: =$L$4/12*O36 -> 1080.3527 | M37: =M36+K37 -> 23293.103 | N37: =N36+L37 -> 32952.841 | O37: =O36-K37 -> 128713.9 | S37: =$T$6-T37 -> 2366.7995 | T37: =$L$4/12*W36 -> 5071.5741 | U37: =U36+S37 -> 63777.908 | V37: =V36+T37 -> 144496.55 | W37: =W36-S37 -> 606222.09 | AA37: =$T$6-AB37 -> #NUM! | AB37: =$AB$4/12*AE36 -> #NUM! | AC37: =AC36+AA37 -> #NUM! | AD37: =AD36+AB37 -> #NUM! | AE37: =AE36-AA37 -> #NUM!
B38: M29 | C38: =$D$6-D38 -> #VALUE! | D38: =H14*B38/I5 -> #VALUE! | E38: =E37+C38 -> #VALUE! | F38: =F37+D38 -> #VALUE! | G38: =G37-C38 -> #VALUE! | J38: =B38 -> M29 | K38: =$L$6-L38 -> 936.1679 | L38: =$L$4/12*O37 -> 1072.6158 | M38: =M37+K38 -> 24229.271 | N38: =N37+L38 -> 34025.457 | O38: =O37-K38 -> 127777.73 | S38: =$T$6-T38 -> 2386.5229 | T38: =$L$4/12*W37 -> 5051.8508 | U38: =U37+S38 -> 66164.431 | V38: =V37+T38 -> 149548.4 | W38: =W37-S38 -> 603835.57 | AA38: =$T$6-AB38 -> #NUM! | AB38: =$AB$4/12*AE37 -> #NUM! | AC38: =AC37+AA38 -> #NUM! | AD38: =AD37+AB38 -> #NUM! | AE38: =AE37-AA38 -> #NUM!
B39: M30 | C39: =$D$6-D39 -> #VALUE! | D39: #VALUE! | E39: =E38+C39 -> #VALUE! | F39: =F38+D39 -> #VALUE! | G39: =G38-C39 -> #VALUE! | J39: =B39 -> M30 | K39: =$L$6-L39 -> 943.9693 | L39: =$L$4/12*O38 -> 1064.8144 | M39: =M38+K39 -> 25173.24 | N39: =N38+L39 -> 35090.271 | O39: =O38-K39 -> 126833.76 | S39: =$T$6-T39 -> 2406.4106 | T39: =$L$4/12*W38 -> 5031.9631 | U39: =U38+S39 -> 68570.841 | V39: =V38+T39 -> 154580.37 | W39: =W38-S39 -> 601429.16 | AA39: =$T$6-AB39 -> #NUM! | AB39: =$AB$4/12*AE38 -> #NUM! | AC39: =AC38+AA39 -> #NUM! | AD39: =AD38+AB39 -> #NUM! | AE39: =AE38-AA39 -> #NUM!
B40: M31 | C40: =$D$6-D40 -> #VALUE! | D40: =$D$4/12*G39 -> #VALUE! | E40: =E39+C40 -> #VALUE! | F40: =F39+D40 -> #VALUE! | G40: =G39-C40 -> #VALUE! | J40: =B40 -> M31 | K40: =$L$6-L40 -> 951.83571 | L40: =$L$4/12*O39 -> 1056.948 | M40: =M39+K40 -> 26125.076 | N40: =N39+L40 -> 36147.219 | O40: =O39-K40 -> 125881.92 | S40: =$T$6-T40 -> 2426.464 | T40: =$L$4/12*W39 -> 5011.9097 | U40: =U39+S40 -> 70997.305 | V40: =V39+T40 -> 159592.28 | W40: =W39-S40 -> 599002.69 | AA40: =$T$6-AB40 -> #NUM! | AB40: =$AB$4/12*AE39 -> #NUM! | AC40: =AC39+AA40 -> #NUM! | AD40: =AD39+AB40 -> #NUM! | AE40: =AE39-AA40 -> #NUM!
B41: M32 | C41: =$D$6-D41 -> #VALUE! | D41: =$D$4/12*G40 -> #VALUE! | E41: =E40+C41 -> #VALUE! | F41: =F40+D41 -> #VALUE! | G41: =G40-C41 -> #VALUE! | J41: =B41 -> M32 | K41: =$L$6-L41 -> 959.76767 | L41: =$L$4/12*O40 -> 1049.016 | M41: =M40+K41 -> 27084.843 | N41: =N40+L41 -> 37196.235 | O41: =O40-K41 -> 124922.16 | S41: =$T$6-T41 -> 2446.6845 | T41: =$L$4/12*W40 -> 4991.6891 | U41: =U40+S41 -> 73443.99 | V41: =V40+T41 -> 164583.97 | W41: =W40-S41 -> 596556.01 | AA41: =$T$6-AB41 -> #NUM! | AB41: =$AB$4/12*AE40 -> #NUM! | AC41: =AC40+AA41 -> #NUM! | AD41: =AD40+AB41 -> #NUM! | AE41: =AE40-AA41 -> #NUM!
B42: M33 | C42: =$D$6-D42 -> #VALUE! | D42: =$D$4/12*G41 -> #VALUE! | E42: =E41+C42 -> #VALUE! | F42: =F41+D42 -> #VALUE! | G42: =G41-C42 -> #VALUE! | J42: =B42 -> M33 | K42: =$L$6-L42 -> 967.76574 | L42: =$L$4/12*O41 -> 1041.018 | M42: =M41+K42 -> 28052.609 | N42: =N41+L42 -> 38237.253 | O42: =O41-K42 -> 123954.39 | S42: =$T$6-T42 -> 2467.0735 | T42: =$L$4/12*W41 -> 4971.3001 | U42: =U41+S42 -> 75911.063 | V42: =V41+T42 -> 169555.27 | W42: =W41-S42 -> 594088.94 | AA42: =$T$6-AB42 -> #NUM! | AB42: =$AB$4/12*AE41 -> #NUM! | AC42: =AC41+AA42 -> #NUM! | AD42: =AD41+AB42 -> #NUM! | AE42: =AE41-AA42 -> #NUM!
B43: M34 | C43: =$D$6-D43 -> #VALUE! | D43: =$D$4/12*G42 -> #VALUE! | E43: =E42+C43 -> #VALUE! | F43: =F42+D43 -> #VALUE! | G43: =G42-C43 -> #VALUE! | J43: =B43 -> M34 | K43: =$L$6-L43 -> 975.83045 | L43: =$L$4/12*O42 -> 1032.9533 | M43: =M42+K43 -> 29028.44 | N43: =N42+L43 -> 39270.206 | O43: =O42-K43 -> 122978.56 | S43: =$T$6-T43 -> 2487.6325 | T43: =$L$4/12*W42 -> 4950.7411 | U43: =U42+S43 -> 78398.696 | V43: =V42+T43 -> 174506.01 | W43: =W42-S43 -> 591601.3 | AA43: =$T$6-AB43 -> #NUM! | AB43: =$AB$4/12*AE42 -> #NUM! | AC43: =AC42+AA43 -> #NUM! | AD43: =AD42+AB43 -> #NUM! | AE43: =AE42-AA43 -> #NUM!
B44: M35 | C44: =$D$6-D44 -> #VALUE! | D44: =$D$4/12*G43 -> #VALUE! | E44: =E43+C44 -> #VALUE! | F44: =F43+D44 -> #VALUE! | G44: =G43-C44 -> #VALUE! | J44: =B44 -> M35 | K44: =$L$6-L44 -> 983.96237 | L44: =$L$4/12*O43 -> 1024.8213 | M44: =M43+K44 -> 30012.402 | N44: =N43+L44 -> 40295.028 | O44: =O43-K44 -> 121994.6 | S44: =$T$6-T44 -> 2508.3628 | T44: =$L$4/12*W43 -> 4930.0109 | U44: =U43+S44 -> 80907.059 | V44: =V43+T44 -> 179436.02 | W44: =W43-S44 -> 589092.94 | AA44: =$T$6-AB44 -> #NUM! | AB44: =$AB$4/12*AE43 -> #NUM! | AC44: =AC43+AA44 -> #NUM! | AD44: =AD43+AB44 -> #NUM! | AE44: =AE43-AA44 -> #NUM!
B45: M36 | C45: =$D$6-D45 -> #VALUE! | D45: =$D$4/12*G44 -> #VALUE! | E45: =E44+C45 -> #VALUE! | F45: =F44+D45 -> #VALUE! | G45: =G44-C45 -> #VALUE! | J45: =B45 -> M36 | K45: =$L$6-L45 -> 992.16206 | L45: =$L$4/12*O44 -> 1016.6216 | M45: =M44+K45 -> 31004.564 | N45: =N44+L45 -> 41311.649 | O45: =O44-K45 -> 121002.44 | S45: =$T$6-T45 -> 2529.2658 | T45: =$L$4/12*W44 -> 4909.1078 | U45: =U44+S45 -> 83436.324 | V45: =V44+T45 -> 184345.13 | W45: =W44-S45 -> 586563.68 | AA45: =$T$6-AB45 -> #NUM! | AB45: =$AB$4/12*AE44 -> #NUM! | AC45: =AC44+AA45 -> #NUM! | AD45: =AD44+AB45 -> #NUM! | AE45: =AE44-AA45 -> #NUM!
B46: M37 | C46: =$D$6-D46 -> #VALUE! | D46: =$D$4/12*G45 -> #VALUE! | E46: =E45+C46 -> #VALUE! | F46: =F45+D46 -> #VALUE! | G46: =G45-C46 -> #VALUE! | J46: =B46 -> M37 | K46: =$L$6-L46 -> 1000.4301 | L46: =$L$4/12*O45 -> 1008.3536 | M46: =M45+K46 -> 32004.994 | N46: =N45+L46 -> 42320.003 | O46: =O45-K46 -> 120002.01 | S46: =$T$6-T46 -> 2550.343 | T46: =$L$4/12*W45 -> 4888.0306 | U46: =U45+S46 -> 85986.667 | V46: =V45+T46 -> 189233.16 | W46: =W45-S46 -> 584013.33 | AA46: =$T$6-AB46 -> #NUM! | AB46: =$AB$4/12*AE45 -> #NUM! | AC46: =AC45+AA46 -> #NUM! | AD46: =AD45+AB46 -> #NUM! | AE46: =AE45-AA46 -> #NUM!
B47: M38 | C47: =$D$6-D47 -> #VALUE! | D47: =$D$4/12*G46 -> #VALUE! | E47: =E46+C47 -> #VALUE! | F47: =F46+D47 -> #VALUE! | G47: =G46-C47 -> #VALUE! | J47: =B47 -> M38 | K47: =$L$6-L47 -> 1008.767 | L47: =$L$4/12*O46 -> 1000.0167 | M47: =M46+K47 -> 33013.761 | N47: =N46+L47 -> 43320.02 | O47: =O46-K47 -> 118993.24 | S47: =$T$6-T47 -> 2571.5959 | T47: =$L$4/12*W46 -> 4866.7778 | U47: =U46+S47 -> 88558.263 | V47: =V46+T47 -> 194099.93 | W47: =W46-S47 -> 581441.74 | AA47: =$T$6-AB47 -> #NUM! | AB47: =$AB$4/12*AE46 -> #NUM! | AC47: =AC46+AA47 -> #NUM! | AD47: =AD46+AB47 -> #NUM! | AE47: =AE46-AA47 -> #NUM!
B48: M39 | C48: =$D$6-D48 -> #VALUE! | D48: =$D$4/12*G47 -> #VALUE! | E48: =E47+C48 -> #VALUE! | F48: =F47+D48 -> #VALUE! | G48: =G47-C48 -> #VALUE! | J48: =B48 -> M39 | K48: =$L$6-L48 -> 1017.1734 | L48: =$L$4/12*O47 -> 991.61032 | M48: =M47+K48 -> 34030.935 | N48: =N47+L48 -> 44311.63 | O48: =O47-K48 -> 117976.07 | S48: =$T$6-T48 -> 2593.0258 | T48: =$L$4/12*W47 -> 4845.3478 | U48: =U47+S48 -> 91151.289 | V48: =V47+T48 -> 198945.28 | W48: =W47-S48 -> 578848.71 | AA48: =$T$6-AB48 -> #NUM! | AB48: =$AB$4/12*AE47 -> #NUM! | AC48: =AC47+AA48 -> #NUM! | AD48: =AD47+AB48 -> #NUM! | AE48: =AE47-AA48 -> #NUM!
B49: M40 | C49: =$D$6-D49 -> #VALUE! | D49: =$D$4/12*G48 -> #VALUE! | E49: =E48+C49 -> #VALUE! | F49: =F48+D49 -> #VALUE! | G49: =G48-C49 -> #VALUE! | J49: =B49 -> M40 | K49: =$L$6-L49 -> 1025.6498 | L49: =$L$4/12*O48 -> 983.13388 | M49: =M48+K49 -> 35056.584 | N49: =N48+L49 -> 45294.764 | O49: =O48-K49 -> 116950.42 | S49: =$T$6-T49 -> 2614.6344 | T49: =$L$4/12*W48 -> 4823.7393 | U49: =U48+S49 -> 93765.924 | V49: =V48+T49 -> 203769.02 | W49: =W48-S49 -> 576234.08 | AA49: =$T$6-AB49 -> #NUM! | AB49: =$AB$4/12*AE48 -> #NUM! | AC49: =AC48+AA49 -> #NUM! | AD49: =AD48+AB49 -> #NUM! | AE49: =AE48-AA49 -> #NUM!
B50: M41 | C50: =$D$6-D50 -> #VALUE! | D50: =$D$4/12*G49 -> #VALUE! | E50: =E49+C50 -> #VALUE! | F50: =F49+D50 -> #VALUE! | G50: =G49-C50 -> #VALUE! | J50: =B50 -> M41 | K50: =$L$6-L50 -> 1034.1969 | L50: =$L$4/12*O49 -> 974.5868 | M50: =M49+K50 -> 36090.781 | N50: =N49+L50 -> 46269.351 | O50: =O49-K50 -> 115916.22 | S50: =$T$6-T50 -> 2636.423 | T50: =$L$4/12*W49 -> 4801.9506 | U50: =U49+S50 -> 96402.347 | V50: =V49+T50 -> 208570.97 | W50: =W49-S50 -> 573597.65 | AA50: =$T$6-AB50 -> #NUM! | AB50: =$AB$4/12*AE49 -> #NUM! | AC50: =AC49+AA50 -> #NUM! | AD50: =AD49+AB50 -> #NUM! | AE50: =AE49-AA50 -> #NUM!
B51: M42 | C51: =$D$6-D51 -> #VALUE! | D51: =$D$4/12*G50 -> #VALUE! | E51: =E50+C51 -> #VALUE! | F51: =F50+D51 -> #VALUE! | G51: =G50-C51 -> #VALUE! | J51: =B51 -> M42 | K51: =$L$6-L51 -> 1042.8152 | L51: =$L$4/12*O50 -> 965.96849 | M51: =M50+K51 -> 37133.596 | N51: =N50+L51 -> 47235.319 | O51: =O50-K51 -> 114873.4 | S51: =$T$6-T51 -> 2658.3932 | T51: =$L$4/12*W50 -> 4779.9804 | U51: =U50+S51 -> 99060.74 | V51: =V50+T51 -> 213350.95 | W51: =W50-S51 -> 570939.26 | AA51: =$T$6-AB51 -> #NUM! | AB51: =$AB$4/12*AE50 -> #NUM! | AC51: =AC50+AA51 -> #NUM! | AD51: =AD50+AB51 -> #NUM! | AE51: =AE50-AA51 -> #NUM!
B52: M43 | C52: =$D$6-D52 -> #VALUE! | D52: =$D$4/12*G51 -> #VALUE! | E52: =E51+C52 -> #VALUE! | F52: =F51+D52 -> #VALUE! | G52: =G51-C52 -> #VALUE! | J52: =B52 -> M43 | K52: =$L$6-L52 -> 1051.5053 | L52: =$L$4/12*O51 -> 957.27836 | M52: =M51+K52 -> 38185.102 | N52: =N51+L52 -> 48192.598 | O52: =O51-K52 -> 113821.9 | S52: =$T$6-T52 -> 2680.5465 | T52: =$L$4/12*W51 -> 4757.8272 | U52: =U51+S52 -> 101741.29 | V52: =V51+T52 -> 218108.78 | W52: =W51-S52 -> 568258.71 | AA52: =$T$6-AB52 -> #NUM! | AB52: =$AB$4/12*AE51 -> #NUM! | AC52: =AC51+AA52 -> #NUM! | AD52: =AD51+AB52 -> #NUM! | AE52: =AE51-AA52 -> #NUM!
B53: M44 | C53: =$D$6-D53 -> #VALUE! | D53: =B44*B53/I5 -> #VALUE! | E53: =E52+C53 -> #VALUE! | F53: =F52+D53 -> #VALUE! | G53: =G52-C53 -> #VALUE! | J53: =B53 -> M44 | K53: =$L$6-L53 -> 1060.2679 | L53: =$L$4/12*O52 -> 948.51582 | M53: =M52+K53 -> 39245.37 | N53: =N52+L53 -> 49141.113 | O53: =O52-K53 -> 112761.63 | S53: =$T$6-T53 -> 2702.8843 | T53: =$L$4/12*W52 -> 4735.4893 | U53: =U52+S53 -> 104444.17 | V53: =V52+T53 -> 222844.27 | W53: =W52-S53 -> 565555.83 | AA53: =$T$6-AB53 -> #NUM! | AB53: =$AB$4/12*AE52 -> #NUM! | AC53: =AC52+AA53 -> #NUM! | AD53: =AD52+AB53 -> #NUM! | AE53: =AE52-AA53 -> #NUM!
B54: M45 | C54: =$D$6-D54 -> #VALUE! | D54: =$D$4/12*G53 -> #VALUE! | E54: =E53+C54 -> #VALUE! | F54: =F53+D54 -> #VALUE! | G54: =G53-C54 -> #VALUE! | J54: =B54 -> M45 | K54: =$L$6-L54 -> 1069.1035 | L54: =$L$4/12*O53 -> 939.68025 | M54: =M53+K54 -> 40314.473 | N54: =N53+L54 -> 50080.794 | O54: =O53-K54 -> 111692.53 | S54: =$T$6-T54 -> 2725.4084 | T54: =$L$4/12*W53 -> 4712.9652 | U54: =U53+S54 -> 107169.58 | V54: =V53+T54 -> 227557.23 | W54: =W53-S54 -> 562830.42 | AA54: =$T$6-AB54 -> #NUM! | AB54: =$AB$4/12*AE53 -> #NUM! | AC54: =AC53+AA54 -> #NUM! | AD54: =AD53+AB54 -> #NUM! | AE54: =AE53-AA54 -> #NUM!
B55: M46 | C55: =$D$6-D55 -> #VALUE! | D55: =$D$4/12*G54 -> #VALUE! | E55: =E54+C55 -> #VALUE! | F55: =F54+D55 -> #VALUE! | G55: =G54-C55 -> #VALUE! | J55: =B55 -> M46 | K55: =$L$6-L55 -> 1078.0126 | L55: =$L$4/12*O54 -> 930.77106 | M55: =M54+K55 -> 41392.486 | N55: =N54+L55 -> 51011.565 | O55: =O54-K55 -> 110614.51 | S55: =$T$6-T55 -> 2748.1201 | T55: =$L$4/12*W54 -> 4690.2535 | U55: =U54+S55 -> 109917.7 | V55: =V54+T55 -> 232247.49 | W55: =W54-S55 -> 560082.3 | AA55: =$T$6-AB55 -> #NUM! | AB55: =$AB$4/12*AE54 -> #NUM! | AC55: =AC54+AA55 -> #NUM! | AD55: =AD54+AB55 -> #NUM! | AE55: =AE54-AA55 -> #NUM!
B56: M47 | C56: =$D$6-D56 -> #VALUE! | D56: =$D$4/12*G55 -> #VALUE! | E56: =E55+C56 -> #VALUE! | F56: =F55+D56 -> #VALUE! | G56: =G55-C56 -> #VALUE! | J56: =B56 -> M47 | K56: =$L$6-L56 -> 1086.9961 | L56: =$L$4/12*O55 -> 921.78762 | M56: =M55+K56 -> 42479.482 | N56: =N55+L56 -> 51933.352 | O56: =O55-K56 -> 109527.52 | S56: =$T$6-T56 -> 2771.0211 | T56: =$L$4/12*W55 -> 4667.3525 | U56: =U55+S56 -> 112688.72 | V56: =V55+T56 -> 236914.84 | W56: =W55-S56 -> 557311.28 | AA56: =$T$6-AB56 -> #NUM! | AB56: =$AB$4/12*AE55 -> #NUM! | AC56: =AC55+AA56 -> #NUM! | AD56: =AD55+AB56 -> #NUM! | AE56: =AE55-AA56 -> #NUM!
B57: M48 | C57: =$D$6-D57 -> #VALUE! | D57: =$D$4/12*G56 -> #VALUE! | E57: =E56+C57 -> #VALUE! | F57: =F56+D57 -> #VALUE! | G57: =G56-C57 -> #VALUE! | J57: =B57 -> M48 | K57: =$L$6-L57 -> 1096.0544 | L57: =$L$4/12*O56 -> 912.72932 | M57: =M56+K57 -> 43575.536 | N57: =N56+L57 -> 52846.082 | O57: =O56-K57 -> 108431.46 | S57: =$T$6-T57 -> 2794.113 | T57: =$L$4/12*W56 -> 4644.2607 | U57: =U56+S57 -> 115482.83 | V57: =V56+T57 -> 241559.1 | W57: =W56-S57 -> 554517.17 | AA57: =$T$6-AB57 -> #NUM! | AB57: =$AB$4/12*AE56 -> #NUM! | AC57: =AC56+AA57 -> #NUM! | AD57: =AD56+AB57 -> #NUM! | AE57: =AE56-AA57 -> #NUM!
B58: M49 | C58: =$D$6-D58 -> #VALUE! | D58: =$D$4/12*G57 -> #VALUE! | E58: =E57+C58 -> #VALUE! | F58: =F57+D58 -> #VALUE! | G58: =G57-C58 -> #VALUE! | J58: =B58 -> M49 | K58: =$L$6-L58 -> 1105.1882 | L58: =$L$4/12*O57 -> 903.59553 | M58: =M57+K58 -> 44680.724 | N58: =N57+L58 -> 53749.677 | O58: =O57-K58 -> 107326.28 | S58: =$T$6-T58 -> 2817.3972 | T58: =$L$4/12*W57 -> 4620.9764 | U58: =U57+S58 -> 118300.23 | V58: =V57+T58 -> 246180.08 | W58: =W57-S58 -> 551699.77 | AA58: =$T$6-AB58 -> #NUM! | AB58: =$AB$4/12*AE57 -> #NUM! | AC58: =AC57+AA58 -> #NUM! | AD58: =AD57+AB58 -> #NUM! | AE58: =AE57-AA58 -> #NUM!
B59: M50 | C59: =$D$6-D59 -> #VALUE! | D59: =$D$4/12*G58 -> #VALUE! | E59: =E58+C59 -> #VALUE! | F59: =F58+D59 -> #VALUE! | G59: =G58-C59 -> #VALUE! | J59: =B59 -> M50 | K59: =$L$6-L59 -> 1114.3981 | L59: =$L$4/12*O58 -> 894.38563 | M59: =M58+K59 -> 45795.123 | N59: =N58+L59 -> 54644.063 | O59: =O58-K59 -> 106211.88 | S59: =$T$6-T59 -> 2840.8755 | T59: =$L$4/12*W58 -> 4597.4981 | U59: =U58+S59 -> 121141.11 | V59: =V58+T59 -> 250777.58 | W59: =W58-S59 -> 548858.89 | AA59: =$T$6-AB59 -> #NUM! | AB59: =$AB$4/12*AE58 -> #NUM! | AC59: =AC58+AA59 -> #NUM! | AD59: =AD58+AB59 -> #NUM! | AE59: =AE58-AA59 -> #NUM!
B60: M51 | C60: =$D$6-D60 -> #VALUE! | D60: =$D$4/12*G59 -> #VALUE! | E60: =E59+C60 -> #VALUE! | F60: =F59+D60 -> #VALUE! | G60: =G59-C60 -> #VALUE! | J60: =B60 -> M51 | K60: =$L$6-L60 -> 1123.6847 | L60: =$L$4/12*O59 -> 885.09898 | M60: =M59+K60 -> 46918.807 | N60: =N59+L60 -> 55529.162 | O60: =O59-K60 -> 105088.19 | S60: =$T$6-T60 -> 2864.5495 | T60: =$L$4/12*W59 -> 4573.8241 | U60: =U59+S60 -> 124005.66 | V60: =V59+T60 -> 255351.4 | W60: =W59-S60 -> 545994.34 | AA60: =$T$6-AB60 -> #NUM! | AB60: =$AB$4/12*AE59 -> #NUM! | AC60: =AC59+AA60 -> #NUM! | AD60: =AD59+AB60 -> #NUM! | AE60: =AE59-AA60 -> #NUM!
B61: M52 | C61: =$D$6-D61 -> #VALUE! | D61: =$D$4/12*G60 -> #VALUE! | E61: =E60+C61 -> #VALUE! | F61: =F60+D61 -> #VALUE! | G61: =G60-C61 -> #VALUE! | J61: =B61 -> M52 | K61: =$L$6-L61 -> 1133.0488 | L61: =$L$4/12*O60 -> 875.73494 | M61: =M60+K61 -> 48051.856 | N61: =N60+L61 -> 56404.897 | O61: =O60-K61 -> 103955.14 | S61: =$T$6-T61 -> 2888.4208 | T61: =$L$4/12*W60 -> 4549.9529 | U61: =U60+S61 -> 126894.08 | V61: =V60+T61 -> 259901.35 | W61: =W60-S61 -> 543105.92 | AA61: =$T$6-AB61 -> #NUM! | AB61: =$AB$4/12*AE60 -> #NUM! | AC61: =AC60+AA61 -> #NUM! | AD61: =AD60+AB61 -> #NUM! | AE61: =AE60-AA61 -> #NUM!
B62: M53 | C62: =$D$6-D62 -> #VALUE! | D62: =$D$4/12*G61 -> #VALUE! | E62: =E61+C62 -> #VALUE! | F62: =F61+D62 -> #VALUE! | G62: =G61-C62 -> #VALUE! | J62: =B62 -> M53 | K62: =$L$6-L62 -> 1142.4908 | L62: =$L$4/12*O61 -> 866.29287 | M62: =M61+K62 -> 49194.347 | N62: =N61+L62 -> 57271.19 | O62: =O61-K62 -> 102812.65 | S62: =$T$6-T62 -> 2912.4909 | T62: =$L$4/12*W61 -> 4525.8827 | U62: =U61+S62 -> 129806.57 | V62: =V61+T62 -> 264427.24 | W62: =W61-S62 -> 540193.43 | AA62: =$T$6-AB62 -> #NUM! | AB62: =$AB$4/12*AE61 -> #NUM! | AC62: =AC61+AA62 -> #NUM! | AD62: =AD61+AB62 -> #NUM! | AE62: =AE61-AA62 -> #NUM!
B63: M54 | C63: =$D$6-D63 -> #VALUE! | D63: =$D$4/12*G62 -> #VALUE! | E63: =E62+C63 -> #VALUE! | F63: =F62+D63 -> #VALUE! | G63: =G62-C63 -> #VALUE! | J63: =B63 -> M54 | K63: =$L$6-L63 -> 1152.0116 | L63: =$L$4/12*O62 -> 856.77211 | M63: =M62+K63 -> 50346.358 | N63: =N62+L63 -> 58127.962 | O63: =O62-K63 -> 101660.64 | S63: =$T$6-T63 -> 2936.7617 | T63: =$L$4/12*W62 -> 4501.6119 | U63: =U62+S63 -> 132743.33 | V63: =V62+T63 -> 268928.85 | W63: =W62-S63 -> 537256.67 | AA63: =$T$6-AB63 -> #NUM! | AB63: =$AB$4/12*AE62 -> #NUM! | AC63: =AC62+AA63 -> #NUM! | AD63: =AD62+AB63 -> #NUM! | AE63: =AE62-AA63 -> #NUM!
B64: M55 | C64: =$D$6-D64 -> #VALUE! | D64: =$D$4/12*G63 -> #VALUE! | E64: =E63+C64 -> #VALUE! | F64: =F63+D64 -> #VALUE! | G64: =G63-C64 -> #VALUE! | J64: =B64 -> M55 | K64: =$L$6-L64 -> 1161.6117 | L64: =$L$4/12*O63 -> 847.17201 | M64: =M63+K64 -> 51507.97 | N64: =N63+L64 -> 58975.134 | O64: =O63-K64 -> 100499.03 | S64: =$T$6-T64 -> 2961.2347 | T64: =$L$4/12*W63 -> 4477.1389 | U64: =U63+S64 -> 135704.56 | V64: =V63+T64 -> 273405.99 | W64: =W63-S64 -> 534295.44 | AA64: =$T$6-AB64 -> #NUM! | AB64: =$AB$4/12*AE63 -> #NUM! | AC64: =AC63+AA64 -> #NUM! | AD64: =AD63+AB64 -> #NUM! | AE64: =AE63-AA64 -> #NUM!
B65: M56 | C65: =$D$6-D65 -> #VALUE! | D65: =$D$4/12*G64 -> #VALUE! | E65: =E64+C65 -> #VALUE! | F65: =F64+D65 -> #VALUE! | G65: =G64-C65 -> #VALUE! | J65: =B65 -> M56 | K65: =$L$6-L65 -> 1171.2918 | L65: =$L$4/12*O64 -> 837.49192 | M65: =M64+K65 -> 52679.262 | N65: =N64+L65 -> 59812.626 | O65: =O64-K65 -> 99327.738 | S65: =$T$6-T65 -> 2985.9117 | T65: =$L$4/12*W64 -> 4452.462 | U65: =U64+S65 -> 138690.48 | V65: =V64+T65 -> 277858.45 | W65: =W64-S65 -> 531309.52 | AA65: =$T$6-AB65 -> #NUM! | AB65: =$AB$4/12*AE64 -> #NUM! | AC65: =AC64+AA65 -> #NUM! | AD65: =AD64+AB65 -> #NUM! | AE65: =AE64-AA65 -> #NUM!
... B249: M240 | C249: =$D$6-D249 -> #VALUE! | D249: =$D$4/12*G248 -> #VALUE! | E249: =E248+C249 -> #VALUE! | F249: =F248+D249 -> #VALUE! | G249: =G248-C249 -> #VALUE! | J249: =B249 -> M240 | K249: =$L$6-L249 -> 5392.9198 | L249: =$L$4/12*O248 -> -3384.1361 | M249: =M248+K249 -> 563496.26 | N249: =N248+L249 -> -81388.166 | O249: =O248-K249 -> -411489.26 | S249: =$T$6-T249 -> 13747.883 | T249: =$L$4/12*W248 -> -6309.5091 | U249: =U248+S249 -> 1440889 | V249: =V248+T249 -> 344320.69 | W249: =W248-S249 -> -770888.98 | AA249: =$T$6-AB249 -> #NUM! | AB249: =$AB$4/12*AE248 -> #NUM! | AC249: =AC248+AA249 -> #NUM! | AD249: =AD248+AB249 -> #NUM! | AE249: =AE248-AA249 -> #NUM!

Sheet S5 - salaire
B2: LES SALAIRES :
C3: Inscrivez vos informations dans ces cellules vertes. Ne rien inscrire dans les autres cellules.
B4: Soit :
B6: Salaires brut : | C6: ='S5 -Outil - Charges'!I19 -> 131170.8
B7: Retenus à la source : | C7: ='S5 -Outil - Charges'!I20 -> 34236.89
B8: Avantages sociaux : | C8: ='S5 -Outil - Charges'!I21 -> 26649.971
B9: Vacances : | C9: =0.04*C6 -> 5246.8319 | I9: Voici l'écriture des salaires à entrer dans Acomba (écriture)
B11: Salaires à payer | C11: =1/4.3333/3 -> 0.076923669 | D11: 1 semaine sur 4,333 semaines par mois
G14: débit | H14: crédit
E16: Compte de banque | G16: =-(G29+G30+G31-H16-H17-H18) -> -89477.396 | H16: =(C6-C7)*C11 -> 7456.5118 | J16: Salaires à payer
H17: =G30+C7 -> 60886.861 | J17: DAS & RAS à payer
H18: =G31 -> 5246.8319 | J18: Vacances à payer
E29: Salaires | G29: =C6 -> 131170.8
E30: Avantages sociaux | G30: =C8 -> 26649.971
E31: Vacances | G31: =C9 -> 5246.8319
G35: =SUM(G16:G31) -> 73590.204 | H35: =SUM(H16:H31) -> 73590.204

Sheet S5 - Transactions Acomba
D1: 0.05 | E1: 0.09975
A2: Compte | B2: Débit | C2: Crédit
A3: Comptes clients | B3: =C6+C5+C4 -> 2589276
A4: TPS à payer | C4: =C6*D1 -> 112601.7
A5: TVQ à payer | C5: =C6*E1 -> 224640.38
A6: Ventes | C6: ='S5 -Outil - Charges'!B5 -> 2252033.9 | D6: (valeur provenant de votre feuille des ventes réelles)
A8: Banque | B8: =C9 -> 1683029.4
A9: Comptes clients | C9: =B3*D9 -> 1683029.4 | D9: 0.65
A11: Achat (si commande Express) | D11: (si pénalité de retard)
A12: Transport sur achats
A13: TPS à recevoir | B13: =(B11+B12)*D1 -> 0
A14: TVQ à recevoir | B14: =(B11+B12)*E1 -> 0
A15: Comptes fournisseurs | C15: =D15*(B11+B12+B13+B14) -> 0 | D15: 0.5
A16: Banque | C16: =D16*(B11+B12+B13+B14) -> 0 | D16: 0.5
A18: Charges taxables (à faire en une écriture)
A19: ='S5 -Outil - Charges'!A28 -> Téléphonie et système de communication | B19: ='S5 -Outil - Charges'!B33 -> 2250
A20: ='S5 -Outil - Charges'!A36 -> Électricité (même valeur pour tous) - Dépenses fixes (facture équilibrée) | B20: ='S5 -Outil - Charges'!D37 -> 18500
A21: ='S5 -Outil - Charges'!A41 -> Frais d'entretien | B21: ='S5 -Outil - Charges'!D50 -> 189537.33
A22: ='S5 -Outil - Charges'!A62 -> Taxes municipales: | B22: ='S5 -Outil - Charges'!D64 -> 10907.722
A23: ='S5 -Outil - Charges'!F28 -> Frais de livraison aux clients: | B23: ='S5 -Outil - Charges'!J40 -> 77107.5
A24: ='S5 -Outil - Charges'!F45 -> Loyer | B24: ='S5 -Outil - Charges'!G47 -> 94242.719
A25: ='S5 -Outil - Charges'!F50 -> Publicité | B25: ='S5 -Outil - Charges'!G55 -> 276244.07
A26: ='S5 -Outil - Charges'!F59 -> Fournitures de bureau: | B26: ='S5 -Outil - Charges'!G63 -> 1437.4091
A27: ='S5 -Outil - Charges'!F82 -> Frais de site électronique
A28: ='S5 -Outil - Charges'!F90 -> Frais de transactions via internet | B28: ='S5 -Outil - Charges'!G92 -> 0
A29: ='S5 -Outil - Charges'!F75 -> Honoraires professionnelles | B29: ='S5 -Outil - Charges'!G77 -> 7882.1187
A30: TPS à recevoir | B30: =SUM(B19:B29)*D1 -> 33905.444
A31: TVQ à recevoir | B31: =SUM(B19:B29)*E1 -> 67641.36
A32: Banque | C32: =SUM(B19:B31) -> 779655.67
A34: Charges non-taxables
A35: ='S5 -Outil - Charges'!A53 -> Assurances: | B35: ='S5 -Outil - Charges'!D59 -> 2478.8391
A36: ='S5 -Outil - Charges'!F67 -> Frais de banque (pas taxables) | B36: ='S5 -Outil - Charges'!G70 -> 118.689
A37: Banque | C37: =SUM(B35:B36) -> 2597.5281
A39: Remboursement hypothèque
A40: Emprunt hypothécaire | B40: ='S5 -Emprunt'!C10+'S5 -Emprunt'!C11+'S5 -Emprunt'!C12 -> 1090.8076
A41: Intérêt | B41: ='S5 -Emprunt'!D10+'S5 -Emprunt'!D11+'S5 -Emprunt'!D12 -> 883.9141
A42: Banque | C42: =SUM(B40:B41) -> 1974.7217
E43: =50000*30.2% -> 15100
A44: Remboursement Capital de risque | E44: =10*21103 -> 211030
A45: Capital de risque | B45: ='S5 -Emprunt'!K10+'S5 -Emprunt'!K11+'S5 -Emprunt'!K12 -> 2244.7791
A46: Intérêt | B46: ='S5 -Emprunt'!L10+'S5 -Emprunt'!L11+'S5 -Emprunt'!L12 -> 3781.572
A47: Banque | C47: =SUM(B45:B46) -> 6026.3511
A49: Écriture de Salaire (voir votre feuille salaire) | B49: ==> saisir la transaction de salaire tel que présentée dans la croix comptable
A51: Écriture d'amortissement (en lien avec votre tableau de calcul Outil-Charges)
A53: ='S5 -Outil - Charges'!A70 -> Terrain | B53: ='S5 -Outil - Charges'!D70 -> 0
A54: Bâtiment - amortissement | B54: ='S5 -Outil - Charges'!D71 -> 0
A55: Bâtiment - amortissement cumulé | C55: =B54 -> 0
A56: Amélioration locative - amortissement | B56: ='S5 -Outil - Charges'!D72 -> 17450
A57: Amélioration locative - amortissement cumulé | C57: =B56 -> 17450
A58: Site transactionnel - amortissement | B58: ='S5 -Outil - Charges'!D73 -> 0
A59: Site transactionnel - amortissement cumulé | C59: =B58 -> 0
A60: Caisses - amortissement | B60: ='S5 -Outil - Charges'!D74 -> 1575
A61: Caisses - amortissement cumulé | C61: =B60 -> 1575
A62: Équipement de cuisine - amortissement | B62: ='S5 -Outil - Charges'!D75 -> 250
A63: Équipmeent de cuisine - amortissement cumulé | C63: =B62 -> 250
A64: Équipeme de manutention - amortissement | B64: ='S5 -Outil - Charges'!D76 -> 1735
A65: Équipement de manutention - amortissement cumulé | C65: =B64 -> 1735
A66: Équipement informatique - amortissement | B66: ='S5 -Outil - Charges'!D77 -> 3000
A67: Équipmeent informatique - amortissement cumulé | C67: =B66 -> 3000
A68: Ameublement - amortissement | B68: ='S5 -Outil - Charges'!D78 -> 5256.5727
A69: Ameublement - amortissement cumulé | C69: =B68 -> 5256.5727
A70: Frais d'incorporation - amortissement | B70: =3000*25% -> 750
A71: Frais d'incorporation - amortissement cumulé | C71: =B70 -> 750
A73: Écriture de régularisation
A75: Étude de marché | B75: 25000
A76: Frais payés d'avance | C76: =D76*B75 -> 6250 | D76: 0.25
A77: Divers | B77: =C76 -> 6250
A79: Inventaire (TRIM 1 seulement) | F79: TRIM "2
A80: Achats | B80: ='S4 - Montage financier'!C3 -> 1453427.5 | F80: Stock de début | G80: ='S5 -Outil - Charges'!B14 -> 10821
A81: Stock de marchandises | C81: =B80 -> 1453427.5 | F81: =A82 -> Stock de marchandises
A82: Stock de marchandises | B82: ='S5 -Outil - Charges'!B14 -> 10821 | F82: =A82 -> Stock de marchandises
A83: Inventaire de fin | C83: =B82 -> 10821 | F83: =A83 -> Inventaire de fin
A85: Intérêt sur la marge de crédit | B85: =11%/4
A86: Intérêt | B86: =('S4 - Montage financier'!D2*11%)/4 -> 18425
A87: Banque | C87: =B86 -> 18425
A89: Remboursement des taxes à recevoir
A90: Banque | B90: ='S4 - Montage financier'!C2 -> 217650.77
A91: Taxes nettes à recevoir | C91: =B90 -> 217650.77
A93: Écriture des taxes (faire votre écriture de taxes pour le Trimestre 1
A94: T.P.S. à payer | B94: =112602 -> 112602 | D94: Voir BV
A95: T.V.Q à payer | B95: =224640 -> 224640
A96: T.P.S à recevoir | C96: =33937 -> 33937
A97: T.V.Q. à recevoir | C97: =67704 -> 67704
A98: Comptes de taxes nettes | B98: =SUM(B94:B95)-SUM(C96:C97) -> 235601
A100: Remboursement de votre marge de crédit en fonction de votre compte de Banque
A101: Marge de crédit | B101: =670000 -> 670000
A102: Banque | C102: =B101 -> 670000

Sheet S6 États des résultats TRIM 1
B2: Issa O
B3: États des résultats
B4: Pour la période se terminant au TRIM 1
A7: Ventes de biens : | B7: Solde TRIM 1 | C7: Solde Année | D7: % Ventes
A8: Ventes | B8: 2252034 | C8: 2252034 | D8: 100
A9: Ventes de biens nettes | B9: 2252034 | C9: 2252034 | D9: 100
A10: Coût des marchandises vendues :
A11: Achats | B11: 1453428 | C11: 1453428 | D11: 64.54
A12: Stocks de fin | B12: -10821 | C12: -10821 | D12: -0.48
A13: Coût des marchandises vendues | B13: 1442607 | C13: 1442607 | D13: 64.06
A14: Bénéfice brut (perte brute) | B14: 809427 | C14: 809427 | D14: 35.94
A17: Frais d'exploitation :
A18: Salaires | B18: 131170.8 | C18: 131170.8 | D18: 5.82
A19: Avantages sociaux | B19: 26649.97 | C19: 26649.97 | D19: 1.18
A20: Vacances | B20: 5246.83 | C20: 5246.83 | D20: 0.23
A21: Téléphonie et système de communication | B21: 2250 | C21: 2250 | D21: 0.1
A22: Publicité | B22: 276244 | C22: 276244 | D22: 12.27
A23: Frais de livraison | B23: 77108 | C23: 77108 | D23: 3.42
A24: Loyer | B24: 94243 | C24: 94243 | D24: 4.18
A25: Électricité | B25: 18500 | C25: 18500 | D25: 0.82
A26: Assurances | B26: 2479 | C26: 2479 | D26: 0.11
A27: Honoraires professionnels | B27: 7882 | C27: 7882 | D27: 0.35
A28: Fournitures de bureau | B28: 1437 | C28: 1437 | D28: 0.06
A29: Taxes, permis, licences | B29: 10908 | C29: 10908 | D29: 0.48
... A39: perte nette | B39: -69656.08 | C39: -69656.08 | D39: -3.09
D44: x

Sheet S7 - Rentabilité par prod. ETUD
D1: Produit | E1: Prix de vente | F1: Coûtant | G1: Dimension par unité en M3 | H1: % commission | I1: % avantages sociaux | J1: % honoraires professionnelles | K1: Ventes en unité TRIM 1 | L1: Ventes en unité TRIM 2 | M1: Ventes en unité (Vitesse de croisière) - année 3 | N1: Salaire | O1: 131171
D2: ='S2 - Inventaire départ'!B4 -> P1 | E2: =Données!I6 -> 10.87 | F2: =Données!H6 -> 6.75 | G2: =Données!G6 -> 0.18 | H2: =$G$18 -> 0.015 | I2: =$H$18 -> 0.24317113 | J2: =$L$18 -> 0.001 | K2: ='S5 -Outil - Ventes'!H6 -> 57067.5 | L2: ='S8 -Outil - Ventes '!H6 -> 84242.5 | M2: ='S1 - projections'!AU24 -> 475534.34 | N2: Avantages sociaux | O2: 26650
D3: ='S2 - Inventaire départ'!B5 -> P2 | E3: =Données!I7 -> 21.74 | F3: =Données!H7 -> 13.5 | G3: =Données!G7 -> 0.225 | H3: =$G$18 -> 0.015 | I3: =$H$18 -> 0.24317113 | J3: =$L$18 -> 0.001 | K3: ='S5 -Outil - Ventes'!H7 -> 134788 | L3: ='S8 -Outil - Ventes '!H7 -> 197834 | M3: ='S1 - projections'!AU25 -> 1114576.2 | N3: Vacances | O3: 5247
D4: ='S2 - Inventaire départ'!B6 -> P3 | E4: =Données!I8 -> 35.02 | F4: =Données!H8 -> 20 | G4: =Données!G8 -> 0.675 | H4: =$G$18 -> 0.015 | I4: =$H$18 -> 0.24317113 | J4: =$L$18 -> 0.001 | K4: ='S5 -Outil - Ventes'!H8 -> 121764.54 | L4: ='S8 -Outil - Ventes '!H8 -> 0 | M4: ='S1 - projections'!AU26 -> 378393.62
D5: ='S2 - Inventaire départ'!B7 -> P4 | E5: =Données!I9 -> 42.26 | F5: =Données!H9 -> 29 | G5: =Données!G9 -> 0.5 | H5: =$G$18 -> 0.015 | I5: =$H$18 -> 0.24317113 | J5: =$L$18 -> 0.001 | K5: ='S5 -Outil - Ventes'!H9 -> 122554 | L5: ='S8 -Outil - Ventes '!H9 -> 181718 | M5: ='S1 - projections'!AU27 -> 1010022.8 | N5: Coût pour 150 m3 (transport sur achat) | O5: 550
D6: ='S2 - Inventaire départ'!B8 -> P5 | E6: =Données!I10 -> 59.17 | F6: =Données!H10 -> 35 | G6: =Données!G10 -> 0.75 | H6: =$G$18 -> 0.015 | I6: =$H$18 -> 0.24317113 | J6: =$L$18 -> 0.001 | K6: ='S5 -Outil - Ventes'!H10 -> 281057.5 | L6: ='S8 -Outil - Ventes '!H10 -> 414130.83 | M6: ='S1 - projections'!AU28 -> 2348717.8 | N6: Coût pour 150 m3 (transport pour livraison) | O6: 450
D7: ='S2 - Inventaire départ'!B9 -> P6 | E7: =Données!I11 -> 64 | F7: =Données!H11 -> 42 | G7: =Données!G11 -> 0.9 | H7: =$G$18 -> 0.015 | I7: =$H$18 -> 0.24317113 | J7: =$L$18 -> 0.001 | K7: ='S5 -Outil - Ventes'!H11 -> 103744 | L7: ='S8 -Outil - Ventes '!H11 -> 0 | M7: ='S1 - projections'!AU29 -> 312855.27
D8: ='S2 - Inventaire départ'!B10 -> P7 | E8: =Données!I12 -> 82.11 | F8: =Données!H12 -> 54 | G8: =Données!G12 -> 0.875 | H8: =$G$18 -> 0.015 | I8: =$H$18 -> 0.24317113 | J8: =$L$18 -> 0.001 | K8: ='S5 -Outil - Ventes'!H12 -> 201497.94 | L8: ='S8 -Outil - Ventes '!H12 -> 295596 | M8: ='S1 - projections'!AU30 -> 1684547.3
D9: ='S2 - Inventaire départ'!B11 -> P8 | E9: =Données!I13 -> 85.73 | F9: =Données!H13 -> 59 | G9: =Données!G13 -> 1.8 | H9: =$G$18 -> 0.015 | I9: =$H$18 -> 0.24317113 | J9: =$L$18 -> 0.001 | K9: ='S5 -Outil - Ventes'!H13 -> 643403.65 | L9: ='S8 -Outil - Ventes '!H13 -> 950745.7 | M9: ='S1 - projections'!AU31 -> 5380323.8
D10: ='S2 - Inventaire départ'!B12 -> P9 | E10: =Données!I14 -> 108.68 | F10: =Données!H14 -> 66 | G10: =Données!G14 -> 0.5625 | H10: =$G$18 -> 0.015 | I10: =$H$18 -> 0.24317113 | J10: =$L$18 -> 0.001 | K10: ='S5 -Outil - Ventes'!H14 -> 464715.68 | L10: ='S8 -Outil - Ventes '!H14 -> 0 | M10: ='S1 - projections'!AU32 -> 1384858.5
D11: ='S2 - Inventaire départ'!B13 -> P10 | E11: =Données!I15 -> 107.47 | F11: =Données!H15 -> 69 | G11: =Données!G15 -> 0.75 | H11: =$G$18 -> 0.015 | I11: =$H$18 -> 0.24317113 | J11: =$L$18 -> 0.001 | K11: ='S5 -Outil - Ventes'!H15 -> 121441.1 | L11: ='S8 -Outil - Ventes '!H15 -> 178185.26 | M11: ='S1 - projections'!AU33 -> 1010358.3
D12: ='S2 - Inventaire départ'!B14 -> P11 | E12: =Données!I16 -> 36.23 | F12: =Données!H16 -> 22 | G12: =Données!G16 -> 0.675 | H12: =$G$18 -> 0.015 | I12: =$H$18 -> 0.24317113 | J12: =$L$18 -> 0.001 | K12: ='S5 -Outil - Ventes'!H16 -> 0 | L12: ='S8 -Outil - Ventes '!H16 -> 38349.455 | M12: ='S1 - projections'!AU34 -> 89480.875
D13: ='S2 - Inventaire départ'!B15 -> P12 | E13: =Données!I17 -> 63.4 | F13: =Données!H17 -> 43 | G13: =Données!G17 -> 1.75 | H13: =$G$18 -> 0.015 | I13: =$H$18 -> 0.24317113 | J13: =$L$18 -> 0.001 | K13: ='S5 -Outil - Ventes'!H17 -> 0 | L13: ='S8 -Outil - Ventes '!H17 -> 188298 | M13: ='S1 - projections'!AU35 -> 467056.32
D14: ='S2 - Inventaire départ'!B16 -> P13 | E14: =Données!I18 -> 99.62 | F14: =Données!H18 -> 65 | G14: =Données!G18 -> 1.25 | H14: =$G$18 -> 0.015 | I14: =$H$18 -> 0.24317113 | J14: =$L$18 -> 0.001 | K14: ='S5 -Outil - Ventes'!H18 -> 0 | L14: ='S8 -Outil - Ventes '!H18 -> 119593.81 | M14: ='S1 - projections'!AU36 -> 296946.68
G18: 0.015 | H18: =(O2+O3)/O1 -> 0.24317113 | L18: =0.001 -> 0.001
A19: Produits | B19: Prix de vente | C19: Coût achat | D19: Rapport sur les ventes (Coût d'achat) | E19: Transport sur achats | F19: Rapport sur les ventes (Transport) | G19: Commission aux vendeurs | H19: Avantages sociaux | I19: Rapport sur les ventes (comm + avantages) | J19: Frais de livraison | K19: Rapport sur les ventes (Livraison) | L19: Honoraires professionnelles | M19: Rapport sur les ventes (Honoraires) | N19: Total des coûts | O19: Rapport sur les ventes (total) | P19: Marge sur les coûts directs | Q19: Rapport sur les ventes (marge) | R19: Marge avec volume pour les ventes TRIM 1 et TRIM2 | S19: Rapport au total de la marge | T19: Marge avec volume en vitesse de croisière (année 3) | U19: Rapport au total de la marge (en vitesse de croisière)
A20: ='S8 – Commande TRIM 2'!B4 -> P1 | B20: =Données!I6 -> 10.87 | C20: =Données!H6 -> 6.75 | D20: =C20/B20 -> 0.62097516 | E20: =$F$41*G2 -> 0.66 | F20: =E20/B20 -> 0.060717571 | G20: =$G$18*B20 -> 0.16305 | H20: =$H$18*G20 -> 0.039649052 | I20: =(G20+H20)/B20 -> 0.018647567 | K20: =J20/B20 -> 0 | L20: =B20*$L$18 -> 0.01087 | M20: =L20/B20 -> 0.001 | N20: =C20+E20+G20+H20+J20+L20 -> 7.6235691 | O20: =N20/B20 -> 0.7013403 | P20: =B20-N20 -> 3.2464309 | Q20: =P20/B20 -> 0.2986597 | R20: =P20*(K2+L2) -> 458753.16 | S20: =R20/$R$33 -> 0.0052273143 | T20: =P20*M2 -> 1543789.4 | U20: =T20/$T$33 -> 0.0054600427
A21: ='S8 – Commande TRIM 2'!B5 -> P2 | B21: =Données!I7 -> 21.74 | C21: =Données!H7 -> 13.5 | D21: =C21/B21 -> 0.62097516 | E21: =$F$41*G3 -> 0.825 | F21: =E21/B21 -> 0.037948482 | G21: =$G$18*B21 -> 0.3261 | H21: =$H$18*G21 -> 0.079298105 | I21: =(G21+H21)/B21 -> 0.018647567 | K21: =J21/B21 -> 0 | L21: =B21*$L$18 -> 0.02174 | M21: =L21/B21 -> 0.001 | N21: =C21+E21+G21+H21+J21+L21 -> 14.752138 | O21: =N21/B21 -> 0.67857121 | P21: =B21-N21 -> 6.9878619 | Q21: =P21/B21 -> 0.32142879 | R21: =P21*(K3+L3) -> 2324316.6 | S21: =R21/$R$33 -> 0.026484686 | T21: =P21*M3 -> 7788504.4 | U21: =T21/$T$33 -> 0.027546223
A22: ='S8 – Commande TRIM 2'!B6 -> P3 | B22: =Données!I8 -> 35.02 | C22: =Données!H8 -> 20 | D22: =C22/B22 -> 0.57110223 | E22: =$F$41*G4 -> 2.475 | F22: =E22/B22 -> 0.070673901 | G22: =$G$18*B22 -> 0.5253 | H22: =$H$18*G22 -> 0.12773779 | I22: =(G22+H22)/B22 -> 0.018647567 | K22: =J22/B22 -> 0 | L22: =B22*$L$18 -> 0.03502 | M22: =L22/B22 -> 0.001 | N22: =C22+E22+G22+H22+J22+L22 -> 23.163058 | O22: =N22/B22 -> 0.66142369 | P22: =B22-N22 -> 11.856942 | Q22: =P22/B22 -> 0.33857631 | R22: =P22*(K4+L4) -> 1443755.1 | S22: =R22/$R$33 -> 0.01645103 | T22: =P22*M4 -> 4486591.3 | U22: =T22/$T$33 -> 0.015868084
A23: ='S8 – Commande TRIM 2'!B7 -> P4 | B23: =Données!I9 -> 42.26 | C23: =Données!H9 -> 29 | D23: =C23/B23 -> 0.68622811 | E23: =$F$41*G5 -> 1.8333333 | F23: =E23/B23 -> 0.043382237 | G23: =$G$18*B23 -> 0.6339 | H23: =$H$18*G23 -> 0.15414618 | I23: =(G23+H23)/B23 -> 0.018647567 | K23: =J23/B23 -> 0 | L23: =B23*$L$18 -> 0.04226 | M23: =L23/B23 -> 0.001 | N23: =C23+E23+G23+H23+J23+L23 -> 31.66364 | O23: =N23/B23 -> 0.74925792 | P23: =B23-N23 -> 10.59636 | Q23: =P23/B23 -> 0.25074208 | R23: =P23*(K5+L5) -> 3224175.8 | S23: =R23/$R$33 -> 0.036738233 | T23: =P23*M5 -> 10702566 | U23: =T23/$T$33 -> 0.037852615
A24: ='S8 – Commande TRIM 2'!B8 -> P5 | B24: =Données!I10 -> 59.17 | C24: =Données!H10 -> 35 | D24: =C24/B24 -> 0.59151597 | E24: =$F$41*G6 -> 2.75 | F24: =E24/B24 -> 0.046476255 | G24: =$G$18*B24 -> 0.88755 | H24: =$H$18*G24 -> 0.21582653 | I24: =(G24+H24)/B24 -> 0.018647567 | K24: =J24/B24 -> 0 | L24: =B24*$L$18 -> 0.05917 | M24: =L24/B24 -> 0.001 | N24: =C24+E24+G24+H24+J24+L24 -> 38.912547 | O24: =N24/B24 -> 0.65763979 | P24: =B24-N24 -> 20.257453 | Q24: =P24/B24 -> 0.34236021 | R24: =P24*(K6+L6) -> 14082745 | S24: =R24/$R$33 -> 0.16046742 | T24: =P24*M6 -> 47579041 | U24: =T24/$T$33 -> 0.16827658
A25: ='S8 – Commande TRIM 2'!B9 -> P6 | B25: =Données!I11 -> 64 | C25: =Données!H11 -> 42 | D25: =C25/B25 -> 0.65625 | E25: =$F$41*G7 -> 3.3 | F25: =E25/B25 -> 0.0515625 | G25: =$G$18*B25 -> 0.96 | H25: =$H$18*G25 -> 0.23344428 | I25: =(G25+H25)/B25 -> 0.018647567 | K25: =J25/B25 -> 0 | L25: =B25*$L$18 -> 0.064 | M25: =L25/B25 -> 0.001 | N25: =C25+E25+G25+H25+J25+L25 -> 46.557444 | O25: =N25/B25 -> 0.72746007 | P25: =B25-N25 -> 17.442556 | Q25: =P25/B25 -> 0.27253993 | R25: =P25*(K7+L7) -> 1809560.5 | S25: =R25/$R$33 -> 0.02061924 | T25: =P25*M7 -> 5456995.5 | U25: =T25/$T$33 -> 0.01930019
A26: ='S8 – Commande TRIM 2'!B10 -> P7 | B26: =Données!I12 -> 82.11 | C26: =Données!H12 -> 54 | D26: =C26/B26 -> 0.65765437 | E26: =$F$41*G8 -> 3.2083333 | F26: =E26/B26 -> 0.0390736 | G26: =$G$18*B26 -> 1.23165 | H26: =$H$18*G26 -> 0.29950172 | I26: =(G26+H26)/B26 -> 0.018647567 | J26: =$K$41*G8 -> 2.625 | K26: =J26/B26 -> 0.031969309 | L26: =B26*$L$18 -> 0.08211 | M26: =L26/B26 -> 0.001 | N26: =C26+E26+G26+H26+J26+L26 -> 61.446595 | O26: =N26/B26 -> 0.74834484 | P26: =B26-N26 -> 20.663405 | Q26: =P26/B26 -> 0.25165516 | R26: =P26*(K8+L8) -> 10271653 | S26: =R26/$R$33 -> 0.11704151 | T26: =P26*M8 -> 34808482 | U26: =T26/$T$33 -> 0.12310993
A27: ='S8 – Commande TRIM 2'!B11 -> P8 | B27: =Données!I13 -> 85.73 | C27: =Données!H13 -> 59 | D27: =C27/B27 -> 0.68820716 | E27: =$F$41*G9 -> 6.6 | F27: =E27/B27 -> 0.076985886 | G27: =$G$18*B27 -> 1.28595 | H27: =$H$18*G27 -> 0.31270591 | I27: =(G27+H27)/B27 -> 0.018647567 | J27: =$K$41*G9 -> 5.4 | K27: =J27/B27 -> 0.062988452 | L27: =B27*$L$18 -> 0.08573 | M27: =L27/B27 -> 0.001 | N27: =C27+E27+G27+H27+J27+L27 -> 72.684386 | O27: =N27/B27 -> 0.84782907 | P27: =B27-N27 -> 13.045614 | Q27: =P27/B27 -> 0.15217093 | R27: =P27*(K9+L9) -> 20796657 | S27: =R27/$R$33 -> 0.23696984 | T27: =P27*M9 -> 70189628 | U27: =T27/$T$33 -> 0.24824524
A28: ='S8 – Commande TRIM 2'!B12 -> P9 | B28: =Données!I14 -> 108.68 | C28: =Données!H14 -> 66 | D28: =C28/B28 -> 0.60728745 | E28: =$F$41*G10 -> 2.0625 | F28: =E28/B28 -> 0.018977733 | G28: =$G$18*B28 -> 1.6302 | H28: =$H$18*G28 -> 0.39641757 | I28: =(G28+H28)/B28 -> 0.018647567 | J28: =$K$41*G10 -> 1.6875 | K28: =J28/B28 -> 0.015527236 | L28: =B28*$L$18 -> 0.10868 | M28: =L28/B28 -> 0.001 | N28: =C28+E28+G28+H28+J28+L28 -> 71.885298 | O28: =N28/B28 -> 0.66143999 | P28: =B28-N28 -> 36.794702 | Q28: =P28/B28 -> 0.33856001 | R28: =P28*(K10+L10) -> 17099075 | S28: =R28/$R$33 -> 0.19483733 | T28: =P28*M10 -> 50955456 | U28: =T28/$T$33 -> 0.18021821
A29: ='S8 – Commande TRIM 2'!B13 -> P10 | B29: =Données!I15 -> 107.47 | C29: =Données!H15 -> 69 | D29: =C29/B29 -> 0.64203964 | E29: =$F$41*G11 -> 2.75 | F29: =E29/B29 -> 0.025588536 | G29: =$G$18*B29 -> 1.61205 | H29: =$H$18*G29 -> 0.39200402 | I29: =(G29+H29)/B29 -> 0.018647567 | K29: =J29/B29 -> 0 | L29: =B29*$L$18 -> 0.10747 | M29: =L29/B29 -> 0.001 | N29: =C29+E29+G29+H29+J29+L29 -> 73.861524 | O29: =N29/B29 -> 0.68727574 | P29: =B29-N29 -> 33.608476 | Q29: =P29/B29 -> 0.31272426 | R29: =P29*(K11+L11) -> 10069985 | S29: =R29/$R$33 -> 0.11474358 | T29: =P29*M11 -> 33956603 | U29: =T29/$T$33 -> 0.12009702
A30: ='S8 – Commande TRIM 2'!B14 -> P11 | B30: =Données!I16 -> 36.23 | C30: =Données!H16 -> 22 | D30: =C30/B30 -> 0.60723158 | E30: =$F$41*G12 -> 2.475 | F30: =E30/B30 -> 0.068313552 | G30: =$G$18*B30 -> 0.54345 | H30: =$H$18*G30 -> 0.13215135 | I30: =(G30+H30)/B30 -> 0.018647567 | K30: =J30/B30 -> 0 | L30: =B30*$L$18 -> 0.03623 | M30: =L30/B30 -> 0.001 | N30: =C30+E30+G30+H30+J30+L30 -> 25.186831 | O30: =N30/B30 -> 0.6951927 | P30: =B30-N30 -> 11.043169 | Q30: =P30/B30 -> 0.3048073 | R30: =P30*(K12+L12) -> 423499.5 | S30: =R30/$R$33 -> 0.0048256125 | T30: =P30*M12 -> 988152.39 | U30: =T30/$T$33 -> 0.0034948771
A31: ='S8 – Commande TRIM 2'!B15 -> P12 | B31: =Données!I17 -> 63.4 | C31: =Données!H17 -> 43 | D31: =C31/B31 -> 0.67823344 | E31: =$F$41*G13 -> 6.4166667 | F31: =E31/B31 -> 0.10120925 | G31: =$G$18*B31 -> 0.951 | H31: =$H$18*G31 -> 0.23125574 | I31: =(G31+H31)/B31 -> 0.018647567 | K31: =J31/B31 -> 0 | L31: =B31*$L$18 -> 0.0634 | M31: =L31/B31 -> 0.001 | N31: =C31+E31+G31+H31+J31+L31 -> 50.662322 | O31: =N31/B31 -> 0.79909026 | P31: =B31-N31 -> 12.737678 | Q31: =P31/B31 -> 0.20090974 | R31: =P31*(K13+L13) -> 2398479.2 | S31: =R31/$R$33 -> 0.02732974 | T31: =P31*M13 -> 5949212.8 | U31: =T31/$T$33 -> 0.021041054
A32: ='S8 – Commande TRIM 2'!B16 -> P13 | B32: =Données!I18 -> 99.62 | C32: =Données!H18 -> 65 | D32: =C32/B32 -> 0.65247942 | E32: =$F$41*G14 -> 4.5833333 | F32: =E32/B32 -> 0.046008164 | G32: =$G$18*B32 -> 1.4943 | H32: =$H$18*G32 -> 0.36337062 | I32: =(G32+H32)/B32 -> 0.018647567 | K32: =J32/B32 -> 0 | L32: =B32*$L$18 -> 0.09962 | M32: =L32/B32 -> 0.001 | N32: =C32+E32+G32+H32+J32+L32 -> 71.540624 | O32: =N32/B32 -> 0.71813515 | P32: =B32-N32 -> 28.079376 | Q32: =P32/B32 -> 0.28186485 | R32: =P32*(K14+L14) -> 3358119.6 | S32: =R32/$R$33 -> 0.03826447 | T32: =P32*M14 -> 8338077.4 | U32: =T32/$T$33 -> 0.029489941
R33: =SUM(R20:R32) -> 87760776 | S33: =R33/$R$33 -> 1 | T33: =SUM(T20:T32) -> 2.827431e+08 | U33: =T33/$T$33 -> 1
E39: Coût pour un m3 | J39: Coût pour un m3
E40: 150 m3 | F40: =O5 -> 550 | J40: 150 m3 | K40: =O6 -> 450
E41: 1 m3 | F41: =F40/150 -> 3.6666667 | J41: 1 m3 | K41: =K40/150 -> 3

Sheet S6 Bilan TRIM 1
C2: Issa O
C3: Bilan
C4: Au TRIM 1
B6: Actif
A7: Actif à court terme
A8: Banque | C8: 350227.53
A9: Comptes clients | C9: 906247
A10: Charges payées d'avance | C10: 25000
A11: Stocks de marchandises | C11: 10821
A12: Total de l'actif à court terme | D12: 1292295.5
A14: Immobilisations
A15: Ameublement | C15: 105131
A16: Amort. cumulé - Ameublement | C16: -5257 | D16: =C15+C16 -> 99874
A18: Équipement informatique | C18: 40000
A19: Amort. cumulé - Équip. informatique | C19: -3000 | D19: =C18+C19 -> 37000
A21: Equipement de ventes - Caisse | C21: 31500
A22: Amort. cumulé - Equip. de vente -Caisse | C22: -1575 | D22: =C21+C22 -> 29925
A24: Équipement- Manutention et Cuisine | C24: 39700
A25: Amort. cumulé - Équipement - Manutention et Cuisine | C25: -1985 | D25: =C24+C25 -> 37715
A27: Améliorations locatives | C27: 349000
A28: Amort. cumulé - Amélior. locatives | C28: -17450 | D28: =C27+C28 -> 331550
A30: Frais d'incorporation reportés | C30: 6500
A31: Amort. cumulé - Frais d'incorporation | C31: -750 | D31: =C30+C31 -> 5750
A33: Total des immobilisations | D33: 541814
A34: Total de l'actif | D34: 1834109.5
B36: Passif
A37: Passif à court terme
A38: Comptes fournisseurs | B38: 851612
A39: Salaires à payer | B39: 7456.51
A40: Vacances à payer | B40: 5246.83
A41: D.A.S. à payer | B41: 60886.86
A42: Taxe a payer | B42: 235601
A43: Capital de risque | B43: 149763.22
A44: Total du passif à court terme | C44: 1310566.4 | D44: x
A46: Passif à long terme
A47: Emprunt hypothécaire | B47: 58199.19
A48: Total du passif à long terme | C48: 58199.19
A49: Total du passif | D49: 1368765.6
B51: Capitaux
A52: Capital - Actions | C52: 450000
A53: Subventions | C53: 85000
A54: Perte nette | C54: -69656.08
A55: Total Capitaux | D55: 465343.92
A57: Total du passif et de l'avoir | D57: 1834109.5

Sheet S8 – Commande TRIM 2
A1: Évaluation de l'inventaire au démarrage TRIM 2: | I1: Données d'entreprise à ajuster en fonction de la situation
F2: (Plafond ou Plancher) | L2: Tableau de comparaison des transporteurs:
C3: Prévision TRIM 2 | D3: inventaire de fin | E3: Lot | F3: Qté à commander | G3: Coût unitaire | H3: Coût total | I3: Volume unitaire (M3) | J3: Volume total (M3) | N3: M3 | O3: Coût | P3: Nombre de voyages | Q3: Coût total
B4: P1 | C4: ='S1 - projections'!F8+'S1 - projections'!G8+'S1 - projections'!H8 -> 7728.7755 | D4: ='S5 -Outil - Ventes'!I6 -> 0 | E4: =Données!J6 -> 50 | F4: =CEILING(C4-D4,E4) -> 7750 | G4: =Données!H6 -> 6.75 | H4: =F4*G4 -> 52312.5 | I4: =Données!G6 -> 0.18 | J4: =F4*I4 -> 1395 | L4: FTL | M4: Fournisseur: | N4: 150 | O4: 925 | P4: =J23 -> 290 | Q4: =P4*O4 -> 268250 | R4: =Q4+Q5 -> 268900
B5: P2 | C5: ='S1 - projections'!F9+'S1 - projections'!G9+'S1 - projections'!H9 -> 9057.5048 | D5: ='S5 -Outil - Ventes'!I7 -> 0 | E5: =Données!J7 -> 100 | F5: =CEILING(C5-D5,E5) -> 9100 | G5: =Données!H7 -> 13.5 | H5: =F5*G5 -> 122850 | I5: =Données!G7 -> 0.225 | J5: =F5*I5 -> 2047.5 | N5: 100 | O5: 650 | P5: =ROUNDUP(J26,0) -> 1 | Q5: =P5*O5 -> 650
B6: P3 | C6: ='S1 - projections'!F10+'S1 - projections'!G10+'S1 - projections'!H10 -> 0 | D6: ='S5 -Outil - Ventes'!I8 -> 223 | E6: =Données!J8 -> 100 | F6: =CEILING(C6-D6,E6) -> -200 | G6: =Données!H8 -> 20 | I6: =Données!G8 -> 0.675 | J6: =F6*I6 -> -135 | L6: LTL | M6: Desgagné: | N6: 150 | O6: 865 | P6: =J23 -> 290 | Q6: =P6*O6 -> 250850 | R6: =Q6+Q7 -> 251069.77
B7: P4 | C7: ='S1 - projections'!F11+'S1 - projections'!G11+'S1 - projections'!H11 -> 4222.4065 | D7: ='S5 -Outil - Ventes'!I9 -> 0 | E7: =Données!J9 -> 100 | F7: =CEILING(C7-D7,E7) -> 4300 | G7: =Données!H9 -> 29 | H7: =F7*G7 -> 124700 | I7: =Données!G9 -> 0.5 | J7: =F7*I7 -> 2150 | N7: 100 | O7: 745 | P7: =J26 -> 0.295 | Q7: =P7*O7 -> 219.775
B8: P5 | C8: ='S1 - projections'!F12+'S1 - projections'!G12+'S1 - projections'!H12 -> 7012.738 | D8: ='S5 -Outil - Ventes'!I10 -> 0 | E8: =Données!J10 -> 50 | F8: =CEILING(C8-D8,E8) -> 7050 | G8: =Données!H10 -> 35 | H8: =F8*G8 -> 246750 | I8: =Données!G10 -> 0.75 | J8: =F8*I8 -> 5287.5
B9: P6 | C9: ='S1 - projections'!F13+'S1 - projections'!G13+'S1 - projections'!H13 -> 0 | D9: ='S5 -Outil - Ventes'!I11 -> 79 | E9: =Données!J11 -> 100 | F9: =CEILING(C9-D9,E9) -> 0 | G9: =Données!H11 -> 42 | H9: =F9*G9 -> 0 | I9: =Données!G11 -> 0.9 | J9: =F9*I9 -> 0
B10: P7 | C10: ='S1 - projections'!F14+'S1 - projections'!G14+'S1 - projections'!H14 -> 3624.4783 | D10: ='S5 -Outil - Ventes'!I12 -> 46 | E10: =Données!J12 -> 50 | F10: =CEILING(C10-D10,E10) -> 3600 | G10: =Données!H12 -> 54 | H10: =F10*G10 -> 194400 | I10: =Données!G12 -> 0.875 | J10: =F10*I10 -> 3150
B11: P8 | C11: ='S1 - projections'!F15+'S1 - projections'!G15+'S1 - projections'!H15 -> 11087.508 | D11: ='S5 -Outil - Ventes'!I13 -> 5 | E11: =Données!J13 -> 10 | F11: =CEILING(C11-D11,E11) -> 11090 | G11: =Données!H13 -> 59 | H11: =F11*G11 -> 654310 | I11: =Données!G13 -> 1.8 | J11: =F11*I11 -> 19962
B12: P9 | C12: ='S1 - projections'!F16+'S1 - projections'!G16+'S1 - projections'!H16 -> 0 | D12: ='S5 -Outil - Ventes'!I14 -> 4 | E12: =Données!J14 -> 10 | F12: =CEILING(C12-D12,E12) -> 0 | G12: =Données!H14 -> 66 | H12: =F12*G12 -> 0 | I12: =Données!G14 -> 0.5625 | J12: =F12*I12 -> 0
B13: P10 | C13: ='S1 - projections'!F17+'S1 - projections'!G17+'S1 - projections'!H17 -> 1660.9116 | D13: ='S5 -Outil - Ventes'!I15 -> 0 | E13: =Données!J15 -> 10 | F13: =CEILING(C13-D13,E13) -> 1670 | G13: =Données!H15 -> 69 | H13: =F13*G13 -> 115230 | I13: =Données!G15 -> 0.75 | J13: =F13*I13 -> 1252.5
B14: P11 | C14: ='S1 - projections'!F18+'S1 - projections'!G18+'S1 - projections'!H18 -> 1128.5438 | D14: ='S5 -Outil - Ventes'!I16 -> 0 | E14: =Données!J16 -> 100 | F14: =CEILING(C14-D14,E14) -> 1200 | G14: =Données!H16 -> 22 | H14: =F14*G14 -> 26400 | I14: =Données!G16 -> 0.675 | J14: =F14*I14 -> 810
B15: P12 | C15: ='S1 - projections'!F19+'S1 - projections'!G19+'S1 - projections'!H19 -> 3366.1738 | D15: ='S5 -Outil - Ventes'!I17 -> 0 | E15: =Données!J17 -> 10 | F15: =CEILING(C15-D15,E15) -> 3370 | G15: =Données!H17 -> 43 | H15: =F15*G15 -> 144910 | I15: =Données!G17 -> 1.75 | J15: =F15*I15 -> 5897.5
B16: P13 | C16: ='S1 - projections'!F20+'S1 - projections'!G20+'S1 - projections'!H20 -> 1362.0357 | D16: ='S5 -Outil - Ventes'!I18 -> 0 | E16: =Données!J18 -> 10 | F16: =CEILING(C16-D16,E16) -> 1370 | G16: =Données!H18 -> 65 | H16: =F16*G16 -> 89050 | I16: =Données!G18 -> 1.25 | J16: =F16*I16 -> 1712.5
H22: =SUM(H4:H16) -> 1770912.5 | J22: =SUM(J4:J16) -> 43529.5 | K22: volume total
J23: =ROUNDDOWN(J22/N4,0) -> 290 | K23: Nombre de voyage de 150 m3 en FTL
I24: volume chargé: | J24: =J23*N4 -> 43500
I25: reste | J25: =J22-J24 -> 29.5 | K25: m3
I26: Voyage 100 m3 | J26: =J25/N7 -> 0.295
B28: Coût de la commande 2= | H28: =H22 -> 1770912.5
B29: +frais de transport = le plus petit montant | H29: =MIN(R4,R6) -> 251069.77
B30: Total: | H30: =SUM(H28:H29) -> 2021982.3
B33: Note: Taxes à recevoir à traiter plus tard

Sheet Ventes potentielle TRIM 2
A1: Ventes potentielles | C1: gr02
C3: Trim 2
B4: P1 | C4: 7933
B5: P2 | C5: 9228
B6: P3 | C6: 0
B7: P4 | C7: 4350
B8: P5 | C8: 6999
B9: P6 | C9: 0
B10: P7 | C10: 3651
B11: P8 | C11: 11111
B12: P9 | C12: 0
B13: P10 | C13: 1658
B14: P11 | C14: 917
B15: P12 | C15: 2570
B16: P13 | C16: 1031

Sheet Bon de commande TRIM 2
B2: Vendu à | C2: Simul inc. | F2: N° bon de commande | G2: 48826
C3: No. 1112223 | F3: Date | G3: 45703
C4: cégep Limoilou
C5: G1G1G1
C6: 581-090-2426
B9: Quantité | C9: Nº de l’article | D9: Description | E9: Prix unitaire | F9: Remise | G9: Total de la ligne
B10: ='S8 – Commande TRIM 2'!F4 -> 7750 | C10: 1 | D10: P1 | E10: ='S8 – Commande TRIM 2'!G4 -> 6.75 | G10: =Table_SalesReceiptDetails6[[#This Row],[Quantité]]*Table_SalesReceiptDetails6[[#This Row],[Prix unitaire]] -> 52312.5
B11: ='S8 – Commande TRIM 2'!F5 -> 9100 | C11: 2 | D11: P2 | E11: ='S8 – Commande TRIM 2'!G5 -> 13.5 | G11: =Table_SalesReceiptDetails6[[#This Row],[Quantité]]*Table_SalesReceiptDetails6[[#This Row],[Prix unitaire]] -> 122850
B12: ='S8 – Commande TRIM 2'!F6 -> -200 | C12: 3 | D12: P3 | E12: ='S8 – Commande TRIM 2'!G6 -> 20 | G12: =Table_SalesReceiptDetails6[[#This Row],[Quantité]]*Table_SalesReceiptDetails6[[#This Row],[Prix unitaire]] -> -4000
B13: ='S8 – Commande TRIM 2'!F7 -> 4300 | C13: 4 | D13: P4 | E13: ='S8 – Commande TRIM 2'!G7 -> 29 | G13: =Table_SalesReceiptDetails6[[#This Row],[Quantité]]*Table_SalesReceiptDetails6[[#This Row],[Prix unitaire]] -> 124700
B14: ='S8 – Commande TRIM 2'!F8 -> 7050 | C14: 5 | D14: P5 | E14: ='S8 – Commande TRIM 2'!G8 -> 35 | G14: =Table_SalesReceiptDetails6[[#This Row],[Quantité]]*Table_SalesReceiptDetails6[[#This Row],[Prix unitaire]] -> 246750
B15: ='S8 – Commande TRIM 2'!F9 -> 0 | C15: 6 | D15: P6 | E15: ='S8 – Commande TRIM 2'!G9 -> 42 | G15: =Table_SalesReceiptDetails6[[#This Row],[Quantité]]*Table_SalesReceiptDetails6[[#This Row],[Prix unitaire]] -> 0
B16: ='S8 – Commande TRIM 2'!F10 -> 3600 | C16: 7 | D16: P7 | E16: ='S8 – Commande TRIM 2'!G10 -> 54 | G16: =Table_SalesReceiptDetails6[[#This Row],[Quantité]]*Table_SalesReceiptDetails6[[#This Row],[Prix unitaire]] -> 194400
B17: ='S8 – Commande TRIM 2'!F11 -> 11090 | C17: 8 | D17: P8 | E17: ='S8 – Commande TRIM 2'!G11 -> 59 | G17: =Table_SalesReceiptDetails6[[#This Row],[Quantité]]*Table_SalesReceiptDetails6[[#This Row],[Prix unitaire]] -> 654310
B18: ='S8 – Commande TRIM 2'!F12 -> 0 | C18: 9 | D18: P9 | E18: ='S8 – Commande TRIM 2'!G12 -> 66 | G18: =Table_SalesReceiptDetails6[[#This Row],[Quantité]]*Table_SalesReceiptDetails6[[#This Row],[Prix unitaire]] -> 0
B19: ='S8 – Commande TRIM 2'!F13 -> 1670 | C19: 10 | D19: P10 | E19: ='S8 – Commande TRIM 2'!G13 -> 69 | G19: =Table_SalesReceiptDetails6[[#This Row],[Quantité]]*Table_SalesReceiptDetails6[[#This Row],[Prix unitaire]] -> 115230
B20: ='S8 – Commande TRIM 2'!F14 -> 1200 | C20: 11 | D20: P11 | E20: ='S8 – Commande TRIM 2'!G14 -> 22 | G20: =Table_SalesReceiptDetails6[[#This Row],[Quantité]]*Table_SalesReceiptDetails6[[#This Row],[Prix unitaire]] -> 26400
B21: ='S8 – Commande TRIM 2'!F15 -> 3370 | C21: 12 | D21: P12 | E21: ='S8 – Commande TRIM 2'!G15 -> 43 | G21: =Table_SalesReceiptDetails6[[#This Row],[Quantité]]*Table_SalesReceiptDetails6[[#This Row],[Prix unitaire]] -> 144910
B22: ='S8 – Commande TRIM 2'!F16 -> 1370 | C22: 13 | D22: P13 | E22: ='S8 – Commande TRIM 2'!G16 -> 65 | G22: =Table_SalesReceiptDetails6[[#This Row],[Quantité]]*Table_SalesReceiptDetails6[[#This Row],[Prix unitaire]] -> 89050
G24: =SUM(Table_SalesReceiptDetails6[Total de la ligne]) -> 1766912.5
B25: Pour toute question concernant cette facture, utilisez les informations de contact : | F25: Sous-total | G25: =SUM(Table_SalesReceiptDetails6[Total de la ligne]) -> 1766912.5
B26: Nom, numéro de téléphone, e-mail du contact | E26: T.P.S. | F26: 0.05 | G26: =F26*G25 -> 88345.625
B27: Nous vous remercions de votre confiance. | E27: T.V.Q | F27: 0.09975 | G27: =G25*F27 -> 176249.52
F28: Total | G28: =G25+G26+G27 -> 2031507.6

Sheet Desgagné TRIM 2
C1: Avec Transport Desgagné, vous allez toujours arriver en premier! | D1: Bon de commande
B2: Transport Desgagnés
B3: 123, rue XYZ | D3: N° de commande : | E3: 1256
B4: Québec, G4D 1S5 | D4: Date : | E4: 45704
B5: 410-555-555 | D5: ID du client : | E5: ABC12345
B6: Service@DGT.com
B7: Simul inc
B8: Entreprise Issa
B9: Cégep Limoilou
B10: Québec, G4D 1S5
B11: 0
B12: Vendeur | C12: Tâche | D12: Conditions de paiement | E12: Date d’échéance
B13: Robert Vézina | C13: Représentant | D13: N/30 +5% retard | E13: 17/02/2026
B15: Quantité | C15: Description | D15: Prix unitaire | E15: Total de la ligne
B16: ='S8 – Commande TRIM 2'!P6 -> 290 | C16: voyages 150 m3 | D16: =865 -> 865 | E16: =Facture5[[#This Row],[Prix unitaire]]*Facture5[[#This Row],[Quantité]] -> 250850
B17: ='S8 – Commande TRIM 2'!P7 -> 0.295 | C17: voyages 100 m3 | D17: 745 | E17: =Facture5[[#This Row],[Prix unitaire]]*Facture5[[#This Row],[Quantité]] -> 219.775
D26: Sous-total | E26: =SUM(Facture5[Total de la ligne]) -> 251069.77
B27: Taxes | D27: 0.14975 | E27: =Facture5[[#Totals],[Total de la ligne]]*0.14975 -> 37597.699
B28: TOTAL | E28: =SUM(E26:E27) -> 288667.47
B29: ***Ceci n'est pas une facture ****
B30: NOUS VOUS REMERCIONS DE VOTRE CONFIANCE.

Sheet S8 -Outil - Ventes 
C3: Analyse des ventes
D4: VOIR DOC. LÉA | H4: E *prix de vente + F*50%*Prix de vente | I4: =(C-E-F) | J4: H * Prix coûtant | K4: Analyse complémentaire (ventes perdue)
B5: Produits | C5: Quantités commandées | D5: Ventes potentielles | E5: Ventes réelles en unités | F5: Inventaire de début | G5: Ventes produit saisonniers en unités | H5: Ventes totales (TRIM 1) en $ (sans les taxes à payer) | I5: Inventaire de fin (en unités) | J5: Inventaire de fin (en $) | K5: Produits | L5: Écart (en unité) | M5: Écart (en $) | N5: Besoins commande 2 | O5: Volume unitaire (M3) | P5: Volume total achété (M3)
B6: P1 | C6: ='S8 – Commande TRIM 2'!F4 -> 7750 | D6: ='Ventes potentielle TRIM 2'!C4 -> 7933 | E6: =MIN(C6:D6) -> 7750 | F6: ='Fournisseur 1'!B10 -> 5300 | H6: =(E6*Données!I6)+(G6*50%)*Données!I6 -> 84242.5 | I6: =C6-E6-G6 -> 0 | J6: =I6*Données!H6 -> 0 | K6: =B6 -> P1 | L6: =IF(D6>E6,D6-E6,0) -> 183 | M6: =L6*Données!I6 -> 1989.21 | O6: ='S3 - IMMO'!J4 -> 0.18 | P6: =(E6+N6)*O6 -> 1395
B7: P2 | C7: ='S8 – Commande TRIM 2'!F5 -> 9100 | D7: ='Ventes potentielle TRIM 2'!C5 -> 9228 | E7: =MIN(C7:D7) -> 9100 | F7: ='Fournisseur 1'!B11 -> 6200 | H7: =(E7*Données!I7)+(G7*50%)*Données!I7 -> 197834 | I7: =C7-E7-G7 -> 0 | J7: =I7*Données!H7 -> 0 | K7: =B7 -> P2 | L7: =IF(D7>E7,D7-E7,0) -> 128 | M7: =L7*Données!I7 -> 2782.72 | O7: ='S3 - IMMO'!J5 -> 0.225 | P7: =(E7+N7)*O7 -> 2047.5
B8: P3 | C8: 0 | D8: ='Ventes potentielle TRIM 2'!C6 -> 0 | E8: =MIN(C8:D8) -> 0 | F8: ='Fournisseur 1'!B12 -> 3700 | H8: =(E8*Données!I8)+(G8*50%)*Données!I8 -> 0 | I8: =C8-E8-G8 -> 0 | J8: =I8*Données!H8 -> 0 | K8: =B8 -> P3 | L8: =IF(D8>E8,D8-E8,0) -> 0 | M8: =L8*Données!I8 -> 0 | O8: ='S3 - IMMO'!J6 -> 0.675 | P8: =(E8+N8)*O8 -> 0
B9: P4 | C9: ='S8 – Commande TRIM 2'!F7 -> 4300 | D9: ='Ventes potentielle TRIM 2'!C7 -> 4350 | E9: =MIN(C9:D9) -> 4300 | F9: ='Fournisseur 1'!B13 -> 2900 | H9: =(E9*Données!I9)+(G9*50%)*Données!I9 -> 181718 | I9: =C9-E9-G9 -> 0 | J9: =I9*Données!H9 -> 0 | K9: =B9 -> P4 | L9: =IF(D9>E9,D9-E9,0) -> 50 | M9: =L9*Données!I9 -> 2113 | O9: ='S3 - IMMO'!J7 -> 0.5 | P9: =(E9+N9)*O9 -> 2150
B10: P5 | C10: ='S8 – Commande TRIM 2'!F8 -> 7050 | D10: ='Ventes potentielle TRIM 2'!C8 -> 6999 | E10: =MIN(C10:D10) -> 6999 | F10: ='Fournisseur 1'!B14 -> 4800 | H10: =(E10*Données!I10)+(G10*50%)*Données!I10 -> 414130.83 | I10: =C10-E10-G10 -> 51 | J10: =I10*Données!H10 -> 1785 | K10: =B10 -> P5 | L10: =IF(D10>E10,D10-E10,0) -> 0 | M10: =L10*Données!I10 -> 0 | O10: ='S3 - IMMO'!J8 -> 0.75 | P10: =(E10+N10)*O10 -> 5249.25
B11: P6 | C11: ='S8 – Commande TRIM 2'!F9 -> 0 | D11: ='Ventes potentielle TRIM 2'!C9 -> 0 | E11: =MIN(C11:D11) -> 0 | F11: ='Fournisseur 1'!B15 -> 1700 | H11: =(E11*Données!I11)+(G11*50%)*Données!I11 -> 0 | I11: =C11-E11-G11 -> 0 | J11: =I11*Données!H11 -> 0 | K11: =B11 -> P6 | L11: =IF(D11>E11,D11-E11,0) -> 0 | M11: =L11*Données!I11 -> 0 | O11: ='S3 - IMMO'!J9 -> 0.9 | P11: =(E11+N11)*O11 -> 0
B12: P7 | C12: ='S8 – Commande TRIM 2'!F10 -> 3600 | D12: ='Ventes potentielle TRIM 2'!C10 -> 3651 | E12: =MIN(C12:D12) -> 3600 | F12: ='Fournisseur 1'!B16 -> 2500 | H12: =(E12*Données!I12)+(G12*50%)*Données!I12 -> 295596 | I12: =C12-E12-G12 -> 0 | J12: =I12*Données!H12 -> 0 | K12: =B12 -> P7 | L12: =IF(D12>E12,D12-E12,0) -> 51 | M12: =L12*Données!I12 -> 4187.61 | O12: ='S3 - IMMO'!J10 -> 0.875 | P12: =(E12+N12)*O12 -> 3150
B13: P8 | C13: ='S8 – Commande TRIM 2'!F11 -> 11090 | D13: ='Ventes potentielle TRIM 2'!C11 -> 11111 | E13: =MIN(C13:D13) -> 11090 | F13: ='Fournisseur 1'!B17 -> 7600 | H13: =(E13*Données!I13)+(G13*50%)*Données!I13 -> 950745.7 | I13: =C13-E13-G13 -> 0 | J13: =I13*Données!H13 -> 0 | K13: =B13 -> P8 | L13: =IF(D13>E13,D13-E13,0) -> 21 | M13: =L13*Données!I13 -> 1800.33 | O13: ='S3 - IMMO'!J11 -> 1.8 | P13: =(E13+N13)*O13 -> 19962
B14: P9 | C14: ='S8 – Commande TRIM 2'!F12 -> 0 | D14: ='Ventes potentielle TRIM 2'!C12 -> 0 | E14: =MIN(C14:D14) -> 0 | F14: ='Fournisseur 1'!B18 -> 4300 | H14: =(E14*Données!I14)+(G14*50%)*Données!I14 -> 0 | I14: =C14-E14-G14 -> 0 | J14: =I14*Données!H14 -> 0 | K14: =B14 -> P9 | L14: =IF(D14>E14,D14-E14,0) -> 0 | M14: =L14*Données!I14 -> 0 | O14: ='S3 - IMMO'!J12 -> 0.5625 | P14: =(E14+N14)*O14 -> 0
B15: P10 | C15: ='S8 – Commande TRIM 2'!F13 -> 1670 | D15: ='Ventes potentielle TRIM 2'!C13 -> 1658 | E15: =MIN(C15:D15) -> 1658 | F15: ='Fournisseur 1'!B19 -> 1200 | H15: =(E15*Données!I15)+(G15*50%)*Données!I15 -> 178185.26 | I15: =C15-E15-G15 -> 12 | J15: =I15*Données!H15 -> 828 | K15: =B15 -> P10 | L15: =IF(D15>E15,D15-E15,0) -> 0 | M15: =L15*Données!I15 -> 0 | O15: ='S3 - IMMO'!J13 -> 0.75 | P15: =(E15+N15)*O15 -> 1243.5
B16: P11 | C16: ='S8 – Commande TRIM 2'!F14 -> 1200 | D16: ='Ventes potentielle TRIM 2'!C14 -> 917 | E16: =MIN(C16:D16) -> 917 | F16: ='Fournisseur 1'!B20 -> 900 | G16: =IF(C16<D16,0,C16-D16) -> 283 | H16: =(E16*Données!I16)+(G16*50%)*Données!I16 -> 38349.455 | I16: =C16-E16-G16 -> 0 | J16: =I16*Données!H16 -> 0 | K16: =B16 -> P11 | L16: =IF(D16>E16,D16-E16,0) -> 0 | M16: =L16*Données!I16 -> 0 | O16: ='S3 - IMMO'!J14 -> 0.675 | P16: =(E16+N16)*O16 -> 618.975
B17: P12 | C17: ='S8 – Commande TRIM 2'!F15 -> 3370 | D17: ='Ventes potentielle TRIM 2'!C15 -> 2570 | E17: =MIN(C17:D17) -> 2570 | F17: ='Fournisseur 1'!B21 -> 2600 | G17: =IF(C17<D17,0,C17-D17) -> 800 | H17: =(E17*Données!I17)+(G17*50%)*Données!I17 -> 188298 | I17: =C17-E17-G17 -> 0 | J17: =I17*Données!H17 -> 0 | K17: =B17 -> P12 | L17: =IF(D17>E17,D17-E17,0) -> 0 | M17: =L17*Données!I17 -> 0 | O17: ='S3 - IMMO'!J15 -> 1.75 | P17: =(E17+N17)*O17 -> 4497.5
B18: P13 | C18: ='S8 – Commande TRIM 2'!F16 -> 1370 | D18: ='Ventes potentielle TRIM 2'!C16 -> 1031 | E18: =MIN(C18:D18) -> 1031 | F18: ='Fournisseur 1'!B22 -> 1100 | G18: =IF(C18<D18,0,C18-D18) -> 339 | H18: =(E18*Données!I18)+(G18*50%)*Données!I18 -> 119593.81 | I18: =C18-E18-G18 -> 0 | J18: =I18*Données!H18 -> 0 | K18: =B18 -> P13 | L18: =IF(D18>E18,D18-E18,0) -> 0 | M18: =L18*Données!I18 -> 0 | O18: ='S3 - IMMO'!J16 -> 1.25 | P18: =(E18+N18)*O18 -> 1288.75
C19: =SUM(C6:C18) -> 50500 | D19: =SUM(D6:D18) -> 49448 | E19: =SUM(E6:E18) -> 49015 | F19: =SUM(F6:F18) -> 44800 | G19: =SUM(G6:G18) -> 1422 | H19: =SUM(H6:H18) -> 2648693.6 | I19: =SUM(I6:I18) -> 63 | J19: =SUM(J6:J18) -> 2613 | L19: =SUM(L6:L18) -> 433 | M19: =SUM(M6:M18) -> 12872.87 | O19: ='S3 - IMMO'!J17 -> Volume total (étalage) | P19: =SUM(P6:P18) -> 41602.475 | Q19: m3

Sheet S8-Outil - Charges 
A1: Outil - Coûts TRIM 2
A2: Tableau des indicateurs: | H2: Sections à compléter
A3: Quantités vendues | B3: ='S8 -Outil - Ventes '!E19 -> 49015 | C3: unités
A4: Volume acheté | B4: ='S8 -Outil - Ventes '!P19 -> 41602.475 | C4: M3 | H4: Taux de taxes = | I4: 0.14975
A5: Valeur des ventes | B5: ='S8 -Outil - Ventes '!H19 -> 2648693.6 | H5: Trimestre/an = | I5: 4
A6: Volume du bâtiment | B6: ='S3 - IMMO'!E8 -> 23269.807 | C6: M3 | H6: Nombre de sem = | I6: 13
H7: Mois/Trimestre = | I7: 3
A9: Coût des marchandises vendues | D9: Salaires (selon Ventes Trim 1)
A11: Inventaire du début | B11: ='S5 -Outil - Ventes'!J19 -> 10821
A12: Achats | B12: ='Bon de commande TRIM 2'!G24 -> 1766912.5 | E12: Capacité TRIM | F12: UDM | G12: salaire/semaine | H12: Nombre | I12: Salaire TRIM 1
A13: Fret à l'achat | B13: ='S8 – Commande TRIM 2'!H29 -> 251069.77 | D13: Gestionnaire | G13: 1000 | H13: 1 | I13: =H13*G13*$I$6 -> 13000
A14: Inventaire de fin | B14: ='S8 -Outil - Ventes '!J19 -> 2613 | D14: Cassier.e.s | E14: 13000 | F14: un | G14: 600 | H14: =B3/E14 -> 3.7703846 | I14: =H14*G14*$I$6 -> 29409
D15: Comptable-gestionnaires | E15: 35100 | F15: un | G15: 950 | H15: =B3/E15 -> 1.3964387 | I15: =H15*G15*$I$6 -> 17246.019
D16: Vendeur.e.s | E16: 13000 | F16: un | G16: 0.025 | H16: =B3/E16 -> 3.7703846 | I16: =G16*B5 -> 66217.339
D17: Manutentionnaire.s | E17: 30000 | F17: m3 | G17: 620 | H17: =B4/E17 -> 1.3867492 | I17: =H17*G17*$I$6 -> 11177.198
D18: Concierge.s | E18: 12000 | F18: m3 | G18: 640 | H18: =B6/E18 -> 1.9391506 | I18: =H18*G18*$I$6 -> 16133.733
D19: Salaires | H19: =ROUND(SUM(H13:H18),1) -> 13.3 | I19: =SUM(I13:I18) -> 153183.29
D20: Retenues à la sources = | E20: 0.26101 | I20: =I19*E20 -> 39982.37
D21: Avantages sociaux = | E21: 0.20317 | I21: =I19*E21 -> 31122.249
D22: Assurances coll = | E22: 12 | I22: =E22*H19*13 -> 2074.8
D23: Fonds de pension = | E23: 0.04 | I23: =I19*E23 -> 6127.3315
D24: Vacances = | E24: 0.04 | I24: =E24*I19 -> 6127.3315
A28: Téléphonie et système de communication | F28: Frais de livraison aux clients:
A29: Coût location/ système / mois | B29: 250
A30: Nombre d'employé par location | B30: 4 | G30: qté vendue | H30: vol. unitaire | I30: Total M3
A31: Nombre de location | B31: =CEILING((H13+H14+H15+H16)/B30,1) -> 3 | F31: P7 | G31: ='S8 -Outil - Ventes '!E12 -> 3600 | H31: =Données!G12 -> 0.875 | I31: =G31*H31 -> 3150
A32: Coût total par mois = | B32: =B29*B31 -> 750 | F32: P8 | G32: ='S8 -Outil - Ventes '!E13 -> 11090 | H32: =Données!G13 -> 1.8 | I32: =G32*H32 -> 19962
A33: Coût par trimestre = | B33: =B32*I7 -> 2250 | F33: P9 | G33: ='S8 -Outil - Ventes '!E14 -> 0 | H33: =Données!G14 -> 0.5625 | I33: =G33*H33 -> 0
A34: Taxes | B34: =B33*I4 -> 336.9375 | I34: =SUM(I31:I33) -> 23112 | J34: m3
H35: voyage = | I35: =ROUNDDOWN(I34/G38,0) -> 154 | J35: =I35*G38 -> 23100
A36: Électricité (même valeur pour tous) - Dépenses fixes (facture équilibrée) | H36: volume restant = | I36: =I34-(I35*G38) -> 12
A37: Total | D37: 18500 | I37: $ voyage
A38: Taxes | D38: =D37*I4 -> 2770.375 | F38: Camion | G38: 150 | H38: m3 | I38: 640 | J38: =I35*I38 -> 98560
G39: 100 | H39: m3 | I39: 500 | J39: =I39*(I36/G39) -> 60
F40: Frais de livraison = | J40: =J38+J39 -> 98620
A41: Frais d'entretien | F41: Taxes | J41: =J40*I4 -> 14768.345
B42: $/an | C42: Référence | D42: $T1
A43: Bâti. Ou Amélior. Loc. | B43: 8 | C43: /an /m3 | D43: ='S3 - IMMO'!E8*'S8-Outil - Charges '!B43 -> 186158.46
A44: Caisses enregis. | B44: 600 | C44: /an / par utilisation | D44: =('S3 - IMMO'!N5*'S8-Outil - Charges '!B44)/4 -> 1050
A45: Équip. De cuisine | B45: 0.1 | C45: $ coût total de l'équipement/an | D45: =('S3 - IMMO'!C37*'S8-Outil - Charges '!B45)/4 -> 125 | F45: Loyer | G45: (Pour ceux qui louent le bâtiment)
A46: Équipement de manutention | B46: 0.1 | C46: $ coût total de l'équipement / an / utilisation | D46: =(('S3 - IMMO'!C36*B46)*H17)/4 -> 1203.0049 | F46: Location mensuelle | G46: =1.35*B6 -> 31414.24
A47: Téléphonie et comm. | B47: 0 | C47: inclus dans la location | F47: Location trimestrielle | G47: =I7*G46 -> 94242.719
A48: Ameublement | B48: 0.05 | C48: $ coût total de l'équipement/an | D48: =('S4 - Montage financier'!C8*'S8-Outil - Charges '!B48)/4 -> 1314.1432 | F48: Taxes | G48: =G47*I4 -> 14112.847
A49: Équip. Inform | B49: 500 | C49: /an / par utilisation | D49: =(B49*(H13+H15+H16))/4 -> 770.85292
A50: Total | D50: =SUM(D43:D49) -> 190621.46 | F50: Publicité
A51: Taxes | D51: =D50*I4 -> 28545.563
F52: % ventes M1 | G52: /mois
A53: Assurances: | F53: 0.12 | G53: 3000
B54: $/an | C54: Référence | D54: $T1 | F54: 0 | G54: =G53*3 -> 9000
A55: Bâti. Ou Amélior. Loc. | B55: 0.015 | C55: $ coût total par an | D55: =('S4 - Montage financier'!C6*'S8-Outil - Charges '!B55)/4 -> 1308.75 | F55: Total | G55: =G54+F54 -> 9000
A56: Équipements (tous) | B56: 0.03 | C56: $ coût total par an | D56: =(B56*('S4 - Montage financier'!C7+'S4 - Montage financier'!C9+'S4 - Montage financier'!C10+'S4 - Montage financier'!C11))/4 -> 834 | F56: Taxes | G56: =G55*I4 -> 1347.75
A57: Mobilier (tous) | B57: 0.005 | C57: $ coût total par an | D57: =(B57*('S3 - IMMO'!C30+'S3 - IMMO'!C31+'S3 - IMMO'!C32+'S3 - IMMO'!C33+'S3 - IMMO'!C34))/4 -> 131.41432
A58: Total | D58: =SUM(D55:D57) -> 2274.1643
A59: Taxes 9% (à inclure) | B59: 0.09 | D59: =D58*(1+B59) -> 2478.8391 | F59: Fournitures de bureau:
F61: $ Employé / an | G61: Équivalent temps plein
A62: Taxes municipales: | B62: Ne s'applique pas à la location | F62: 700 | G62: =H13+H14+H15+H16 -> 9.937208
D63: $T1 | F63: Total | G63: =G62*F62/I5 -> 1739.0114
A64: Taxes municipales | B64: 0.025 | C64: /an du coût Terrain et Bâtiment | D64: =(('S4 - Montage financier'!L6+'S4 - Montage financier'!L7)*'S8-Outil - Charges '!B64)/4 -> 10907.722 | F64: Taxes | G64: =G63*I4 -> 260.41696
A65: Taxes | D65: =D64*I4 -> 1633.4314
A72: Amortissement (pas taxables) | F72: 15 | G72: 5000 | H72: un vendues
A73: Biens | B73: Amortissement annuel | C73: Valeur | D73: Charges d'amort. TRIM | F73: Produits vendus = | G73: =B3 -> 49015 | H73: un vendues
A74: Terrain | B74: NA | C74: ='S4 - Montage financier'!L6 -> 1483450.2 | F74: Frais de banque | G74: =G73/G72*F72 -> 147.045
A75: Bâtiment | B75: 0.04
A76: Améliorations locatives | B76: 0.2 | C76: ='S4 - Montage financier'!C6 -> 349000 | D76: =(C76*B76)/4 -> 17450
A77: Site transactionnel | B77: 0.5
A78: Modules de caisses enre. | B78: 0.2 | C78: ='S4 - Montage financier'!C7 -> 31500 | D78: =(C78*B78)/4 -> 1575
A79: Équipement de cuisine | B79: 0.2 | C79: ='S4 - Montage financier'!C11 -> 5000 | D79: =(C79*B79)/4 -> 250 | F79: Honoraires professionnelles
A80: Équipement de manutention | B80: 0.2 | C80: ='S4 - Montage financier'!C10 -> 34700 | D80: =(C80*B80)/4 -> 1735 | F80: 0.0035 | G80: des ventes totales
A81: Équipement informatique | B81: 0.3 | C81: ='S4 - Montage financier'!C9 -> 40000 | D81: =(C81*B81)/4 -> 3000 | F81: Total | G81: =F80*B5 -> 9270.4274
A82: Ameublements | B82: 0.2 | C82: ='S4 - Montage financier'!C8 -> 105131.45 | D82: =(C82*B82)/4 -> 5256.5727 | F82: Taxes | G82: =G81*I4 -> 1388.2465
F84: Si commerce électronique
F86: Frais de site électronique
F87: Domaine = | G87: 750 | H87: /an
F88: Total | G88: =G87/I5 -> 187.5 | H88: /trimestre
F89: Espace de stockage= | G89: 155 | H89: /mois
F90: Total | G90: =G89*I7 -> 465
F91: Frais de site total | G91: =G90+G88 -> 652.5
F92: Taxes | G92: =G91*I4 -> 97.711875
F94: Frais de transactions via internet
F95: Taux | G95: 0.025
F96: Frais de transaction
F97: Taxes | G97: =G96*I4 -> 0

Sheet S8 -Emprunt 
B1: Hypothèque | J1: Capital de risque | R1: Marge de crédit
C3: Valeur de l'emprunt : | D3: ='S4 - Montage financier'!D4 -> 59290 | K3: Valeur de l'emprunt : | L3: ='S4 - Montage financier'!D5 -> 152007 | S3: Valeur de l'emprunt : | T3: ='S4 - Montage financier'!D2 -> 670000 | AA3: Valeur de l'emprunt : | AB3: 0
C4: Taux de l'emprunt : | D4: 0.06 | K4: Taux de l'emprunt : | L4: 0.1 | S4: Taux de l'emprunt : | T4: 0.06 | AA4: Taux de l'emprunt : | AB4: 0
C5: Durée de l'emprunt : | D5: 10 | E5: ans | K5: Durée de l'emprunt : | L5: 10 | M5: ans | S5: Durée de l'emprunt : | T5: 10 | U5: ans | AA5: Durée de l'emprunt : | AB5: 0 | AC5: ans
C6: Versement : | D6: =-PMT(D4/12,D5*12,D3) -> 658.24056 | E6: par mois | K6: Versement : | L6: =-PMT(L4/12,L5*12,L3) -> 2008.7837 | M6: par mois | S6: Versement : | T6: =-PMT(T4/12,T5*12,T3) -> 7438.3736 | U6: par mois | AA6: Versement : | AB6: =-PMT(AB4/12,AB5*12,AB3) -> #NUM! | AC6: par mois
B9: Date | C9: portion du capital | D9: portion intérêt | E9: capital cumulé | F9: intérêt cumulé | G9: solde | J9: Date | K9: portion du capital | L9: portion intérêt | M9: capital cumulé | N9: intérêt cumulé | O9: solde | R9: Date | S9: portion du capital | T9: portion intérêt | U9: capital cumulé | V9: intérêt cumulé | W9: solde | Z9: Date | AA9: portion du capital | AB9: portion intérêt | AC9: capital cumulé | AD9: intérêt cumulé | AE9: solde
B10: M1 | C10: =D6-D10 -> 361.79056 | D10: =D4/12*D3 -> 296.45 | E10: =C10 -> 361.79056 | F10: =D10 -> 296.45 | G10: =D3-C10 -> 58928.209 | J10: =B10 -> M1 | K10: =L6-L10 -> 742.05871 | L10: =L4/12*L3 -> 1266.725 | M10: =K10 -> 742.05871 | N10: =L10 -> 1266.725 | O10: =L3-K10 -> 151264.94 | S10: =T6-T10 -> 4088.3736 | T10: =T4/12*T3 -> 3350 | U10: =S10 -> 4088.3736 | V10: =T10 -> 3350 | W10: =T3-S10 -> 665911.63 | AA10: =AB6-AB10 -> #NUM! | AB10: =AB4/12*AB3 -> 0 | AC10: =AA10 -> #NUM! | AD10: =AB10 -> 0 | AE10: =AB3-AA10 -> #NUM!
B11: M2 | C11: =$D$6-D11 -> 363.59951 | D11: =$D$4/12*G10 -> 294.64105 | E11: =E10+C11 -> 725.39006 | F11: =F10+D11 -> 591.09105 | G11: =G10-C11 -> 58564.61 | J11: =B11 -> M2 | K11: =$L$6-L11 -> 748.24253 | L11: =$L$4/12*O10 -> 1260.5412 | M11: =M10+K11 -> 1490.3012 | N11: =N10+L11 -> 2527.2662 | O11: =O10-K11 -> 150516.7 | S11: =$T$6-T11 -> 4108.8155 | T11: =$T$4/12*W10 -> 3329.5581 | U11: =U10+S11 -> 8197.1891 | V11: =V10+T11 -> 6679.5581 | W11: =W10-S11 -> 661802.81 | AA11: =$AB$6-AB11 -> #NUM! | AB11: =$AB$4/12*AE10 -> #NUM! | AC11: =AC10+AA11 -> #NUM! | AD11: =AD10+AB11 -> #NUM! | AE11: =AE10-AA11 -> #NUM!
B12: M3 | C12: =$D$6-D12 -> 365.41751 | D12: =$D$4/12*G11 -> 292.82305 | E12: =E11+C12 -> 1090.8076 | F12: =F11+D12 -> 883.9141 | G12: =G11-C12 -> 58199.192 | J12: =B12 -> M3 | K12: =$L$6-L12 -> 754.47788 | L12: =$L$4/12*O11 -> 1254.3058 | M12: =M11+K12 -> 2244.7791 | N12: =N11+L12 -> 3781.572 | O12: =O11-K12 -> 149762.22 | S12: =$T$6-T12 -> 1923.3502 | T12: =$L$4/12*W11 -> 5515.0234 | U12: =U11+S12 -> 10120.539 | V12: =V11+T12 -> 12194.582 | W12: =W11-S12 -> 659879.46 | AA12: =$T$6-AB12 -> #NUM! | AB12: =$AB$4/12*AE11 -> #NUM! | AC12: =AC11+AA12 -> #NUM! | AD12: =AD11+AB12 -> #NUM! | AE12: =AE11-AA12 -> #NUM!
B13: M4 | C13: =$D$6-D13 -> 367.24459 | D13: =$D$4/12*G12 -> 290.99596 | E13: =E12+C13 -> 1458.0522 | F13: =F12+D13 -> 1174.9101 | G13: =G12-C13 -> 57831.948 | J13: =B13 -> M4 | K13: =$L$6-L13 -> 760.7652 | L13: =$L$4/12*O12 -> 1248.0185 | M13: =M12+K13 -> 3005.5443 | N13: =N12+L13 -> 5029.5905 | O13: =O12-K13 -> 149001.46 | S13: =$T$6-T13 -> 1939.3781 | T13: =$L$4/12*W12 -> 5498.9955 | U13: =U12+S13 -> 12059.917 | V13: =V12+T13 -> 17693.577 | W13: =W12-S13 -> 657940.08 | AA13: =$T$6-AB13 -> #NUM! | AB13: =$AB$4/12*AE12 -> #NUM! | AC13: =AC12+AA13 -> #NUM! | AD13: =AD12+AB13 -> #NUM! | AE13: =AE12-AA13 -> #NUM!
B14: M5 | C14: =$D$6-D14 -> 369.08082 | D14: =$D$4/12*G13 -> 289.15974 | E14: =E13+C14 -> 1827.133 | F14: =F13+D14 -> 1464.0698 | G14: =G13-C14 -> 57462.867 | J14: =B14 -> M5 | K14: =$L$6-L14 -> 767.10491 | L14: =$L$4/12*O13 -> 1241.6788 | M14: =M13+K14 -> 3772.6492 | N14: =N13+L14 -> 6271.2693 | O14: =O13-K14 -> 148234.35 | S14: =$T$6-T14 -> 1955.5396 | T14: =$L$4/12*W13 -> 5482.834 | U14: =U13+S14 -> 14015.457 | V14: =V13+T14 -> 23176.411 | W14: =W13-S14 -> 655984.54 | AA14: =$T$6-AB14 -> #NUM! | AB14: =$AB$4/12*AE13 -> #NUM! | AC14: =AC13+AA14 -> #NUM! | AD14: =AD13+AB14 -> #NUM! | AE14: =AE13-AA14 -> #NUM!
B15: M6 | C15: =$D$6-D15 -> 370.92622 | D15: =$D$4/12*G14 -> 287.31434 | E15: =E14+C15 -> 2198.0592 | F15: =F14+D15 -> 1751.3841 | G15: =G14-C15 -> 57091.941 | J15: =B15 -> M6 | K15: =$L$6-L15 -> 773.49745 | L15: =$L$4/12*O14 -> 1235.2863 | M15: =M14+K15 -> 4546.1467 | N15: =N14+L15 -> 7506.5556 | O15: =O14-K15 -> 147460.85 | S15: =$T$6-T15 -> 1971.8358 | T15: =$L$4/12*W14 -> 5466.5379 | U15: =U14+S15 -> 15987.293 | V15: =V14+T15 -> 28642.949 | W15: =W14-S15 -> 654012.71 | AA15: =$T$6-AB15 -> #NUM! | AB15: =$AB$4/12*AE14 -> #NUM! | AC15: =AC14+AA15 -> #NUM! | AD15: =AD14+AB15 -> #NUM! | AE15: =AE14-AA15 -> #NUM!
B16: M7 | C16: =$D$6-D16 -> 372.78085 | D16: =$D$4/12*G15 -> 285.4597 | E16: =E15+C16 -> 2570.8401 | F16: =F15+D16 -> 2036.8438 | G16: =G15-C16 -> 56719.16 | J16: =B16 -> M7 | K16: =$L$6-L16 -> 779.94326 | L16: =$L$4/12*O15 -> 1228.8404 | M16: =M15+K16 -> 5326.0899 | N16: =N15+L16 -> 8735.396 | O16: =O15-K16 -> 146680.91 | S16: =$T$6-T16 -> 1988.2677 | T16: =$L$4/12*W15 -> 5450.1059 | U16: =U15+S16 -> 17975.561 | V16: =V15+T16 -> 34093.055 | W16: =W15-S16 -> 652024.44 | AA16: =$T$6-AB16 -> #NUM! | AB16: =$AB$4/12*AE15 -> #NUM! | AC16: =AC15+AA16 -> #NUM! | AD16: =AD15+AB16 -> #NUM! | AE16: =AE15-AA16 -> #NUM!
B17: M8 | C17: =$D$6-D17 -> 374.64476 | D17: =$D$4/12*G16 -> 283.5958 | E17: =E16+C17 -> 2945.4848 | F17: =F16+D17 -> 2320.4396 | G17: =G16-C17 -> 56344.515 | J17: =B17 -> M8 | K17: =$L$6-L17 -> 786.44279 | L17: =$L$4/12*O16 -> 1222.3409 | M17: =M16+K17 -> 6112.5327 | N17: =N16+L17 -> 9957.7369 | O17: =O16-K17 -> 145894.47 | S17: =$T$6-T17 -> 2004.8366 | T17: =$L$4/12*W16 -> 5433.537 | U17: =U16+S17 -> 19980.397 | V17: =V16+T17 -> 39526.592 | W17: =W16-S17 -> 650019.6 | AA17: =$T$6-AB17 -> #NUM! | AB17: =$AB$4/12*AE16 -> #NUM! | AC17: =AC16+AA17 -> #NUM! | AD17: =AD16+AB17 -> #NUM! | AE17: =AE16-AA17 -> #NUM!
B18: M9 | C18: =$D$6-D18 -> 376.51798 | D18: =$D$4/12*G17 -> 281.72258 | E18: =E17+C18 -> 3322.0028 | F18: =F17+D18 -> 2602.1622 | G18: =G17-C18 -> 55967.997 | J18: =B18 -> M9 | K18: =$L$6-L18 -> 792.99648 | L18: =$L$4/12*O17 -> 1215.7872 | M18: =M17+K18 -> 6905.5292 | N18: =N17+L18 -> 11173.524 | O18: =O17-K18 -> 145101.47 | S18: =$T$6-T18 -> 2021.5436 | T18: =$L$4/12*W17 -> 5416.83 | U18: =U17+S18 -> 22001.941 | V18: =V17+T18 -> 44943.422 | W18: =W17-S18 -> 647998.06 | AA18: =$T$6-AB18 -> #NUM! | AB18: =$AB$4/12*AE17 -> #NUM! | AC18: =AC17+AA18 -> #NUM! | AD18: =AD17+AB18 -> #NUM! | AE18: =AE17-AA18 -> #NUM!
B19: M10 | C19: =$D$6-D19 -> 378.40057 | D19: =$D$4/12*G18 -> 279.83999 | E19: =E18+C19 -> 3700.4034 | F19: =F18+D19 -> 2882.0022 | G19: =G18-C19 -> 55589.597 | J19: =B19 -> M10 | K19: =$L$6-L19 -> 799.60478 | L19: =$L$4/12*O18 -> 1209.1789 | M19: =M18+K19 -> 7705.134 | N19: =N18+L19 -> 12382.703 | O19: =O18-K19 -> 144301.87 | S19: =$T$6-T19 -> 2038.3898 | T19: =$L$4/12*W18 -> 5399.9838 | U19: =U18+S19 -> 24040.331 | V19: =V18+T19 -> 50343.406 | W19: =W18-S19 -> 645959.67 | AA19: =$T$6-AB19 -> #NUM! | AB19: =$AB$4/12*AE18 -> #NUM! | AC19: =AC18+AA19 -> #NUM! | AD19: =AD18+AB19 -> #NUM! | AE19: =AE18-AA19 -> #NUM!
B20: M11 | C20: =$D$6-D20 -> 380.29257 | D20: =$D$4/12*G19 -> 277.94798 | E20: =E19+C20 -> 4080.6959 | F20: =F19+D20 -> 3159.9502 | G20: =G19-C20 -> 55209.304 | J20: =B20 -> M11 | K20: =$L$6-L20 -> 806.26816 | L20: =$L$4/12*O19 -> 1202.5156 | M20: =M19+K20 -> 8511.4021 | N20: =N19+L20 -> 13585.219 | O20: =O19-K20 -> 143495.6 | S20: =$T$6-T20 -> 2055.3764 | T20: =$L$4/12*W19 -> 5382.9972 | U20: =U19+S20 -> 26095.707 | V20: =V19+T20 -> 55726.403 | W20: =W19-S20 -> 643904.29 | AA20: =$T$6-AB20 -> #NUM! | AB20: =$AB$4/12*AE19 -> #NUM! | AC20: =AC19+AA20 -> #NUM! | AD20: =AD19+AB20 -> #NUM! | AE20: =AE19-AA20 -> #NUM!
B21: M12 | C21: =$D$6-D21 -> 382.19404 | D21: =$D$4/12*G20 -> 276.04652 | E21: =E20+C21 -> 4462.89 | F21: =F20+D21 -> 3435.9967 | G21: =G20-C21 -> 54827.11 | J21: =B21 -> M12 | K21: =$L$6-L21 -> 812.98706 | L21: =$L$4/12*O20 -> 1195.7966 | M21: =M20+K21 -> 9324.3892 | N21: =N20+L21 -> 14781.015 | O21: =O20-K21 -> 142682.61 | S21: =$T$6-T21 -> 2072.5045 | T21: =$L$4/12*W20 -> 5365.8691 | U21: =U20+S21 -> 28168.212 | V21: =V20+T21 -> 61092.272 | W21: =W20-S21 -> 641831.79 | AA21: =$T$6-AB21 -> #NUM! | AB21: =$AB$4/12*AE20 -> #NUM! | AC21: =AC20+AA21 -> #NUM! | AD21: =AD20+AB21 -> #NUM! | AE21: =AE20-AA21 -> #NUM!
B22: M13 | C22: =$D$6-D22 -> 384.10501 | D22: =$D$4/12*G21 -> 274.13555 | E22: =E21+C22 -> 4846.995 | F22: =F21+D22 -> 3710.1323 | G22: =G21-C22 -> 54443.005 | J22: =B22 -> M13 | K22: =$L$6-L22 -> 819.76195 | L22: =$L$4/12*O21 -> 1189.0218 | M22: =M21+K22 -> 10144.151 | N22: =N21+L22 -> 15970.037 | O22: =O21-K22 -> 141862.85 | S22: =$T$6-T22 -> 2089.7754 | T22: =$L$4/12*W21 -> 5348.5982 | U22: =U21+S22 -> 30257.987 | V22: =V21+T22 -> 66440.87 | W22: =W21-S22 -> 639742.01 | AA22: =$T$6-AB22 -> #NUM! | AB22: =$AB$4/12*AE21 -> #NUM! | AC22: =AC21+AA22 -> #NUM! | AD22: =AD21+AB22 -> #NUM! | AE22: =AE21-AA22 -> #NUM!
B23: M14 | C23: =$D$6-D23 -> 386.02553 | D23: =$D$4/12*G22 -> 272.21503 | E23: =E22+C23 -> 5233.0205 | F23: =F22+D23 -> 3982.3473 | G23: =G22-C23 -> 54056.979 | J23: =B23 -> M14 | K23: =$L$6-L23 -> 826.5933 | L23: =$L$4/12*O22 -> 1182.1904 | M23: =M22+K23 -> 10970.744 | N23: =N22+L23 -> 17152.227 | O23: =O22-K23 -> 141036.26 | S23: =$T$6-T23 -> 2107.1902 | T23: =$L$4/12*W22 -> 5331.1834 | U23: =U22+S23 -> 32365.177 | V23: =V22+T23 -> 71772.054 | W23: =W22-S23 -> 637634.82 | AA23: =$T$6-AB23 -> #NUM! | AB23: =$AB$4/12*AE22 -> #NUM! | AC23: =AC22+AA23 -> #NUM! | AD23: =AD22+AB23 -> #NUM! | AE23: =AE22-AA23 -> #NUM!
... B36: M27 | C36: =$D$6-D36 -> 411.88391 | D36: =$D$4/12*G35 -> 246.35664 | E36: =E35+C36 -> 10430.556 | F36: =F35+D36 -> 7341.9394 | G36: =G35-C36 -> 48859.444 | J36: =B36 -> M27 | K36: =$L$6-L36 -> 920.75799 | L36: =$L$4/12*O35 -> 1088.0257 | M36: =M35+K36 -> 22364.672 | N36: =N35+L36 -> 31872.488 | O36: =O35-K36 -> 129642.33 | S36: =$T$6-T36 -> 2347.2392 | T36: =$L$4/12*W35 -> 5091.1344 | U36: =U35+S36 -> 61411.108 | V36: =V35+T36 -> 139424.98 | W36: =W35-S36 -> 608588.89 | AA36: =$T$6-AB36 -> #NUM! | AB36: =$AB$4/12*AE35 -> #NUM! | AC36: =AC35+AA36 -> #NUM! | AD36: =AD35+AB36 -> #NUM! | AE36: =AE35-AA36 -> #NUM!
B37: M28 | C37: =$D$6-D37 -> #VALUE! | D37: =B6*B37/I5 -> #VALUE! | E37: =E36+C37 -> #VALUE! | F37: =F36+D37 -> #VALUE! | G37: =G36-C37 -> #VALUE! | J37: =B37 -> M28 | K37: =$L$6-L37 -> 928.43097 | L37: =$L$4/12*O36 -> 1080.3527 | M37: =M36+K37 -> 23293.103 | N37: =N36+L37 -> 32952.841 | O37: =O36-K37 -> 128713.9 | S37: =$T$6-T37 -> 2366.7995 | T37: =$L$4/12*W36 -> 5071.5741 | U37: =U36+S37 -> 63777.908 | V37: =V36+T37 -> 144496.55 | W37: =W36-S37 -> 606222.09 | AA37: =$T$6-AB37 -> #NUM! | AB37: =$AB$4/12*AE36 -> #NUM! | AC37: =AC36+AA37 -> #NUM! | AD37: =AD36+AB37 -> #NUM! | AE37: =AE36-AA37 -> #NUM!
B38: M29 | C38: =$D$6-D38 -> #VALUE! | D38: =H14*B38/I5 -> #VALUE! | E38: =E37+C38 -> #VALUE! | F38: =F37+D38 -> #VALUE! | G38: =G37-C38 -> #VALUE! | J38: =B38 -> M29 | K38: =$L$6-L38 -> 936.1679 | L38: =$L$4/12*O37 -> 1072.6158 | M38: =M37+K38 -> 24229.271 | N38: =N37+L38 -> 34025.457 | O38: =O37-K38 -> 127777.73 | S38: =$T$6-T38 -> 2386.5229 | T38: =$L$4/12*W37 -> 5051.8508 | U38: =U37+S38 -> 66164.431 | V38: =V37+T38 -> 149548.4 | W38: =W37-S38 -> 603835.57 | AA38: =$T$6-AB38 -> #NUM! | AB38: =$AB$4/12*AE37 -> #NUM! | AC38: =AC37+AA38 -> #NUM! | AD38: =AD37+AB38 -> #NUM! | AE38: =AE37-AA38 -> #NUM!
B39: M30 | C39: =$D$6-D39 -> #VALUE! | D39: #VALUE! | E39: =E38+C39 -> #VALUE! | F39: =F38+D39 -> #VALUE! | G39: =G38-C39 -> #VALUE! | J39: =B39 -> M30 | K39: =$L$6-L39 -> 943.9693 | L39: =$L$4/12*O38 -> 1064.8144 | M39: =M38+K39 -> 25173.24 | N39: =N38+L39 -> 35090.271 | O39: =O38-K39 -> 126833.76 | S39: =$T$6-T39 -> 2406.4106 | T39: =$L$4/12*W38 -> 5031.9631 | U39: =U38+S39 -> 68570.841 | V39: =V38+T39 -> 154580.37 | W39: =W38-S39 -> 601429.16 | AA39: =$T$6-AB39 -> #NUM! | AB39: =$AB$4/12*AE38 -> #NUM! | AC39: =AC38+AA39 -> #NUM! | AD39: =AD38+AB39 -> #NUM! | AE39: =AE38-AA39 -> #NUM!
B40: M31 | C40: =$D$6-D40 -> #VALUE! | D40: =$D$4/12*G39 -> #VALUE! | E40: =E39+C40 -> #VALUE! | F40: =F39+D40 -> #VALUE! | G40: =G39-C40 -> #VALUE! | J40: =B40 -> M31 | K40: =$L$6-L40 -> 951.83571 | L40: =$L$4/12*O39 -> 1056.948 | M40: =M39+K40 -> 26125.076 | N40: =N39+L40 -> 36147.219 | O40: =O39-K40 -> 125881.92 | S40: =$T$6-T40 -> 2426.464 | T40: =$L$4/12*W39 -> 5011.9097 | U40: =U39+S40 -> 70997.305 | V40: =V39+T40 -> 159592.28 | W40: =W39-S40 -> 599002.69 | AA40: =$T$6-AB40 -> #NUM! | AB40: =$AB$4/12*AE39 -> #NUM! | AC40: =AC39+AA40 -> #NUM! | AD40: =AD39+AB40 -> #NUM! | AE40: =AE39-AA40 -> #NUM!
B41: M32 | C41: =$D$6-D41 -> #VALUE! | D41: =$D$4/12*G40 -> #VALUE! | E41: =E40+C41 -> #VALUE! | F41: =F40+D41 -> #VALUE! | G41: =G40-C41 -> #VALUE! | J41: =B41 -> M32 | K41: =$L$6-L41 -> 959.76767 | L41: =$L$4/12*O40 -> 1049.016 | M41: =M40+K41 -> 27084.843 | N41: =N40+L41 -> 37196.235 | O41: =O40-K41 -> 124922.16 | S41: =$T$6-T41 -> 2446.6845 | T41: =$L$4/12*W40 -> 4991.6891 | U41: =U40+S41 -> 73443.99 | V41: =V40+T41 -> 164583.97 | W41: =W40-S41 -> 596556.01 | AA41: =$T$6-AB41 -> #NUM! | AB41: =$AB$4/12*AE40 -> #NUM! | AC41: =AC40+AA41 -> #NUM! | AD41: =AD40+AB41 -> #NUM! | AE41: =AE40-AA41 -> #NUM!
B42: M33 | C42: =$D$6-D42 -> #VALUE! | D42: =$D$4/12*G41 -> #VALUE! | E42: =E41+C42 -> #VALUE! | F42: =F41+D42 -> #VALUE! | G42: =G41-C42 -> #VALUE! | J42: =B42 -> M33 | K42: =$L$6-L42 -> 967.76574 | L42: =$L$4/12*O41 -> 1041.018 | M42: =M41+K42 -> 28052.609 | N42: =N41+L42 -> 38237.253 | O42: =O41-K42 -> 123954.39 | S42: =$T$6-T42 -> 2467.0735 | T42: =$L$4/12*W41 -> 4971.3001 | U42: =U41+S42 -> 75911.063 | V42: =V41+T42 -> 169555.27 | W42: =W41-S42 -> 594088.94 | AA42: =$T$6-AB42 -> #NUM! | AB42: =$AB$4/12*AE41 -> #NUM! | AC42: =AC41+AA42 -> #NUM! | AD42: =AD41+AB42 -> #NUM! | AE42: =AE41-AA42 -> #NUM!
B43: M34 | C43: =$D$6-D43 -> #VALUE! | D43: =$D$4/12*G42 -> #VALUE! | E43: =E42+C43 -> #VALUE! | F43: =F42+D43 -> #VALUE! | G43: =G42-C43 -> #VALUE! | J43: =B43 -> M34 | K43: =$L$6-L43 -> 975.83045 | L43: =$L$4/12*O42 -> 1032.9533 | M43: =M42+K43 -> 29028.44 | N43: =N42+L43 -> 39270.206 | O43: =O42-K43 -> 122978.56 | S43: =$T$6-T43 -> 2487.6325 | T43: =$L$4/12*W42 -> 4950.7411 | U43: =U42+S43 -> 78398.696 | V43: =V42+T43 -> 174506.01 | W43: =W42-S43 -> 591601.3 | AA43: =$T$6-AB43 -> #NUM! | AB43: =$AB$4/12*AE42 -> #NUM! | AC43: =AC42+AA43 -> #NUM! | AD43: =AD42+AB43 -> #NUM! | AE43: =AE42-AA43 -> #NUM!
B44: M35 | C44: =$D$6-D44 -> #VALUE! | D44: =$D$4/12*G43 -> #VALUE! | E44: =E43+C44 -> #VALUE! | F44: =F43+D44 -> #VALUE! | G44: =G43-C44 -> #VALUE! | J44: =B44 -> M35 | K44: =$L$6-L44 -> 983.96237 | L44: =$L$4/12*O43 -> 1024.8213 | M44: =M43+K44 -> 30012.402 | N44: =N43+L44 -> 40295.028 | O44: =O43-K44 -> 121994.6 | S44: =$T$6-T44 -> 2508.3628 | T44: =$L$4/12*W43 -> 4930.0109 | U44: =U43+S44 -> 80907.059 | V44: =V43+T44 -> 179436.02 | W44: =W43-S44 -> 589092.94 | AA44: =$T$6-AB44 -> #NUM! | AB44: =$AB$4/12*AE43 -> #NUM! | AC44: =AC43+AA44 -> #NUM! | AD44: =AD43+AB44 -> #NUM! | AE44: =AE43-AA44 -> #NUM!
B45: M36 | C45: =$D$6-D45 -> #VALUE! | D45: =$D$4/12*G44 -> #VALUE! | E45: =E44+C45 -> #VALUE! | F45: =F44+D45 -> #VALUE! | G45: =G44-C45 -> #VALUE! | J45: =B45 -> M36 | K45: =$L$6-L45 -> 992.16206 | L45: =$L$4/12*O44 -> 1016.6216 | M45: =M44+K45 -> 31004.564 | N45: =N44+L45 -> 41311.649 | O45: =O44-K45 -> 121002.44 | S45: =$T$6-T45 -> 2529.2658 | T45: =$L$4/12*W44 -> 4909.1078 | U45: =U44+S45 -> 83436.324 | V45: =V44+T45 -> 184345.13 | W45: =W44-S45 -> 586563.68 | AA45: =$T$6-AB45 -> #NUM! | AB45: =$AB$4/12*AE44 -> #NUM! | AC45: =AC44+AA45 -> #NUM! | AD45: =AD44+AB45 -> #NUM! | AE45: =AE44-AA45 -> #NUM!
B46: M37 | C46: =$D$6-D46 -> #VALUE! | D46: =$D$4/12*G45 -> #VALUE! | E46: =E45+C46 -> #VALUE! | F46: =F45+D46 -> #VALUE! | G46: =G45-C46 -> #VALUE! | J46: =B46 -> M37 | K46: =$L$6-L46 -> 1000.4301 | L46: =$L$4/12*O45 -> 1008.3536 | M46: =M45+K46 -> 32004.994 | N46: =N45+L46 -> 42320.003 | O46: =O45-K46 -> 120002.01 | S46: =$T$6-T46 -> 2550.343 | T46: =$L$4/12*W45 -> 4888.0306 | U46: =U45+S46 -> 85986.667 | V46: =V45+T46 -> 189233.16 | W46: =W45-S46 -> 584013.33 | AA46: =$T$6-AB46 -> #NUM! | AB46: =$AB$4/12*AE45 -> #NUM! | AC46: =AC45+AA46 -> #NUM! | AD46: =AD45+AB46 -> #NUM! | AE46: =AE45-AA46 -> #NUM!
B47: M38 | C47: =$D$6-D47 -> #VALUE! | D47: =$D$4/12*G46 -> #VALUE! | E47: =E46+C47 -> #VALUE! | F47: =F46+D47 -> #VALUE! | G47: =G46-C47 -> #VALUE! | J47: =B47 -> M38 | K47: =$L$6-L47 -> 1008.767 | L47: =$L$4/12*O46 -> 1000.0167 | M47: =M46+K47 -> 33013.761 | N47: =N46+L47 -> 43320.02 | O47: =O46-K47 -> 118993.24 | S47: =$T$6-T47 -> 2571.5959 | T47: =$L$4/12*W46 -> 4866.7778 | U47: =U46+S47 -> 88558.263 | V47: =V46+T47 -> 194099.93 | W47: =W46-S47 -> 581441.74 | AA47: =$T$6-AB47 -> #NUM! | AB47: =$AB$4/12*AE46 -> #NUM! | AC47: =AC46+AA47 -> #NUM! | AD47: =AD46+AB47 -> #NUM! | AE47: =AE46-AA47 -> #NUM!
B48: M39 | C48: =$D$6-D48 -> #VALUE! | D48: =$D$4/12*G47 -> #VALUE! | E48: =E47+C48 -> #VALUE! | F48: =F47+D48 -> #VALUE! | G48: =G47-C48 -> #VALUE! | J48: =B48 -> M39 | K48: =$L$6-L48 -> 1017.1734 | L48: =$L$4/12*O47 -> 991.61032 | M48: =M47+K48 -> 34030.935 | N48: =N47+L48 -> 44311.63 | O48: =O47-K48 -> 117976.07 | S48: =$T$6-T48 -> 2593.0258 | T48: =$L$4/12*W47 -> 4845.3478 | U48: =U47+S48 -> 91151.289 | V48: =V47+T48 -> 198945.28 | W48: =W47-S48 -> 578848.71 | AA48: =$T$6-AB48 -> #NUM! | AB48: =$AB$4/12*AE47 -> #NUM! | AC48: =AC47+AA48 -> #NUM! | AD48: =AD47+AB48 -> #NUM! | AE48: =AE47-AA48 -> #NUM!
B49: M40 | C49: =$D$6-D49 -> #VALUE! | D49: =$D$4/12*G48 -> #VALUE! | E49: =E48+C49 -> #VALUE! | F49: =F48+D49 -> #VALUE! | G49: =G48-C49 -> #VALUE! | J49: =B49 -> M40 | K49: =$L$6-L49 -> 1025.6498 | L49: =$L$4/12*O48 -> 983.13388 | M49: =M48+K49 -> 35056.584 | N49: =N48+L49 -> 45294.764 | O49: =O48-K49 -> 116950.42 | S49: =$T$6-T49 -> 2614.6344 | T49: =$L$4/12*W48 -> 4823.7393 | U49: =U48+S49 -> 93765.924 | V49: =V48+T49 -> 203769.02 | W49: =W48-S49 -> 576234.08 | AA49: =$T$6-AB49 -> #NUM! | AB49: =$AB$4/12*AE48 -> #NUM! | AC49: =AC48+AA49 -> #NUM! | AD49: =AD48+AB49 -> #NUM! | AE49: =AE48-AA49 -> #NUM!
B50: M41 | C50: =$D$6-D50 -> #VALUE! | D50: =$D$4/12*G49 -> #VALUE! | E50: =E49+C50 -> #VALUE! | F50: =F49+D50 -> #VALUE! | G50: =G49-C50 -> #VALUE! | J50: =B50 -> M41 | K50: =$L$6-L50 -> 1034.1969 | L50: =$L$4/12*O49 -> 974.5868 | M50: =M49+K50 -> 36090.781 | N50: =N49+L50 -> 46269.351 | O50: =O49-K50 -> 115916.22 | S50: =$T$6-T50 -> 2636.423 | T50: =$L$4/12*W49 -> 4801.9506 | U50: =U49+S50 -> 96402.347 | V50: =V49+T50 -> 208570.97 | W50: =W49-S50 -> 573597.65 | AA50: =$T$6-AB50 -> #NUM! | AB50: =$AB$4/12*AE49 -> #NUM! | AC50: =AC49+AA50 -> #NUM! | AD50: =AD49+AB50 -> #NUM! | AE50: =AE49-AA50 -> #NUM!
B51: M42 | C51: =$D$6-D51 -> #VALUE! | D51: =$D$4/12*G50 -> #VALUE! | E51: =E50+C51 -> #VALUE! | F51: =F50+D51 -> #VALUE! | G51: =G50-C51 -> #VALUE! | J51: =B51 -> M42 | K51: =$L$6-L51 -> 1042.8152 | L51: =$L$4/12*O50 -> 965.96849 | M51: =M50+K51 -> 37133.596 | N51: =N50+L51 -> 47235.319 | O51: =O50-K51 -> 114873.4 | S51: =$T$6-T51 -> 2658.3932 | T51: =$L$4/12*W50 -> 4779.9804 | U51: =U50+S51 -> 99060.74 | V51: =V50+T51 -> 213350.95 | W51: =W50-S51 -> 570939.26 | AA51: =$T$6-AB51 -> #NUM! | AB51: =$AB$4/12*AE50 -> #NUM! | AC51: =AC50+AA51 -> #NUM! | AD51: =AD50+AB51 -> #NUM! | AE51: =AE50-AA51 -> #NUM!
B52: M43 | C52: =$D$6-D52 -> #VALUE! | D52: =$D$4/12*G51 -> #VALUE! | E52: =E51+C52 -> #VALUE! | F52: =F51+D52 -> #VALUE! | G52: =G51-C52 -> #VALUE! | J52: =B52 -> M43 | K52: =$L$6-L52 -> 1051.5053 | L52: =$L$4/12*O51 -> 957.27836 | M52: =M51+K52 -> 38185.102 | N52: =N51+L52 -> 48192.598 | O52: =O51-K52 -> 113821.9 | S52: =$T$6-T52 -> 2680.5465 | T52: =$L$4/12*W51 -> 4757.8272 | U52: =U51+S52 -> 101741.29 | V52: =V51+T52 -> 218108.78 | W52: =W51-S52 -> 568258.71 | AA52: =$T$6-AB52 -> #NUM! | AB52: =$AB$4/12*AE51 -> #NUM! | AC52: =AC51+AA52 -> #NUM! | AD52: =AD51+AB52 -> #NUM! | AE52: =AE51-AA52 -> #NUM!
B53: M44 | C53: =$D$6-D53 -> #VALUE! | D53: =B44*B53/I5 -> #VALUE! | E53: =E52+C53 -> #VALUE! | F53: =F52+D53 -> #VALUE! | G53: =G52-C53 -> #VALUE! | J53: =B53 -> M44 | K53: =$L$6-L53 -> 1060.2679 | L53: =$L$4/12*O52 -> 948.51582 | M53: =M52+K53 -> 39245.37 | N53: =N52+L53 -> 49141.113 | O53: =O52-K53 -> 112761.63 | S53: =$T$6-T53 -> 2702.8843 | T53: =$L$4/12*W52 -> 4735.4893 | U53: =U52+S53 -> 104444.17 | V53: =V52+T53 -> 222844.27 | W53: =W52-S53 -> 565555.83 | AA53: =$T$6-AB53 -> #NUM! | AB53: =$AB$4/12*AE52 -> #NUM! | AC53: =AC52+AA53 -> #NUM! | AD53: =AD52+AB53 -> #NUM! | AE53: =AE52-AA53 -> #NUM!
B54: M45 | C54: =$D$6-D54 -> #VALUE! | D54: =$D$4/12*G53 -> #VALUE! | E54: =E53+C54 -> #VALUE! | F54: =F53+D54 -> #VALUE! | G54: =G53-C54 -> #VALUE! | J54: =B54 -> M45 | K54: =$L$6-L54 -> 1069.1035 | L54: =$L$4/12*O53 -> 939.68025 | M54: =M53+K54 -> 40314.473 | N54: =N53+L54 -> 50080.794 | O54: =O53-K54 -> 111692.53 | S54: =$T$6-T54 -> 2725.4084 | T54: =$L$4/12*W53 -> 4712.9652 | U54: =U53+S54 -> 107169.58 | V54: =V53+T54 -> 227557.23 | W54: =W53-S54 -> 562830.42 | AA54: =$T$6-AB54 -> #NUM! | AB54: =$AB$4/12*AE53 -> #NUM! | AC54: =AC53+AA54 -> #NUM! | AD54: =AD53+AB54 -> #NUM! | AE54: =AE53-AA54 -> #NUM!
B55: M46 | C55: =$D$6-D55 -> #VALUE! | D55: =$D$4/12*G54 -> #VALUE! | E55: =E54+C55 -> #VALUE! | F55: =F54+D55 -> #VALUE! | G55: =G54-C55 -> #VALUE! | J55: =B55 -> M46 | K55: =$L$6-L55 -> 1078.0126 | L55: =$L$4/12*O54 -> 930.77106 | M55: =M54+K55 -> 41392.486 | N55: =N54+L55 -> 51011.565 | O55: =O54-K55 -> 110614.51 | S55: =$T$6-T55 -> 2748.1201 | T55: =$L$4/12*W54 -> 4690.2535 | U55: =U54+S55 -> 109917.7 | V55: =V54+T55 -> 232247.49 | W55: =W54-S55 -> 560082.3 | AA55: =$T$6-AB55 -> #NUM! | AB55: =$AB$4/12*AE54 -> #NUM! | AC55: =AC54+AA55 -> #NUM! | AD55: =AD54+AB55 -> #NUM! | AE55: =AE54-AA55 -> #NUM!
B56: M47 | C56: =$D$6-D56 -> #VALUE! | D56: =$D$4/12*G55 -> #VALUE! | E56: =E55+C56 -> #VALUE! | F56: =F55+D56 -> #VALUE! | G56: =G55-C56 -> #VALUE! | J56: =B56 -> M47 | K56: =$L$6-L56 -> 1086.9961 | L56: =$L$4/12*O55 -> 921.78762 | M56: =M55+K56 -> 42479.482 | N56: =N55+L56 -> 51933.352 | O56: =O55-K56 -> 109527.52 | S56: =$T$6-T56 -> 2771.0211 | T56: =$L$4/12*W55 -> 4667.3525 | U56: =U55+S56 -> 112688.72 | V56: =V55+T56 -> 236914.84 | W56: =W55-S56 -> 557311.28 | AA56: =$T$6-AB56 -> #NUM! | AB56: =$AB$4/12*AE55 -> #NUM! | AC56: =AC55+AA56 -> #NUM! | AD56: =AD55+AB56 -> #NUM! | AE56: =AE55-AA56 -> #NUM!
B57: M48 | C57: =$D$6-D57 -> #VALUE! | D57: =$D$4/12*G56 -> #VALUE! | E57: =E56+C57 -> #VALUE! | F57: =F56+D57 -> #VALUE! | G57: =G56-C57 -> #VALUE! | J57: =B57 -> M48 | K57: =$L$6-L57 -> 1096.0544 | L57: =$L$4/12*O56 -> 912.72932 | M57: =M56+K57 -> 43575.536 | N57: =N56+L57 -> 52846.082 | O57: =O56-K57 -> 108431.46 | S57: =$T$6-T57 -> 2794.113 | T57: =$L$4/12*W56 -> 4644.2607 | U57: =U56+S57 -> 115482.83 | V57: =V56+T57 -> 241559.1 | W57: =W56-S57 -> 554517.17 | AA57: =$T$6-AB57 -> #NUM! | AB57: =$AB$4/12*AE56 -> #NUM! | AC57: =AC56+AA57 -> #NUM! | AD57: =AD56+AB57 -> #NUM! | AE57: =AE56-AA57 -> #NUM!
B58: M49 | C58: =$D$6-D58 -> #VALUE! | D58: =$D$4/12*G57 -> #VALUE! | E58: =E57+C58 -> #VALUE! | F58: =F57+D58 -> #VALUE! | G58: =G57-C58 -> #VALUE! | J58: =B58 -> M49 | K58: =$L$6-L58 -> 1105.1882 | L58: =$L$4/12*O57 -> 903.59553 | M58: =M57+K58 -> 44680.724 | N58: =N57+L58 -> 53749.677 | O58: =O57-K58 -> 107326.28 | S58: =$T$6-T58 -> 2817.3972 | T58: =$L$4/12*W57 -> 4620.9764 | U58: =U57+S58 -> 118300.23 | V58: =V57+T58 -> 246180.08 | W58: =W57-S58 -> 551699.77 | AA58: =$T$6-AB58 -> #NUM! | AB58: =$AB$4/12*AE57 -> #NUM! | AC58: =AC57+AA58 -> #NUM! | AD58: =AD57+AB58 -> #NUM! | AE58: =AE57-AA58 -> #NUM!
B59: M50 | C59: =$D$6-D59 -> #VALUE! | D59: =$D$4/12*G58 -> #VALUE! | E59: =E58+C59 -> #VALUE! | F59: =F58+D59 -> #VALUE! | G59: =G58-C59 -> #VALUE! | J59: =B59 -> M50 | K59: =$L$6-L59 -> 1114.3981 | L59: =$L$4/12*O58 -> 894.38563 | M59: =M58+K59 -> 45795.123 | N59: =N58+L59 -> 54644.063 | O59: =O58-K59 -> 106211.88 | S59: =$T$6-T59 -> 2840.8755 | T59: =$L$4/12*W58 -> 4597.4981 | U59: =U58+S59 -> 121141.11 | V59: =V58+T59 -> 250777.58 | W59: =W58-S59 -> 548858.89 | AA59: =$T$6-AB59 -> #NUM! | AB59: =$AB$4/12*AE58 -> #NUM! | AC59: =AC58+AA59 -> #NUM! | AD59: =AD58+AB59 -> #NUM! | AE59: =AE58-AA59 -> #NUM!
B60: M51 | C60: =$D$6-D60 -> #VALUE! | D60: =$D$4/12*G59 -> #VALUE! | E60: =E59+C60 -> #VALUE! | F60: =F59+D60 -> #VALUE! | G60: =G59-C60 -> #VALUE! | J60: =B60 -> M51 | K60: =$L$6-L60 -> 1123.6847 | L60: =$L$4/12*O59 -> 885.09898 | M60: =M59+K60 -> 46918.807 | N60: =N59+L60 -> 55529.162 | O60: =O59-K60 -> 105088.19 | S60: =$T$6-T60 -> 2864.5495 | T60: =$L$4/12*W59 -> 4573.8241 | U60: =U59+S60 -> 124005.66 | V60: =V59+T60 -> 255351.4 | W60: =W59-S60 -> 545994.34 | AA60: =$T$6-AB60 -> #NUM! | AB60: =$AB$4/12*AE59 -> #NUM! | AC60: =AC59+AA60 -> #NUM! | AD60: =AD59+AB60 -> #NUM! | AE60: =AE59-AA60 -> #NUM!
B61: M52 | C61: =$D$6-D61 -> #VALUE! | D61: =$D$4/12*G60 -> #VALUE! | E61: =E60+C61 -> #VALUE! | F61: =F60+D61 -> #VALUE! | G61: =G60-C61 -> #VALUE! | J61: =B61 -> M52 | K61: =$L$6-L61 -> 1133.0488 | L61: =$L$4/12*O60 -> 875.73494 | M61: =M60+K61 -> 48051.856 | N61: =N60+L61 -> 56404.897 | O61: =O60-K61 -> 103955.14 | S61: =$T$6-T61 -> 2888.4208 | T61: =$L$4/12*W60 -> 4549.9529 | U61: =U60+S61 -> 126894.08 | V61: =V60+T61 -> 259901.35 | W61: =W60-S61 -> 543105.92 | AA61: =$T$6-AB61 -> #NUM! | AB61: =$AB$4/12*AE60 -> #NUM! | AC61: =AC60+AA61 -> #NUM! | AD61: =AD60+AB61 -> #NUM! | AE61: =AE60-AA61 -> #NUM!
B62: M53 | C62: =$D$6-D62 -> #VALUE! | D62: =$D$4/12*G61 -> #VALUE! | E62: =E61+C62 -> #VALUE! | F62: =F61+D62 -> #VALUE! | G62: =G61-C62 -> #VALUE! | J62: =B62 -> M53 | K62: =$L$6-L62 -> 1142.4908 | L62: =$L$4/12*O61 -> 866.29287 | M62: =M61+K62 -> 49194.347 | N62: =N61+L62 -> 57271.19 | O62: =O61-K62 -> 102812.65 | S62: =$T$6-T62 -> 2912.4909 | T62: =$L$4/12*W61 -> 4525.8827 | U62: =U61+S62 -> 129806.57 | V62: =V61+T62 -> 264427.24 | W62: =W61-S62 -> 540193.43 | AA62: =$T$6-AB62 -> #NUM! | AB62: =$AB$4/12*AE61 -> #NUM! | AC62: =AC61+AA62 -> #NUM! | AD62: =AD61+AB62 -> #NUM! | AE62: =AE61-AA62 -> #NUM!
B63: M54 | C63: =$D$6-D63 -> #VALUE! | D63: =$D$4/12*G62 -> #VALUE! | E63: =E62+C63 -> #VALUE! | F63: =F62+D63 -> #VALUE! | G63: =G62-C63 -> #VALUE! | J63: =B63 -> M54 | K63: =$L$6-L63 -> 1152.0116 | L63: =$L$4/12*O62 -> 856.77211 | M63: =M62+K63 -> 50346.358 | N63: =N62+L63 -> 58127.962 | O63: =O62-K63 -> 101660.64 | S63: =$T$6-T63 -> 2936.7617 | T63: =$L$4/12*W62 -> 4501.6119 | U63: =U62+S63 -> 132743.33 | V63: =V62+T63 -> 268928.85 | W63: =W62-S63 -> 537256.67 | AA63: =$T$6-AB63 -> #NUM! | AB63: =$AB$4/12*AE62 -> #NUM! | AC63: =AC62+AA63 -> #NUM! | AD63: =AD62+AB63 -> #NUM! | AE63: =AE62-AA63 -> #NUM!
B64: M55 | C64: =$D$6-D64 -> #VALUE! | D64: =$D$4/12*G63 -> #VALUE! | E64: =E63+C64 -> #VALUE! | F64: =F63+D64 -> #VALUE! | G64: =G63-C64 -> #VALUE! | J64: =B64 -> M55 | K64: =$L$6-L64 -> 1161.6117 | L64: =$L$4/12*O63 -> 847.17201 | M64: =M63+K64 -> 51507.97 | N64: =N63+L64 -> 58975.134 | O64: =O63-K64 -> 100499.03 | S64: =$T$6-T64 -> 2961.2347 | T64: =$L$4/12*W63 -> 4477.1389 | U64: =U63+S64 -> 135704.56 | V64: =V63+T64 -> 273405.99 | W64: =W63-S64 -> 534295.44 | AA64: =$T$6-AB64 -> #NUM! | AB64: =$AB$4/12*AE63 -> #NUM! | AC64: =AC63+AA64 -> #NUM! | AD64: =AD63+AB64 -> #NUM! | AE64: =AE63-AA64 -> #NUM!
B65: M56 | C65: =$D$6-D65 -> #VALUE! | D65: =$D$4/12*G64 -> #VALUE! | E65: =E64+C65 -> #VALUE! | F65: =F64+D65 -> #VALUE! | G65: =G64-C65 -> #VALUE! | J65: =B65 -> M56 | K65: =$L$6-L65 -> 1171.2918 | L65: =$L$4/12*O64 -> 837.49192 | M65: =M64+K65 -> 52679.262 | N65: =N64+L65 -> 59812.626 | O65: =O64-K65 -> 99327.738 | S65: =$T$6-T65 -> 2985.9117 | T65: =$L$4/12*W64 -> 4452.462 | U65: =U64+S65 -> 138690.48 | V65: =V64+T65 -> 277858.45 | W65: =W64-S65 -> 531309.52 | AA65: =$T$6-AB65 -> #NUM! | AB65: =$AB$4/12*AE64 -> #NUM! | AC65: =AC64+AA65 -> #NUM! | AD65: =AD64+AB65 -> #NUM! | AE65: =AE64-AA65 -> #NUM!
... B249: M240 | C249: =$D$6-D249 -> #VALUE! | D249: =$D$4/12*G248 -> #VALUE! | E249: =E248+C249 -> #VALUE! | F249: =F248+D249 -> #VALUE! | G249: =G248-C249 -> #VALUE! | J249: =B249 -> M240 | K249: =$L$6-L249 -> 5392.9198 | L249: =$L$4/12*O248 -> -3384.1361 | M249: =M248+K249 -> 563496.26 | N249: =N248+L249 -> -81388.166 | O249: =O248-K249 -> -411489.26 | S249: =$T$6-T249 -> 13747.883 | T249: =$L$4/12*W248 -> -6309.5091 | U249: =U248+S249 -> 1440889 | V249: =V248+T249 -> 344320.69 | W249: =W248-S249 -> -770888.98 | AA249: =$T$6-AB249 -> #NUM! | AB249: =$AB$4/12*AE248 -> #NUM! | AC249: =AC248+AA249 -> #NUM! | AD249: =AD248+AB249 -> #NUM! | AE249: =AE248-AA249 -> #NUM!

Sheet S8 - salaire 
B2: LES SALAIRES :
C3: Inscrivez vos informations dans ces cellules vertes. Ne rien inscrire dans les autres cellules.
B4: Soit :
B6: Salaires brut : | C6: ='S8-Outil - Charges '!I19 -> 153183.29
B7: Retenus à la source : | C7: ='S8-Outil - Charges '!I20 -> 39982.37
B8: Avantages sociaux : | C8: ='S8-Outil - Charges '!I21 -> 31122.249
B9: Vacances : | C9: =0.04*C6 -> 6127.3315 | I9: Voici l'écriture des salaires à entrer dans Acomba (écriture)
B11: Salaires à payer | C11: =1/4.3333/3 -> 0.076923669 | D11: 1 semaine sur 4,333 semaines par mois
G14: débit | H14: crédit
E16: Compte de banque | G16: =-(G29+G30+G31-H16-H17-H18) -> -104493.09 | H16: =(C6-C7)*C11 -> 8707.8299 | J16: Salaires à payer
H17: =G30+C7 -> 71104.619 | J17: DAS & RAS à payer
H18: =G31 -> 6127.3315 | J18: Vacances à payer
E29: Salaires | G29: =C6 -> 153183.29
E30: Avantages sociaux | G30: =C8 -> 31122.249
E31: Vacances | G31: =C9 -> 6127.3315
G35: =SUM(G16:G31) -> 85939.78 | H35: =SUM(H16:H31) -> 85939.78

Sheet S8 Bilan TRIM1
C2: Issa O
C3: Bilan
C4: Au TRIM 1
B6: Actif
A7: Actif à court terme
A8: Banque | C8: 350227.53
A9: Comptes clients | C9: 906247
A10: Charges payées d'avance | C10: 25000
A11: Stocks de marchandises | C11: 10821
A12: Total de l'actif à court terme | D12: 1292295.5
A14: Immobilisations
A15: Ameublement | C15: 105131
A16: Amort. cumulé - Ameublement | C16: -5257 | D16: =C15+C16 -> 99874
A18: Équipement informatique | C18: 40000
A19: Amort. cumulé - Équip. informatique | C19: -3000 | D19: =C18+C19 -> 37000
A21: Equipement de ventes - Caisse | C21: 31500
A22: Amort. cumulé - Equip. de vente -Caisse | C22: -1575 | D22: =C21+C22 -> 29925
A24: Équipement- Manutention et Cuisine | C24: 39700
A25: Amort. cumulé - Équipement - Manutention et Cuisine | C25: -1985 | D25: =C24+C25 -> 37715
A27: Améliorations locatives | C27: 349000
A28: Amort. cumulé - Amélior. locatives | C28: -17450 | D28: =C27+C28 -> 331550
A30: Frais d'incorporation reportés | C30: 6500
A31: Amort. cumulé - Frais d'incorporation | C31: -750 | D31: =C30+C31 -> 5750
A33: Total des immobilisations | D33: 541814
A34: Total de l'actif | D34: 1834109.5
B36: Passif
A37: Passif à court terme
A38: Comptes fournisseurs | C38: 851612
A39: Salaires à payer | C39: 7456.51
A40: Vacances à payer | C40: 5246.83
A41: D.A.S. à payer | C41: 60886.86
A42: Taxe a payer | C42: 235601
A43: Capital de risque | C43: 149763.22
A44: Total du passif à court terme | C44: 1310566.4 | D44: x
A46: Passif à long terme
A47: Emprunt hypothécaire | C47: 58199.19
A48: Total du passif à long terme | C48: 58199.19
A49: Total du passif | C49: 1368765.6
B51: Capitaux
A52: Capital - Actions | C52: 450000
A53: Subventions | C53: 85000
A54: Perte nette | C54: -69656.08
A55: Total Capitaux | D55: 465343.92
A57: Total du passif et de l'avoir | D57: 1834109.5

Sheet S8- Transactions Acomba TRIM 2
D1: 0.05 | E1: 0.09975
A2: Compte | B2: Débit | C2: Crédit
A3: Comptes clients | B3: =C6+C5+C4 -> 3045335.4
A4: TPS à payer | C4: =C6*D1 -> 132434.68
A5: TVQ à payer | C5: =C6*E1 -> 264207.18
A6: Ventes | C6: ='S8-Outil - Charges '!B5 -> 2648693.6 | D6: (valeur provenant de votre feuille des ventes réelles)
A8: Banque | B8: =C9 -> 1979468
A9: Comptes clients | C9: =B3*D9 -> 1979468 | D9: 0.65
A11: Achat | B11: ='Bon de commande TRIM 2'!G25 -> 1766912.5 | D11: (si pénalité de retard)
A12: Transport sur achats | B12: =Facture5[[#Totals],[Total de la ligne]] -> 251069.77
A13: TPS à recevoir | B13: =(B11+B12)*D1 -> 100899.11
A14: TVQ à recevoir | B14: =(B11+B12)*E1 -> 201293.73
A15: Comptes fournisseurs | C15: =D15*(B11+B12+B13+B14) -> 1160087.6 | D15: 0.5
A16: Banque | C16: =D16*(B11+B12+B13+B14) -> 1160087.6 | D16: 0.5
A18: Charges taxables (à faire en une écriture)
A19: ='S5 -Outil - Charges'!A28 -> Téléphonie et système de communication | B19: ='S8-Outil - Charges '!B33 -> 2250
A20: ='S5 -Outil - Charges'!A36 -> Électricité (même valeur pour tous) - Dépenses fixes (facture équilibrée) | B20: ='S8-Outil - Charges '!D37 -> 18500
A21: ='S5 -Outil - Charges'!A41 -> Frais d'entretien | B21: ='S8-Outil - Charges '!D50 -> 190621.46
A22: ='S5 -Outil - Charges'!A62 -> Taxes municipales: | B22: ='S8-Outil - Charges '!D64 -> 10907.722
A23: ='S5 -Outil - Charges'!F28 -> Frais de livraison aux clients: | B23: ='S8-Outil - Charges '!J40 -> 98620
A24: ='S5 -Outil - Charges'!F45 -> Loyer | B24: ='S8-Outil - Charges '!G47 -> 94242.719
A25: ='S5 -Outil - Charges'!F50 -> Publicité | B25: ='S8-Outil - Charges '!G55 -> 9000
A26: ='S5 -Outil - Charges'!F59 -> Fournitures de bureau: | B26: ='S8-Outil - Charges '!G63 -> 1739.0114
A27: ='S5 -Outil - Charges'!F82 -> Frais de site électronique
A28: ='S5 -Outil - Charges'!F90 -> Frais de transactions via internet | B28: ='S5 -Outil - Charges'!G92 -> 0
A29: ='S5 -Outil - Charges'!F75 -> Honoraires professionnelles | B29: ='S8-Outil - Charges '!G81 -> 9270.4274
A30: TPS à recevoir | B30: =SUM(B19:B29)*D1 -> 21757.567
A31: TVQ à recevoir | B31: =SUM(B19:B29)*E1 -> 43406.346
A32: Banque | C32: =SUM(B19:B31) -> 500315.25
A34: Charges non-taxables
A35: ='S5 -Outil - Charges'!A53 -> Assurances: | B35: ='S8-Outil - Charges '!D59 -> 2478.8391
A36: ='S5 -Outil - Charges'!F67 -> Frais de banque (pas taxables) | B36: ='S8-Outil - Charges '!G74 -> 147.045
A37: Banque | C37: =SUM(B35:B36) -> 2625.8841
A39: Remboursement hypothèque
A40: Emprunt hypothécaire | B40: ='S8 -Emprunt '!C13+'S8 -Emprunt '!C14+'S8 -Emprunt '!C15 -> 1107.2516
A41: Intérêt | B41: ='S8 -Emprunt '!D13+'S8 -Emprunt '!D14+'S8 -Emprunt '!D15 -> 867.47004
A42: Banque | C42: =SUM(B40:B41) -> 1974.7217
E43: =50000*30.2% -> 15100
A44: Remboursement Capital de risque | E44: =10*21103 -> 211030
A45: Capital de risque | B45: ='S8 -Emprunt '!K13+'S8 -Emprunt '!K14+'S8 -Emprunt '!K15 -> 2301.3676
A46: Intérêt | B46: ='S8 -Emprunt '!L13+'S8 -Emprunt '!L14+'S8 -Emprunt '!L15 -> 3724.9836
A47: Banque | C47: =SUM(B45:B46) -> 6026.3511
A49: Écriture de Salaire (voir votre feuille salaire) | B49: ==> saisir la transaction de salaire tel que présentée dans la croix comptable
A51: Écriture d'amortissement (en lien avec votre tableau de calcul Outil-Charges)
A53: ='S5 -Outil - Charges'!A70 -> Terrain | B53: ='S5 -Outil - Charges'!D70 -> 0
A54: Bâtiment - amortissement | B54: ='S5 -Outil - Charges'!D71 -> 0
A55: Bâtiment - amortissement cumulé | C55: =B54 -> 0
A56: Amélioration locative - amortissement | B56: ='S8-Outil - Charges '!D76 -> 17450
A57: Amélioration locative - amortissement cumulé | C57: =B56 -> 17450
A58: Site transactionnel - amortissement | B58: ='S5 -Outil - Charges'!D73 -> 0
A59: Site transactionnel - amortissement cumulé | C59: =B58 -> 0
A60: Caisses - amortissement | B60: ='S8-Outil - Charges '!D78 -> 1575
A61: Caisses - amortissement cumulé | C61: =B60 -> 1575
A62: Équipement de cuisine - amortissement | B62: ='S8-Outil - Charges '!D79 -> 250
A63: Équipmeent de cuisine - amortissement cumulé | C63: =B62 -> 250
A64: Équipeme de manutention - amortissement | B64: ='S8-Outil - Charges '!D80 -> 1735
A65: Équipement de manutention - amortissement cumulé | C65: =B64 -> 1735
A66: Équipement informatique - amortissement | B66: ='S8-Outil - Charges '!D81 -> 3000
A67: Équipmeent informatique - amortissement cumulé | C67: =B66 -> 3000
A68: Ameublement - amortissement | B68: ='S8-Outil - Charges '!D82 -> 5256.5727
A69: Ameublement - amortissement cumulé | C69: =B68 -> 5256.5727
A70: Frais d'incorporation - amortissement | B70: =3000*25% -> 750
A71: Frais d'incorporation - amortissement cumulé | C71: =B70 -> 750
A73: Écriture de régularisation
A75: Étude de marché | B75: 25000
A76: Frais payés d'avance | C76: =D76*B75 -> 6250 | D76: 0.25
A77: Divers | B77: =C76 -> 6250
A79: Inventaire (TRIM 2 seulement) | F79: TRIM "2
A80: Achats | B80: ='S8-Outil - Charges '!B12 -> 1766912.5 | F80: Stock de début | G80: ='S8-Outil - Charges '!B11 -> 10821
A81: Stock de marchandises | C81: =B80 -> 1766912.5 | F81: =A81 -> Stock de marchandises | H81: =G80 -> 10821
A82: Stock de marchandises de fin | B82: ='S8-Outil - Charges '!B14 -> 2613 | F82: =A82 -> Stock de marchandises de fin | G82: =B82 -> 2613
A83: Inventaire de fin | C83: =B82 -> 2613 | F83: =A83 -> Inventaire de fin | H83: =G82 -> 2613
A85: Intérêt sur la marge de crédit | B85: =11%/4
A86: Intérêt | B86: =('S4 - Montage financier'!D2*11%)/4 -> 18425
A87: Banque | C87: =B86 -> 18425
A89: Remboursement des taxes à recevoir
A90: Banque | B90: ='S4 - Montage financier'!C2 -> 217650.77
A91: Taxes nettes à recevoir | C91: =B90 -> 217650.77
A93: Écriture des taxes (faire votre écriture de taxes pour le Trimestre 2
A94: T.P.S. à payer | B94: =135435-3000 -> 132435 | D94: Voir BV
A95: T.V.Q à payer | B95: 264206
A96: T.P.S à recevoir | C96: 122657
A97: T.V.Q. à recevoir | C97: 244700
A98: Comptes de taxes nettes | C98: =(B94+B95)-(C96+C97) -> 29284
A100: Remboursement de votre marge de crédit en fonction de votre compte de Banque
A101: Marge de crédit | B101: =670000 -> 670000
A102: Banque | C102: =B101 -> 670000

Sheet S8 Bilan TRIM2 
C2: Issa O
C3: Bilan
C4: Au TRIM 2
B6: TRIM1 | D6: AV TRIM 1 | E6: TRIM 2 | G6: AV TRIM 2 | H6: AH
B7: Actif
A8: Actif à court terme
A9: Banque | B9: 350227.53 | D9: =B9/$C$35 -> 0.19095235 | E9: 304863 | G9: =E9/$F$35 -> 0.15904789 | H9: =(E9-B9)/B9 -> -0.12952874
A10: Comptes clients | B10: 906247 | D10: =B10/$C$35 -> 0.49410735 | E10: 1065867 | G10: =E10/$F$35 -> 0.55606584 | H10: =(E10-B10)/B10 -> 0.176133
A11: Charges payées d'avance | B11: 25000 | D11: =B11/$C$35 -> 0.013630593 | E11: 31500 | G11: =E11/$F$35 -> 0.016433639 | H11: =(E11-B11)/B11 -> 0.26
A12: Stocks de marchandises de fin | B12: 10821 | D12: =B12/$C$35 -> 0.0058998658 | E12: 2613 | G12: =E12/$F$35 -> 0.0013632095 | H12: =(E12-B12)/B12 -> -0.75852509
A13: Total de l'actif à court terme | C13: 1292295.5 | D13: =C13/$C$35 -> 0.70459016 | F13: 1404843 | G13: =F13/$F$35 -> 0.73291058 | H13: =(F13-C13)/C13 -> 0.087091124
A15: Immobilisations
A16: Ameublement | B16: 105131 | E16: 105131
A17: Amort. cumulé - Ameublement | B17: -5257 | C17: =B16+B17 -> 99874 | D17: =C17/$C$35 -> 0.054453673 | E17: -10514 | F17: =E16+E17 -> 94617 | G17: =F17/$F$35 -> 0.049361957 | H17: =(F17-C17)/C17 -> -0.052636322
A19: Équipement informatique | B19: 40000 | E19: 40000
A20: Amort. cumulé - Équip. informatique | B20: -3000 | C20: =B19+B20 -> 37000 | D20: =C20/$C$35 -> 0.020173277 | E20: -6000 | F20: =E19+E20 -> 34000 | G20: =F20/$F$35 -> 0.017737896 | H20: =(F20-C20)/C20 -> -0.081081081
A22: Equipement de ventes - Caisse | B22: 31500 | E22: 31500
A23: Amort. cumulé - Equip. de vente -Caisse | B23: -1575 | C23: =B22+B23 -> 29925 | D23: =C23/$C$35 -> 0.016315819 | E23: -3150 | F23: =E22+E23 -> 28350 | G23: =F23/$F$35 -> 0.014790275 | H23: =(F23-C23)/C23 -> -0.052631579
A25: Équipement- Manutention et Cuisine | B25: 39700 | E25: 39700
A26: Amort. cumulé - Équipement - Manutention et Cuisine | B26: -1985 | C26: =B25+B26 -> 37715 | D26: =C26/$C$35 -> 0.020563112 | E26: -3810 | F26: =E25+E26 -> 35890 | G26: =F26/$F$35 -> 0.018723915 | H26: =(F26-C26)/C26 -> -0.048389235
A28: Améliorations locatives | B28: 349000 | E28: 349000
A29: Amort. cumulé - Amélior. locatives | B29: -17450 | C29: =B28+B29 -> 331550 | D29: =C29/$C$35 -> 0.18076892 | E29: -34900 | F29: =E28+E29 -> 314100 | G29: =F29/$F$35 -> 0.16386686 | H29: =(F29-C29)/C29 -> -0.052631579
A31: Frais d'incorporation reportés | B31: 6500 | E31: 6500
A32: Amort. cumulé - Frais d'incorporation | B32: -750 | C32: =B31+B32 -> 5750 | D32: =C32/$C$35 -> 0.0031350363 | E32: -1500 | F32: =E31+E32 -> 5000 | G32: =F32/$F$35 -> 0.0026085142 | H32: =(F32-C32)/C32 -> -0.13043478
A34: Total des immobilisations | C34: 541814 | D34: =C34/$C$35 -> 0.29540984 | F34: 511957 | G34: =F34/$F$35 -> 0.26708942 | H34: =(F34-C34)/C34 -> -0.055105627
A35: Total de l'actif | C35: 1834109.5 | D35: =C35/$C$35 -> 1 | F35: 1916800 | G35: =F35/$F$35 -> 1 | H35: =(F35-C35)/C35 -> 0.045084805
B37: Passif
A38: Passif à court terme
A39: Comptes fournisseurs | B39: 851612 | D39: =B39/$C$35 -> 0.46431905 | F39: 1160088 | G39: =F39/$F$35 -> 0.6052212 | H39: =(F39-B39)/B39 -> 0.36222599
A40: Salaires à payer | B40: 7456.51 | D40: =B40/$C$35 -> 0.004065466 | F40: 71104.62 | G40: =F40/$F$35 -> 0.037095482 | H40: =(F40-B40)/B40 -> 8.5359116
A41: Vacances à payer | B41: 5246.83 | D41: =B41/$C$35 -> 0.0028606961 | F41: 11374.16 | G41: =F41/$F$35 -> 0.0059339316 | H41: =(F41-B41)/B41 -> 1.1678156
A42: D.A.S. à payer | B42: 60886.86 | D42: =B42/$C$35 -> 0.03319696 | F42: 8707.83 | G42: =F42/$F$35 -> 0.0045428996 | H42: =(F42-B42)/B42 -> -0.85698343
A43: Taxe a payer | B43: 235601 | D43: =B43/$C$35 -> 0.12845525 | F43: 29284 | G43: =F43/$F$35 -> 0.015277546 | H43: =(F43-B43)/B43 -> -0.87570511
A44: Capital de risque | B44: 149763.22 | D44: =B44/$C$35 -> 0.081654458 | F44: 147461.85 | G44: =F44/$F$35 -> 0.076931266 | H44: =(F44-B44)/B44 -> -0.015366724
A45: Total du passif à court terme | B45: 1310566.4 | D45: =B45/$C$35 -> 0.71455188 | F45: 1428020.5 | G45: =F45/$F$35 -> 0.74500233 | H45: =(F45-B45)/B45 -> 0.089620822
A47: Passif à long terme
A48: Emprunt hypothécaire | B48: 58199.19 | D48: =B48/$C$35 -> 0.031731578 | F48: 57091.94 | G48: =F48/$F$35 -> 0.029785027 | H48: =(F48-B48)/B48 -> -0.019025179
A49: Total du passif à long terme | B49: 58199.19 | D49: =B49/$C$35 -> 0.031731578 | F49: 57091.94 | G49: =F49/$F$35 -> 0.029785027 | H49: =(F49-B49)/B49 -> -0.019025179
A50: Total du passif | B50: 1368765.6 | D50: =B50/$C$35 -> 0.74628346 | F50: 1485112.4 | G50: =F50/$F$35 -> 0.77478735 | H50: =(F50-B50)/B50 -> 0.085001252
B52: Capitaux
A53: Capital - Actions | B53: 450000 | D53: =B53/$C$35 -> 0.24535067 | F53: 450000 | G53: =F53/$F$35 -> 0.23476628 | H53: =(F53-B53)/B53 -> 0
A54: Subventions | B54: 85000 | D54: =B54/$C$35 -> 0.046344015 | F54: 85000 | G54: =F54/$F$35 -> 0.044344741 | H54: =(F54-B54)/B54 -> 0
A55: Perte nette | B55: -69656.08 | D55: =B55/$C$35 -> -0.037978146 | F55: -103312.4 | G55: =F55/$F$35 -> -0.053898372 | H55: =(F55-B55)/B55 -> 0.4831785
A56: Total Capitaux | C56: 465343.92 | D56: =C56/$C$35 -> 0.25371654 | F56: 431687.6 | G56: =F56/$F$35 -> 0.22521265 | H56: =(F56-C56)/C56 -> -0.07232569
A58: Total du passif et de l'avoir | C58: 1834109.5 | D58: =C58/$C$35 -> 1 | F58: 1916800 | G58: =F58/$F$35 -> 1 | H58: =(F58-C58)/C58 -> 0.045084805

Sheet S6 États des résultats TRIM 2
B2: Issa O
B3: États des résultats
B4: Pour la période se terminant au TRIM 2
A7: Ventes de biens : | B7: Solde TRIM 1 | C7: % ventes trim1 | D7: Solde TRIM 2 | E7: % ventes trim2 | F7: Solde Année cumul | G7: % Ventes total trim1 et 2
A8: Ventes | B8: 2252034 | C8: =B8/$B$8 -> 1 | D8: 2648694 | E8: =D8/$D$8 -> 1 | F8: =B8+D8 -> 4900728 | G8: =F8/$F$8 -> 1
A9: Ventes de biens nettes | B9: 2252034 | C9: =B9/$B$8 -> 1 | D9: 2648694 | E9: =D9/$D$8 -> 1 | F9: =B9+D9 -> 4900728 | G9: =F9/$F$8 -> 1 | J9: Rendement sur les capitaux propres
A10: Coût des marchandises vendues : | K10: Bén/Cap. Propres | M10: Trim 1 | N10: ='S8 Bilan TRIM2 '!B55/'S8 Bilan TRIM2 '!C56 -> -0.14968731
A11: Achats | B11: 1453428 | C11: =B11/$B$8 -> 0.64538457 | D11: 1766913 | E11: =D11/$D$8 -> 0.66708838 | F11: =B11+D11 -> 3220341 | G11: =F11/$F$8 -> 0.65711482 | M11: Trim 2 | N11: ='S8 Bilan TRIM2 '!F55/'S8 Bilan TRIM2 '!F56 -> -0.23932214
A12: Frais de transport sur achats | D12: 251070 | E12: =D12/$D$8 -> 0.094790112 | F12: =B12+D12 -> 251070 | G12: =F12/$F$8 -> 0.051231164
A13: Stocks de début | D13: 10821 | E13: =D13/$D$8 -> 0.0040854096 | F13: =D13 -> 10821 | G13: =F13/$F$8 -> 0.0022080393
A14: Stocks de fin | B14: -10821 | C14: =B14/$B$8 -> -0.0048049896 | D14: -2613 | E14: =D14/$D$8 -> -0.00098652392 | F14: =-(-B14-D14) -> -13434 | G14: =F14/$F$8 -> -0.0027412254
A15: Coût des marchandises vendues | B15: 1442607 | C15: =B15/$B$8 -> 0.64057958 | D15: =SUM(D11:D14) -> 2026191 | E15: =D15/$D$8 -> 0.76497738 | F15: =B15+D15 -> 3468798 | G15: =F15/$F$8 -> 0.7078128 | I15: Efficacité des opérations | N15: Efficacité de l'actif | R15: Effet de levier
A16: Bénéfice brut (perte brute) | B16: =B9-B15 -> 809427 | C16: =B16/$B$8 -> 0.35942042 | D16: =D9-D15 -> 622503 | E16: =D16/$D$8 -> 0.23502262 | F16: =F9-F15 -> 1431930 | G16: =F16/$F$8 -> 0.2921872 | K16: Bén/ventes | O16: Ventes/actif | S16: Actif/Avoir
J17: Trim 1 | K17: =B16/B8 -> 0.35942042 | O17: Trim 1 | P17: =B8/'S8 Bilan TRIM2 '!C35 -> 1.2278623 | S17: Trim 1 | T17: ='S8 Bilan TRIM2 '!C35/'S8 Bilan TRIM2 '!C56 -> 3.9414065
J18: Trim 2 | K18: =D16/D8 -> 0.23502262 | O18: Trim 2 | P18: =D8/'S8 Bilan TRIM2 '!F35 -> 1.3818312 | S18: Trim 2 | T18: ='S8 Bilan TRIM2 '!F35/'S8 Bilan TRIM2 '!F56 -> 4.440248
A19: Frais d'exploitation :
A20: Salaires | B20: 131170.8 | C20: =B20/$B$8 -> 0.058245479 | D20: 153183.29 | E20: =D20/$D$8 -> 0.057833517 | F20: =B20+D20 -> 284354.09 | G20: =F20/$F$8 -> 0.058022826 | N20: Liquidité | O20: ACT/PCT | P20: ACT - PCT
A21: Avantages sociaux | B21: 26649.97 | C21: =B21/$B$8 -> 0.011833733 | D21: 31122.25 | E21: =D21/$D$8 -> 0.011750036 | F21: =B21+D21 -> 57772.22 | G21: =F21/$F$8 -> 0.011788498 | N21: Trim 1 | O21: ='S8 Bilan TRIM2 '!C13/'S8 Bilan TRIM2 '!B45 -> 0.98605878 | P21: ='S8 Bilan TRIM2 '!C13-'S8 Bilan TRIM2 '!B45 -> -18270.89
A22: Vacances | B22: 5246.83 | C22: =B22/$B$8 -> 0.0023298183 | D22: 6127.33 | E22: =D22/$D$8 -> 0.0023133401 | F22: =B22+D22 -> 11374.16 | G22: =F22/$F$8 -> 0.0023209123 | N22: Trim 2 | O22: ='S8 Bilan TRIM2 '!F13/'S8 Bilan TRIM2 '!F45 -> 0.98376952 | P22: ='S8 Bilan TRIM2 '!F13-'S8 Bilan TRIM2 '!F45 -> -23177.46
A23: Téléphonie et système de communication | B23: 2250 | C23: =B23/$B$8 -> 0.00099909682 | D23: 2250 | E23: =D23/$D$8 -> 0.00084947525 | F23: =B23+D23 -> 4500 | G23: =F23/$F$8 -> 0.00091823092
A24: Publicité | B24: 276244 | C24: =B24/$B$8 -> 0.12266422 | D24: 9000 | E24: =D24/$D$8 -> 0.003397901 | F24: =B24+D24 -> 285244 | G24: =F24/$F$8 -> 0.058204414
A25: Frais de livraison | B25: 77108 | C25: =B25/$B$8 -> 0.03423927 | D25: 98620 | E25: =D25/$D$8 -> 0.037233444 | F25: =B25+D25 -> 175728 | G25: =F25/$F$8 -> 0.03585753
A26: Loyer | B26: 94243 | C26: =B26/$B$8 -> 0.041847947 | D26: 94243 | E26: =D26/$D$8 -> 0.035580932 | F26: =B26+D26 -> 188486 | G26: =F26/$F$8 -> 0.038460816
A27: Électricité | B27: 18500 | C27: =B27/$B$8 -> 0.008214796 | D27: 18500 | E27: =D27/$D$8 -> 0.0069845743 | F27: =B27+D27 -> 37000 | G27: =F27/$F$8 -> 0.0075498987
A28: Assurances | B28: 2479 | C28: =B28/$B$8 -> 0.0011007827 | D28: 2626 | E28: =D28/$D$8 -> 0.000991432 | F28: =B28+D28 -> 5105 | G28: =F28/$F$8 -> 0.001041682
A29: Honoraires professionnels | B29: 7882 | C29: =B29/$B$8 -> 0.0034999472 | D29: 9270 | E29: =D29/$D$8 -> 0.003499838 | F29: =B29+D29 -> 17152 | G29: =F29/$F$8 -> 0.0034998882
A30: Fournitures de bureau | B30: 1437 | C30: =B30/$B$8 -> 0.00063808983 | D30: 1739 | E30: =D30/$D$8 -> 0.00065654998 | F30: =B30+D30 -> 3176 | G30: =F30/$F$8 -> 0.00064806698
